Workbook

Sheet ToPowerBI
A1: Query | B1: ReportingStartDate | C1: ReportingEndDate | D1: Reporter | E1: UCITS_special mutual fund type | F1: Capital variability | G1: Fund category | H1: Fund Management Company | I1: AIF | J1: Status | K1: Lifetime (whole years) | L1: Row number
A2: PEF | B2: 39783 | C2: 43496 | D2: Placeringsfond SEB Money Manager | E2: UCITS | F2: Open-end | G2: Money market fund | H2: SEB | I2: Not found | J2: =IF(ISNUMBER(MATCH($D2,'Lopettaneet 2013->'!$D:$D,0)),INDEX('Lopettaneet 2013->'!$K:$K,MATCH($D2,'Lopettaneet 2013->'!$D:$D,0)),"Continues") -> Merged | K2: =IF($J2="Continues",DATEDIF($B2,TODAY(),"Y"),INDEX('Lopettaneet 2013->'!$L:$L,MATCH($D2,'Lopettaneet 2013->'!$D:$D,0))) -> 10 | L2: 1
A3: PEF | B3: 41974 | C3: 43100 | D3: Oy Wedeco Ab | E3: Non-UCITS | F3: Closed-end | G3: Buy-out fund | H3: Wedeco | I3: Not found | J3: =IF(ISNUMBER(MATCH($D3,'Lopettaneet 2013->'!$D:$D,0)),INDEX('Lopettaneet 2013->'!$K:$K,MATCH($D3,'Lopettaneet 2013->'!$D:$D,0)),"Continues") -> Closed | K3: =IF($J3="Continues",DATEDIF($B3,TODAY(),"Y"),INDEX('Lopettaneet 2013->'!$L:$L,MATCH($D3,'Lopettaneet 2013->'!$D:$D,0))) -> 3 | L3: 1
A4: MMF | B4: 39783 | C4: 43465 | D4: OP-Euro -sijoitusrahasto | E4: UCITS | F4: Open-end | G4: Bond fund | H4: Osuuspankki | I4: Retail | J4: =IF(ISNUMBER(MATCH($D4,'Lopettaneet 2013->'!$D:$D,0)),INDEX('Lopettaneet 2013->'!$K:$K,MATCH($D4,'Lopettaneet 2013->'!$D:$D,0)),"Continues") -> Closed | K4: =IF($J4="Continues",DATEDIF($B4,TODAY(),"Y"),INDEX('Lopettaneet 2013->'!$L:$L,MATCH($D4,'Lopettaneet 2013->'!$D:$D,0))) -> 10 | L4: 2
A5: PEF | B5: 41974 | C5: 42735 | D5: Finnventure Rahasto V Ky | E5: Non-UCITS | F5: Closed-end | G5: Buy-out fund | H5: Not found | I5: Not found | J5: =IF(ISNUMBER(MATCH($D5,'Lopettaneet 2013->'!$D:$D,0)),INDEX('Lopettaneet 2013->'!$K:$K,MATCH($D5,'Lopettaneet 2013->'!$D:$D,0)),"Continues") -> Closed | K5: =IF($J5="Continues",DATEDIF($B5,TODAY(),"Y"),INDEX('Lopettaneet 2013->'!$L:$L,MATCH($D5,'Lopettaneet 2013->'!$D:$D,0))) -> 2 | L5: 2
A6: MMF | B6: 41122 | C6: 43465 | D6: S-Pankki Lyhyt Korko Sijoitusrahasto | E6: UCITS | F6: Open-end | G6: Bond fund | H6: S-Pankki | I6: Retail | J6: =IF(ISNUMBER(MATCH($D6,'Lopettaneet 2013->'!$D:$D,0)),INDEX('Lopettaneet 2013->'!$K:$K,MATCH($D6,'Lopettaneet 2013->'!$D:$D,0)),"Continues") -> Closed | K6: =IF($J6="Continues",DATEDIF($B6,TODAY(),"Y"),INDEX('Lopettaneet 2013->'!$L:$L,MATCH($D6,'Lopettaneet 2013->'!$D:$D,0))) -> 6 | L6: 3
A7: PEF | B7: 41974 | C7: 42369 | D7: Maneq Fund 2002 Ky | E7: Non-UCITS | F7: Closed-end | G7: Buy-out fund | H7: Maneq | I7: Not found | J7: =IF(ISNUMBER(MATCH($D7,'Lopettaneet 2013->'!$D:$D,0)),INDEX('Lopettaneet 2013->'!$K:$K,MATCH($D7,'Lopettaneet 2013->'!$D:$D,0)),"Continues") -> Closed | K7: =IF($J7="Continues",DATEDIF($B7,TODAY(),"Y"),INDEX('Lopettaneet 2013->'!$L:$L,MATCH($D7,'Lopettaneet 2013->'!$D:$D,0))) -> 1 | L7: 3
A8: MMF | B8: 39783 | C8: 40908 | D8: Placeringsfonden Handelsbanken Euroränta | E8: UCITS | F8: Open-end | G8: Bond fund | H8: Handelsbanken | I8: Not found | J8: =IF(ISNUMBER(MATCH($D8,'Lopettaneet 2013->'!$D:$D,0)),INDEX('Lopettaneet 2013->'!$K:$K,MATCH($D8,'Lopettaneet 2013->'!$D:$D,0)),"Continues") -> Closed | K8: =IF($J8="Continues",DATEDIF($B8,TODAY(),"Y"),INDEX('Lopettaneet 2013->'!$L:$L,MATCH($D8,'Lopettaneet 2013->'!$D:$D,0))) -> 3 | L8: 4
A9: PEF | B9: 41974 | C9: 43738 | D9: Finnmezzanine Rahasto III A Ky | E9: Non-UCITS | F9: Closed-end | G9: Buy-out fund | H9: Finnmezzanine | I9: Not found | J9: =IF(ISNUMBER(MATCH($D9,'Lopettaneet 2013->'!$D:$D,0)),INDEX('Lopettaneet 2013->'!$K:$K,MATCH($D9,'Lopettaneet 2013->'!$D:$D,0)),"Continues") -> Closed | K9: =IF($J9="Continues",DATEDIF($B9,TODAY(),"Y"),INDEX('Lopettaneet 2013->'!$L:$L,MATCH($D9,'Lopettaneet 2013->'!$D:$D,0))) -> 4 | L9: 4
A10: MMF | B10: 40909 | C10: 41912 | D10: Placeringsfonden Handelsbanken Euroränta | E10: UCITS | F10: Open-end | G10: Bond fund | H10: Handelsbanken | I10: Not found | J10: =IF(ISNUMBER(MATCH($D10,'Lopettaneet 2013->'!$D:$D,0)),INDEX('Lopettaneet 2013->'!$K:$K,MATCH($D10,'Lopettaneet 2013->'!$D:$D,0)),"Continues") -> Closed | K10: =IF($J10="Continues",DATEDIF($B10,TODAY(),"Y"),INDEX('Lopettaneet 2013->'!$L:$L,MATCH($D10,'Lopettaneet 2013->'!$D:$D,0))) -> 3 | L10: 5
A11: PEF | B11: 41974 | C11: 42369 | D11: Finnmezzanine Rahasto III C Ky | E11: Non-UCITS | F11: Closed-end | G11: Buy-out fund | H11: Finnmezzanine | I11: Not found | J11: =IF(ISNUMBER(MATCH($D11,'Lopettaneet 2013->'!$D:$D,0)),INDEX('Lopettaneet 2013->'!$K:$K,MATCH($D11,'Lopettaneet 2013->'!$D:$D,0)),"Continues") -> Closed | K11: =IF($J11="Continues",DATEDIF($B11,TODAY(),"Y"),INDEX('Lopettaneet 2013->'!$L:$L,MATCH($D11,'Lopettaneet 2013->'!$D:$D,0))) -> 1 | L11: 5
A12: MMF | B12: 39783 | C12: 42277 | D12: Sijoitusrahasto Alfred Berg Korko | E12: UCITS | F12: Open-end | G12: Money market fund | H12: Evli | I12: Not found | J12: =IF(ISNUMBER(MATCH($D12,'Lopettaneet 2013->'!$D:$D,0)),INDEX('Lopettaneet 2013->'!$K:$K,MATCH($D12,'Lopettaneet 2013->'!$D:$D,0)),"Continues") -> Merged | K12: =IF($J12="Continues",DATEDIF($B12,TODAY(),"Y"),INDEX('Lopettaneet 2013->'!$L:$L,MATCH($D12,'Lopettaneet 2013->'!$D:$D,0))) -> 6 | L12: 6
A13: PEF | B13: 41974 | C13: 43738 | D13: Finnmezzanine Rahasto III B Ky | E13: Non-UCITS | F13: Closed-end | G13: Buy-out fund | H13: Finnmezzanine | I13: Not found | J13: =IF(ISNUMBER(MATCH($D13,'Lopettaneet 2013->'!$D:$D,0)),INDEX('Lopettaneet 2013->'!$K:$K,MATCH($D13,'Lopettaneet 2013->'!$D:$D,0)),"Continues") -> Closed | K13: =IF($J13="Continues",DATEDIF($B13,TODAY(),"Y"),INDEX('Lopettaneet 2013->'!$L:$L,MATCH($D13,'Lopettaneet 2013->'!$D:$D,0))) -> 4 | L13: 6
... A1356: PEF | B1356: 45352 | C1356: 55153 | D1356: NSI Feeder I Ky | E1356: Non-UCITS | F1356: Closed-end | G1356: Venture Capital fund | H1356: Nordic Science Investments Oy | I1356: Non-Retail | J1356: =IF(ISNUMBER(MATCH($D1356,'Lopettaneet 2013->'!$D:$D,0)),INDEX('Lopettaneet 2013->'!$K:$K,MATCH($D1356,'Lopettaneet 2013->'!$D:$D,0)),"Continues") -> Continues | K1356: =IF($J1356="Continues",DATEDIF($B1356,TODAY(),"Y"),INDEX('Lopettaneet 2013->'!$L:$L,MATCH($D1356,'Lopettaneet 2013->'!$D:$D,0))) -> 1 | L1356: 1091
A1357: PEF | B1357: 45444 | C1357: 55153 | D1357: OpenOcean Fund 2024 Ky | E1357: Non-UCITS | F1357: Closed-end | G1357: Venture Capital fund | H1357: OpenOcean Oy | I1357: Not found | J1357: Continues | K1357: =IF($J1357="Continues",DATEDIF($B1357,TODAY(),"Y"),INDEX('Lopettaneet 2013->'!$L:$L,MATCH($D1357,'Lopettaneet 2013->'!$D:$D,0))) -> 0 | L1357: 1092
A1358: PEF | B1358: 45444 | C1358: 55153 | D1358: Evolver Fund II Ky | E1358: Non-UCITS | F1358: Closed-end | G1358: Buy-out fund | H1358: Evolver Equity Ab | I1358: Not found | J1358: Continues | K1358: =IF($J1358="Continues",DATEDIF($B1358,TODAY(),"Y"),INDEX('Lopettaneet 2013->'!$L:$L,MATCH($D1358,'Lopettaneet 2013->'!$D:$D,0))) -> 0 | L1358: 1093
A1359: PEF | B1359: 45444 | C1359: 55153 | D1359: Eteläpohjalainen kasvurahasto Ky | E1359: Non-UCITS | F1359: Closed-end | G1359: Venture Capital fund | H1359: Redstone Nordics Oy | I1359: Not found | J1359: Continues | K1359: =IF($J1359="Continues",DATEDIF($B1359,TODAY(),"Y"),INDEX('Lopettaneet 2013->'!$L:$L,MATCH($D1359,'Lopettaneet 2013->'!$D:$D,0))) -> 0 | L1359: 1094
A1360: IVF | B1360: 45444 | C1360: 55153 | D1360: Erikoissijoitusrahasto CapMan Growth Equity Fund III Feeder | E1360: Non-UCITS | F1360: Open-end | G1360: Stock fund | H1360: CapMan | I1360: Not found | J1360: Continues | K1360: =IF($J1360="Continues",DATEDIF($B1360,TODAY(),"Y"),INDEX('Lopettaneet 2013->'!$L:$L,MATCH($D1360,'Lopettaneet 2013->'!$D:$D,0))) -> 0 | L1360: 1095
A1361: IVF | B1361: 45413 | C1361: 55153 | D1361: Placeringsfond Nordea Norge Pluss | E1361: UCITS | F1361: Open-end | G1361: Stock fund | H1361: Nordea | I1361: Not found | J1361: Continues | K1361: =IF($J1361="Continues",DATEDIF($B1361,TODAY(),"Y"),INDEX('Lopettaneet 2013->'!$L:$L,MATCH($D1361,'Lopettaneet 2013->'!$D:$D,0))) -> 1 | L1361: 1096
A1362: IVF | B1362: 45413 | C1362: 55153 | D1362: Placeringsfond Nordea Kort Obligasjon Pluss | E1362: UCITS | F1362: Open-end | G1362: Bond fund | H1362: Nordea | I1362: Not found | J1362: Continues | K1362: =IF($J1362="Continues",DATEDIF($B1362,TODAY(),"Y"),INDEX('Lopettaneet 2013->'!$L:$L,MATCH($D1362,'Lopettaneet 2013->'!$D:$D,0))) -> 1 | L1362: 1097
A1363: IVF | B1363: 45413 | C1363: 55153 | D1363: Placeringsfond Nordea FRN Kreditt | E1363: UCITS | F1363: Open-end | G1363: Bond fund | H1363: Nordea | I1363: Not found | J1363: Continues | K1363: =IF($J1363="Continues",DATEDIF($B1363,TODAY(),"Y"),INDEX('Lopettaneet 2013->'!$L:$L,MATCH($D1363,'Lopettaneet 2013->'!$D:$D,0))) -> 1 | L1363: 1098
A1364: IVF | B1364: 45413 | C1364: 55153 | D1364: Placeringsfond Nordea Obligasjon II | E1364: UCITS | F1364: Open-end | G1364: Bond fund | H1364: Nordea | I1364: Not found | J1364: Continues | K1364: =IF($J1364="Continues",DATEDIF($B1364,TODAY(),"Y"),INDEX('Lopettaneet 2013->'!$L:$L,MATCH($D1364,'Lopettaneet 2013->'!$D:$D,0))) -> 1 | L1364: 1099
A1365: IVF | B1365: 45413 | C1365: 55153 | D1365: Placeringsfond Nordea Obligasjon III | E1365: UCITS | F1365: Open-end | G1365: Bond fund | H1365: Nordea | I1365: Not found | J1365: Continues | K1365: =IF($J1365="Continues",DATEDIF($B1365,TODAY(),"Y"),INDEX('Lopettaneet 2013->'!$L:$L,MATCH($D1365,'Lopettaneet 2013->'!$D:$D,0))) -> 1 | L1365: 1100
A1366: IVF | B1366: 45444 | C1366: 55153 | D1366: OP-Alternative Credit II -erikoissijoitusrahasto | E1366: Non-UCITS | F1366: Open-end | G1366: Bond fund | H1366: Osuuspankki | I1366: Not found | J1366: Continues | K1366: =IF($J1366="Continues",DATEDIF($B1366,TODAY(),"Y"),INDEX('Lopettaneet 2013->'!$L:$L,MATCH($D1366,'Lopettaneet 2013->'!$D:$D,0))) -> 0 | L1366: 1101
A1367: PEF | B1367: 45444 | C1367: 55153 | D1367: Ethos Residential Opportunities I Ky | E1367: Non-UCITS | F1367: Closed-end | G1367: Real-estate fund | H1367: Ethos Capital Oy | I1367: Not found | J1367: Continues | K1367: =IF($J1367="Continues",DATEDIF($B1367,TODAY(),"Y"),INDEX('Lopettaneet 2013->'!$L:$L,MATCH($D1367,'Lopettaneet 2013->'!$D:$D,0))) -> 0 | L1367: 1102
A1368: IVF | B1368: 45413 | C1368: 55153 | D1368: S-Pankki European Private Credit Erikoissijoitusrahasto | E1368: Non-UCITS | F1368: Open-end | G1368: Other fund | H1368: S-Pankki | I1368: Not found | J1368: Continues | K1368: =IF($J1368="Continues",DATEDIF($B1368,TODAY(),"Y"),INDEX('Lopettaneet 2013->'!$L:$L,MATCH($D1368,'Lopettaneet 2013->'!$D:$D,0))) -> 1 | L1368: 1103
... A1371: IVF | B1371: 45413 | C1371: 55153 | D1371: OP-Kestävä Yrityslaina -sijoitusrahasto | E1371: UCITS | F1371: Open-end | G1371: Bond fund | H1371: Osuuspankki | I1371: Not found | J1371: Continues | K1371: =IF($J1371="Continues",DATEDIF($B1371,TODAY(),"Y"),INDEX('Lopettaneet 2013->'!$L:$L,MATCH($D1371,'Lopettaneet 2013->'!$D:$D,0))) -> 1 | L1371: 1106
A1372: IVF | B1372: 39783 | C1372: 45443 | D1372: Sijoitusrahasto LähiTapiola Kuluttaja ESG | E1372: UCITS | F1372: Open-end | G1372: Stock fund | H1372: Lähitapiola | I1372: =IFERROR(INDEX([2]Sheet1!$B:$B,MATCH($D1372,[2]Sheet1!$A:$A,0)),"Not found") -> Retail | J1372: Merged | K1372: =IF($I1372="Continues",DATEDIF($B1372,TODAY(),"Y"),DATEDIF($B1372,$C1372,"Y")) -> 15 | L1372: 1107
A1373: IVF | B1373: 39783 | C1373: 45443 | D1373: Sijoitusrahasto LähiTapiola Kuluttaja ESG | E1373: UCITS | F1373: Open-end | G1373: Stock fund | H1373: Lähitapiola | I1373: =IFERROR(INDEX([2]Sheet1!$B:$B,MATCH($D1373,[2]Sheet1!$A:$A,0)),"Not found") -> Retail | J1373: Merged | K1373: =IF($I1373="Continues",DATEDIF($B1373,TODAY(),"Y"),DATEDIF($B1373,$C1373,"Y")) -> 15 | L1373: 1108
A1374: IVF | B1374: 39783 | C1374: 45443 | D1374: Sijoitusrahasto LähiTapiola Kuluttaja ESG | E1374: UCITS | F1374: Open-end | G1374: Stock fund | H1374: Lähitapiola | I1374: =IFERROR(INDEX([2]Sheet1!$B:$B,MATCH($D1374,[2]Sheet1!$A:$A,0)),"Not found") -> Retail | J1374: Merged | K1374: =IF($I1374="Continues",DATEDIF($B1374,TODAY(),"Y"),DATEDIF($B1374,$C1374,"Y")) -> 15 | L1374: 1109
A1375: IVF | B1375: 39783 | C1375: 45473 | D1375: Sijoitusrahasto Nordea Aasialaiset Tähdet | E1375: UCITS | F1375: Open-end | G1375: Stock fund | H1375: Nordea | I1375: =IFERROR(INDEX([2]Sheet1!$B:$B,MATCH($D1375,[2]Sheet1!$A:$A,0)),"Not found") -> Retail | J1375: Closed | K1375: =IF($I1375="Continues",DATEDIF($B1375,TODAY(),"Y"),DATEDIF($B1375,$C1375,"Y")) -> 15 | L1375: 1110
A1376: IVF | B1376: 40940 | C1376: 45443 | D1376: Erikoissijoitusrahasto Aktia Rahastoyhtiö Oy Vakaa Korko | E1376: Non-UCITS | F1376: Open-end | G1376: Bond fund | H1376: Aktia Rahastoyhtiö Oy | I1376: =IFERROR(INDEX([2]Sheet1!$B:$B,MATCH($D1376,[2]Sheet1!$A:$A,0)),"Not found") -> Not found | J1376: Merged | K1376: =IF($I1376="Continues",DATEDIF($B1376,TODAY(),"Y"),DATEDIF($B1376,$C1376,"Y")) -> 12 | L1376: 1111
A1377: IVF | B1377: 40940 | C1377: 45443 | D1377: Erikoissijoitusrahasto Aktia Rahastoyhtiö Oy Vakaa Korko | E1377: Non-UCITS | F1377: Open-end | G1377: Bond fund | H1377: Aktia Rahastoyhtiö Oy | I1377: =IFERROR(INDEX([2]Sheet1!$B:$B,MATCH($D1377,[2]Sheet1!$A:$A,0)),"Not found") -> Not found | J1377: Merged | K1377: =IF($I1377="Continues",DATEDIF($B1377,TODAY(),"Y"),DATEDIF($B1377,$C1377,"Y")) -> 12 | L1377: 1112
A1378: IVF | B1378: 41214 | C1378: 45443 | D1378: Sijoitusrahasto Nordea Private Banking Kort Obligasjon Pluss | E1378: UCITS | F1378: Open-end | G1378: Bond fund | H1378: Nordea | I1378: =IFERROR(INDEX([2]Sheet1!$B:$B,MATCH($D1378,[2]Sheet1!$A:$A,0)),"Not found") -> Retail | J1378: Merged | K1378: =IF($I1378="Continues",DATEDIF($B1378,TODAY(),"Y"),DATEDIF($B1378,$C1378,"Y")) -> 11 | L1378: 1113
A1379: IVF | B1379: 41214 | C1379: 45443 | D1379: Sijoitusrahasto Nordea Private Banking Obligasjon | E1379: UCITS | F1379: Open-end | G1379: Bond fund | H1379: Nordea | I1379: =IFERROR(INDEX([2]Sheet1!$B:$B,MATCH($D1379,[2]Sheet1!$A:$A,0)),"Not found") -> Retail | J1379: Merged | K1379: =IF($I1379="Continues",DATEDIF($B1379,TODAY(),"Y"),DATEDIF($B1379,$C1379,"Y")) -> 11 | L1379: 1114
A1380: IVF | B1380: 41244 | C1380: 45412 | D1380: Sijoitusrahasto Evli Globaali Korko | E1380: UCITS | F1380: Open-end | G1380: Bond fund | H1380: Evli | I1380: =IFERROR(INDEX([2]Sheet1!$B:$B,MATCH($D1380,[2]Sheet1!$A:$A,0)),"Not found") -> Retail | J1380: Merged | K1380: =IF($I1380="Continues",DATEDIF($B1380,TODAY(),"Y"),DATEDIF($B1380,$C1380,"Y")) -> 11 | L1380: 1115
A1381: IVF | B1381: 42186 | C1381: 45443 | D1381: Specialplaceringsfonden Aktia Rahastoyhtiö Oy SLS | E1381: Non-UCITS | F1381: Open-end | G1381: Stock fund | H1381: Aktia Rahastoyhtiö Oy | I1381: =IFERROR(INDEX([2]Sheet1!$B:$B,MATCH($D1381,[2]Sheet1!$A:$A,0)),"Not found") -> Not found | J1381: Closed | K1381: =IF($I1381="Continues",DATEDIF($B1381,TODAY(),"Y"),DATEDIF($B1381,$C1381,"Y")) -> 8 | L1381: 1116
A1382: PEF | B1382: 42614 | C1382: 45473 | D1382: Epiqus Kotouttaminen I Ky | E1382: Non-UCITS | F1382: Closed-end | G1382: Other fund | H1382: Epiqus | I1382: =IFERROR(INDEX([2]Sheet1!$B:$B,MATCH($D1382,[2]Sheet1!$A:$A,0)),"Not found") -> Non-Retail | J1382: Closed | K1382: =IF($I1382="Continues",DATEDIF($B1382,TODAY(),"Y"),DATEDIF($B1382,$C1382,"Y")) -> 7 | L1382: 1117
A1383: PEF | B1383: 43800 | C1383: 45473 | D1383: Epiqus Kotouttaminen Holding I Ky | E1383: Non-UCITS | F1383: Closed-end | G1383: Other fund | H1383: Epiqus | I1383: =IFERROR(INDEX([2]Sheet1!$B:$B,MATCH($D1383,[2]Sheet1!$A:$A,0)),"Not found") -> Non-Retail | J1383: Closed | K1383: =IF($I1383="Continues",DATEDIF($B1383,TODAY(),"Y"),DATEDIF($B1383,$C1383,"Y")) -> 4 | L1383: 1118
A1384: IVF | B1384: 44378 | C1384: 45412 | D1384: GRIT SLS Erikoissijoitusrahasto | E1384: Non-UCITS | F1384: Open-end | G1384: Stock fund | H1384: GRIT Rahastoyhtiö Oy | I1384: =IFERROR(INDEX([2]Sheet1!$B:$B,MATCH($D1384,[2]Sheet1!$A:$A,0)),"Not found") -> Non-Retail | J1384: Closed | K1384: =IF($I1384="Continues",DATEDIF($B1384,TODAY(),"Y"),DATEDIF($B1384,$C1384,"Y")) -> 2 | L1384: 1119
A1385: IVF | B1385: 45505 | C1385: 55153 | D1385: Erikoissijoitusrahasto eQ PE SF V | E1385: Non-UCITS | F1385: Open-end | G1385: Other fund | H1385: eQ Rahastoyhtiö Oy | I1385: Not found | J1385: =IF(ISNUMBER(MATCH($D1385,'Lopettaneet 2013->'!$D:$D,0)),INDEX('Lopettaneet 2013->'!$K:$K,MATCH($D1385,'Lopettaneet 2013->'!$D:$D,0)),"Continues") -> Continues | K1385: =IF($J1385="Continues",DATEDIF($B1385,TODAY(),"Y"),INDEX('Lopettaneet 2013->'!$L:$L,MATCH($D1385,'Lopettaneet 2013->'!$D:$D,0))) -> 0 | L1385: 1120
A1386: PEF | B1386: 45536 | C1386: 55153 | D1386: Suomen Kuntakiinteistöt 1 Ky | E1386: Non-UCITS | F1386: Closed-end | G1386: Real-estate fund | H1386: YKS Management Oy | I1386: Not found | J1386: =IF(ISNUMBER(MATCH($D1386,'Lopettaneet 2013->'!$D:$D,0)),INDEX('Lopettaneet 2013->'!$K:$K,MATCH($D1386,'Lopettaneet 2013->'!$D:$D,0)),"Continues") -> Continues | K1386: =IF($J1386="Continues",DATEDIF($B1386,TODAY(),"Y"),INDEX('Lopettaneet 2013->'!$L:$L,MATCH($D1386,'Lopettaneet 2013->'!$D:$D,0))) -> 0 | L1386: 1121
A1387: PEF | B1387: 45536 | C1387: 55153 | D1387: Equilibrium Fund A Ky | E1387: Non-UCITS | F1387: Closed-end | G1387: Other fund | H1387: Equilibrium Funds Oy | I1387: Not found | J1387: =IF(ISNUMBER(MATCH($D1387,'Lopettaneet 2013->'!$D:$D,0)),INDEX('Lopettaneet 2013->'!$K:$K,MATCH($D1387,'Lopettaneet 2013->'!$D:$D,0)),"Continues") -> Continues | K1387: =IF($J1387="Continues",DATEDIF($B1387,TODAY(),"Y"),INDEX('Lopettaneet 2013->'!$L:$L,MATCH($D1387,'Lopettaneet 2013->'!$D:$D,0))) -> 0 | L1387: 1122
A1388: IVF | B1388: 45536 | C1388: 55153 | D1388: Placeringsfond Nordea Stabile Aksjer Global Valutasikret | E1388: UCITS | F1388: Open-end | G1388: Stock fund | H1388: Nordea | I1388: Not found | J1388: =IF(ISNUMBER(MATCH($D1388,'Lopettaneet 2013->'!$D:$D,0)),INDEX('Lopettaneet 2013->'!$K:$K,MATCH($D1388,'Lopettaneet 2013->'!$D:$D,0)),"Continues") -> Continues | K1388: =IF($J1388="Continues",DATEDIF($B1388,TODAY(),"Y"),INDEX('Lopettaneet 2013->'!$L:$L,MATCH($D1388,'Lopettaneet 2013->'!$D:$D,0))) -> 0 | L1388: 1123
A1389: IVF | B1389: 45536 | C1389: 55153 | D1389: Placeringsfond Nordea Stabile Aksjer Global | E1389: UCITS | F1389: Open-end | G1389: Stock fund | H1389: Nordea | I1389: Not found | J1389: =IF(ISNUMBER(MATCH($D1389,'Lopettaneet 2013->'!$D:$D,0)),INDEX('Lopettaneet 2013->'!$K:$K,MATCH($D1389,'Lopettaneet 2013->'!$D:$D,0)),"Continues") -> Continues | K1389: =IF($J1389="Continues",DATEDIF($B1389,TODAY(),"Y"),INDEX('Lopettaneet 2013->'!$L:$L,MATCH($D1389,'Lopettaneet 2013->'!$D:$D,0))) -> 0 | L1389: 1124
A1390: IVF | B1390: 45536 | C1390: 55153 | D1390: Placeringsfond Nordea Norge Verdi | E1390: UCITS | F1390: Open-end | G1390: Stock fund | H1390: Nordea | I1390: Not found | J1390: =IF(ISNUMBER(MATCH($D1390,'Lopettaneet 2013->'!$D:$D,0)),INDEX('Lopettaneet 2013->'!$K:$K,MATCH($D1390,'Lopettaneet 2013->'!$D:$D,0)),"Continues") -> Continues | K1390: =IF($J1390="Continues",DATEDIF($B1390,TODAY(),"Y"),INDEX('Lopettaneet 2013->'!$L:$L,MATCH($D1390,'Lopettaneet 2013->'!$D:$D,0))) -> 0 | L1390: 1125
A1391: IVF | B1391: 45536 | C1391: 55153 | D1391: Placeringsfond Nordea Kort Obligasjon | E1391: UCITS | F1391: Open-end | G1391: Bond fund | H1391: Nordea | I1391: Not found | J1391: =IF(ISNUMBER(MATCH($D1391,'Lopettaneet 2013->'!$D:$D,0)),INDEX('Lopettaneet 2013->'!$K:$K,MATCH($D1391,'Lopettaneet 2013->'!$D:$D,0)),"Continues") -> Continues | K1391: =IF($J1391="Continues",DATEDIF($B1391,TODAY(),"Y"),INDEX('Lopettaneet 2013->'!$L:$L,MATCH($D1391,'Lopettaneet 2013->'!$D:$D,0))) -> 0 | L1391: 1126
A1392: IVF | B1392: 45536 | C1392: 55153 | D1392: Placeringsfond Nordea Plan Konservativ | E1392: UCITS | F1392: Open-end | G1392: Combination fund | H1392: Nordea | I1392: Not found | J1392: =IF(ISNUMBER(MATCH($D1392,'Lopettaneet 2013->'!$D:$D,0)),INDEX('Lopettaneet 2013->'!$K:$K,MATCH($D1392,'Lopettaneet 2013->'!$D:$D,0)),"Continues") -> Continues | K1392: =IF($J1392="Continues",DATEDIF($B1392,TODAY(),"Y"),INDEX('Lopettaneet 2013->'!$L:$L,MATCH($D1392,'Lopettaneet 2013->'!$D:$D,0))) -> 0 | L1392: 1127
A1393: IVF | B1393: 45536 | C1393: 55153 | D1393: Placeringsfond Nordea Plan Moderat | E1393: UCITS | F1393: Open-end | G1393: Combination fund | H1393: Nordea | I1393: Not found | J1393: =IF(ISNUMBER(MATCH($D1393,'Lopettaneet 2013->'!$D:$D,0)),INDEX('Lopettaneet 2013->'!$K:$K,MATCH($D1393,'Lopettaneet 2013->'!$D:$D,0)),"Continues") -> Continues | K1393: =IF($J1393="Continues",DATEDIF($B1393,TODAY(),"Y"),INDEX('Lopettaneet 2013->'!$L:$L,MATCH($D1393,'Lopettaneet 2013->'!$D:$D,0))) -> 0 | L1393: 1128
A1394: IVF | B1394: 45536 | C1394: 55153 | D1394: Placeringsfond Nordea Plan Balansert | E1394: UCITS | F1394: Open-end | G1394: Combination fund | H1394: Nordea | I1394: Not found | J1394: =IF(ISNUMBER(MATCH($D1394,'Lopettaneet 2013->'!$D:$D,0)),INDEX('Lopettaneet 2013->'!$K:$K,MATCH($D1394,'Lopettaneet 2013->'!$D:$D,0)),"Continues") -> Continues | K1394: =IF($J1394="Continues",DATEDIF($B1394,TODAY(),"Y"),INDEX('Lopettaneet 2013->'!$L:$L,MATCH($D1394,'Lopettaneet 2013->'!$D:$D,0))) -> 0 | L1394: 1129
A1395: IVF | B1395: 45536 | C1395: 55153 | D1395: Placeringsfond Nordea Plan Vekstorientert | E1395: UCITS | F1395: Open-end | G1395: Combination fund | H1395: Nordea | I1395: Not found | J1395: =IF(ISNUMBER(MATCH($D1395,'Lopettaneet 2013->'!$D:$D,0)),INDEX('Lopettaneet 2013->'!$K:$K,MATCH($D1395,'Lopettaneet 2013->'!$D:$D,0)),"Continues") -> Continues | K1395: =IF($J1395="Continues",DATEDIF($B1395,TODAY(),"Y"),INDEX('Lopettaneet 2013->'!$L:$L,MATCH($D1395,'Lopettaneet 2013->'!$D:$D,0))) -> 0 | L1395: 1130
A1396: IVF | B1396: 45536 | C1396: 55153 | D1396: Placeringsfond Nordea Plan Offensiv | E1396: UCITS | F1396: Open-end | G1396: Combination fund | H1396: Nordea | I1396: Not found | J1396: =IF(ISNUMBER(MATCH($D1396,'Lopettaneet 2013->'!$D:$D,0)),INDEX('Lopettaneet 2013->'!$K:$K,MATCH($D1396,'Lopettaneet 2013->'!$D:$D,0)),"Continues") -> Continues | K1396: =IF($J1396="Continues",DATEDIF($B1396,TODAY(),"Y"),INDEX('Lopettaneet 2013->'!$L:$L,MATCH($D1396,'Lopettaneet 2013->'!$D:$D,0))) -> 0 | L1396: 1131
... A1411: IVF | B1411: 45536 | C1411: 55153 | D1411: Alexandria Pääomasijoitukset Erikoissijoitusrahasto | E1411: Non-UCITS | F1411: Open-end | G1411: Other fund | H1411: Alexandria | I1411: Not found | J1411: =IF(ISNUMBER(MATCH($D1411,'Lopettaneet 2013->'!$D:$D,0)),INDEX('Lopettaneet 2013->'!$K:$K,MATCH($D1411,'Lopettaneet 2013->'!$D:$D,0)),"Continues") -> Continues | K1411: =IF($J1411="Continues",DATEDIF($B1411,TODAY(),"Y"),INDEX('Lopettaneet 2013->'!$L:$L,MATCH($D1411,'Lopettaneet 2013->'!$D:$D,0))) -> 0 | L1411: 1146
A1412: IVF | B1412: 39783 | C1412: 45565 | D1412: OP-Reaalikorko -sijoitusrahasto | E1412: UCITS | F1412: Open-end | G1412: Bond fund | H1412: Osuuspankki | I1412: Retail | J1412: =IF(ISNUMBER(MATCH($D1412,'Lopettaneet 2013->'!$D:$D,0)),INDEX('Lopettaneet 2013->'!$K:$K,MATCH($D1412,'Lopettaneet 2013->'!$D:$D,0)),"Continues") -> Merged | K1412: =IF($H1412="Continues",DATEDIF($B1412,TODAY(),"Y"),INDEX('Lopettaneet 2013->'!$L:$L,MATCH($D1412,'Lopettaneet 2013->'!$D:$D,0))) -> 15 | L1412: 1147
A1413: IVF | B1413: 40179 | C1413: 45565 | D1413: OP-EMD Local Currency -erikoissijoitusrahasto | E1413: Non-UCITS | F1413: Open-end | G1413: Bond fund | H1413: Osuuspankki | I1413: Retail | J1413: =IF(ISNUMBER(MATCH($D1413,'Lopettaneet 2013->'!$D:$D,0)),INDEX('Lopettaneet 2013->'!$K:$K,MATCH($D1413,'Lopettaneet 2013->'!$D:$D,0)),"Continues") -> Merged | K1413: =IF($H1413="Continues",DATEDIF($B1413,TODAY(),"Y"),INDEX('Lopettaneet 2013->'!$L:$L,MATCH($D1413,'Lopettaneet 2013->'!$D:$D,0))) -> 14 | L1413: 1148
A1414: IVF | B1414: 41000 | C1414: 45565 | D1414: OP-EMD Hard Currency Corporate IG -sijoitusrahasto | E1414: UCITS | F1414: Open-end | G1414: Bond fund | H1414: Osuuspankki | I1414: Retail | J1414: =IF(ISNUMBER(MATCH($D1414,'Lopettaneet 2013->'!$D:$D,0)),INDEX('Lopettaneet 2013->'!$K:$K,MATCH($D1414,'Lopettaneet 2013->'!$D:$D,0)),"Continues") -> Merged | K1414: =IF($H1414="Continues",DATEDIF($B1414,TODAY(),"Y"),INDEX('Lopettaneet 2013->'!$L:$L,MATCH($D1414,'Lopettaneet 2013->'!$D:$D,0))) -> 12 | L1414: 1149
A1415: IVF | B1415: 41214 | C1415: 45565 | D1415: Sijoitusrahasto Nordea Private Banking FRN | E1415: UCITS | F1415: Open-end | G1415: Bond fund | H1415: Nordea | I1415: Retail | J1415: =IF(ISNUMBER(MATCH($D1415,'Lopettaneet 2013->'!$D:$D,0)),INDEX('Lopettaneet 2013->'!$K:$K,MATCH($D1415,'Lopettaneet 2013->'!$D:$D,0)),"Continues") -> Merged | K1415: =IF($H1415="Continues",DATEDIF($B1415,TODAY(),"Y"),INDEX('Lopettaneet 2013->'!$L:$L,MATCH($D1415,'Lopettaneet 2013->'!$D:$D,0))) -> 11 | L1415: 1150
A1416: IVF | B1416: 41365 | C1416: 45535 | D1416: Sijoitusrahasto FOURTON Tempo | E1416: UCITS | F1416: Open-end | G1416: Stock fund | H1416: Fourton | I1416: Retail | J1416: =IF(ISNUMBER(MATCH($D1416,'Lopettaneet 2013->'!$D:$D,0)),INDEX('Lopettaneet 2013->'!$K:$K,MATCH($D1416,'Lopettaneet 2013->'!$D:$D,0)),"Continues") -> Merged | K1416: =IF($H1416="Continues",DATEDIF($B1416,TODAY(),"Y"),INDEX('Lopettaneet 2013->'!$L:$L,MATCH($D1416,'Lopettaneet 2013->'!$D:$D,0))) -> 11 | L1416: 1151
A1417: IVF | B1417: 42705 | C1417: 45565 | D1417: OP-Japanin Tähdet –sijoitusrahasto | E1417: UCITS | F1417: Open-end | G1417: Stock fund | H1417: Osuuspankki | I1417: Retail | J1417: =IF(ISNUMBER(MATCH($D1417,'Lopettaneet 2013->'!$D:$D,0)),INDEX('Lopettaneet 2013->'!$K:$K,MATCH($D1417,'Lopettaneet 2013->'!$D:$D,0)),"Continues") -> Merged | K1417: =IF($H1417="Continues",DATEDIF($B1417,TODAY(),"Y"),INDEX('Lopettaneet 2013->'!$L:$L,MATCH($D1417,'Lopettaneet 2013->'!$D:$D,0))) -> 7 | L1417: 1152
A1418: IVF | B1418: 43101 | C1418: 45565 | D1418: OP-High Yield Amerikka -sijoitusrahasto | E1418: UCITS | F1418: Open-end | G1418: Bond fund | H1418: Osuuspankki | I1418: Retail | J1418: =IF(ISNUMBER(MATCH($D1418,'Lopettaneet 2013->'!$D:$D,0)),INDEX('Lopettaneet 2013->'!$K:$K,MATCH($D1418,'Lopettaneet 2013->'!$D:$D,0)),"Continues") -> Merged | K1418: =IF($H1418="Continues",DATEDIF($B1418,TODAY(),"Y"),INDEX('Lopettaneet 2013->'!$L:$L,MATCH($D1418,'Lopettaneet 2013->'!$D:$D,0))) -> 6 | L1418: 1153
A1419: PEF | B1419: 45627 | C1419: 55153 | D1419: BOA Kyy Ky | E1419: Non-UCITS | F1419: Closed-end | G1419: Buy-out fund | H1419: BOA Capital Oy | I1419: Not found | J1419: =IF(ISNUMBER(MATCH($D1419,'Lopettaneet 2013->'!$D:$D,0)),INDEX('Lopettaneet 2013->'!$K:$K,MATCH($D1419,'Lopettaneet 2013->'!$D:$D,0)),"Continues") -> Continues | K1419: =IF($J1419="Continues",DATEDIF($B1419,TODAY(),"Y"),INDEX('Lopettaneet 2013->'!$L:$L,MATCH($D1419,'Lopettaneet 2013->'!$D:$D,0))) -> 0 | L1419: 1154
A1420: PEF | B1420: 45627 | C1420: 55153 | D1420: Evli Private Capital Fund I Ky | E1420: Non-UCITS | F1420: Closed-end | G1420: Buy-out fund | H1420: Evli | I1420: Not found | J1420: =IF(ISNUMBER(MATCH($D1420,'Lopettaneet 2013->'!$D:$D,0)),INDEX('Lopettaneet 2013->'!$K:$K,MATCH($D1420,'Lopettaneet 2013->'!$D:$D,0)),"Continues") -> Continues | K1420: =IF($J1420="Continues",DATEDIF($B1420,TODAY(),"Y"),INDEX('Lopettaneet 2013->'!$L:$L,MATCH($D1420,'Lopettaneet 2013->'!$D:$D,0))) -> 0 | L1420: 1155
A1421: PEF | B1421: 45627 | C1421: 55153 | D1421: Evli Private Capital I Feeder A Ky | E1421: Non-UCITS | F1421: Closed-end | G1421: Buy-out fund | H1421: Evli | I1421: Not found | J1421: =IF(ISNUMBER(MATCH($D1421,'Lopettaneet 2013->'!$D:$D,0)),INDEX('Lopettaneet 2013->'!$K:$K,MATCH($D1421,'Lopettaneet 2013->'!$D:$D,0)),"Continues") -> Continues | K1421: =IF($J1421="Continues",DATEDIF($B1421,TODAY(),"Y"),INDEX('Lopettaneet 2013->'!$L:$L,MATCH($D1421,'Lopettaneet 2013->'!$D:$D,0))) -> 0 | L1421: 1156
A1422: PEF | B1422: 45627 | C1422: 55153 | D1422: Fundco PE Strategies I Ky | E1422: Non-UCITS | F1422: Closed-end | G1422: Buy-out fund | H1422: fundco oy | I1422: Not found | J1422: =IF(ISNUMBER(MATCH($D1422,'Lopettaneet 2013->'!$D:$D,0)),INDEX('Lopettaneet 2013->'!$K:$K,MATCH($D1422,'Lopettaneet 2013->'!$D:$D,0)),"Continues") -> Continues | K1422: =IF($J1422="Continues",DATEDIF($B1422,TODAY(),"Y"),INDEX('Lopettaneet 2013->'!$L:$L,MATCH($D1422,'Lopettaneet 2013->'!$D:$D,0))) -> 0 | L1422: 1157
A1423: PEF | B1423: 45627 | C1423: 55153 | D1423: Fundco PE I Ky | E1423: Non-UCITS | F1423: Closed-end | G1423: Buy-out fund | H1423: fundco oy | I1423: Not found | J1423: =IF(ISNUMBER(MATCH($D1423,'Lopettaneet 2013->'!$D:$D,0)),INDEX('Lopettaneet 2013->'!$K:$K,MATCH($D1423,'Lopettaneet 2013->'!$D:$D,0)),"Continues") -> Continues | K1423: =IF($J1423="Continues",DATEDIF($B1423,TODAY(),"Y"),INDEX('Lopettaneet 2013->'!$L:$L,MATCH($D1423,'Lopettaneet 2013->'!$D:$D,0))) -> 0 | L1423: 1158
A1424: PEF | B1424: 45627 | C1424: 55153 | D1424: Aktia Rahastoyhtiö Oy Velkarahastot II Ky | E1424: Non-UCITS | F1424: Closed-end | G1424: Bond fund | H1424: Aktia Rahastoyhtiö Oy | I1424: Not found | J1424: =IF(ISNUMBER(MATCH($D1424,'Lopettaneet 2013->'!$D:$D,0)),INDEX('Lopettaneet 2013->'!$K:$K,MATCH($D1424,'Lopettaneet 2013->'!$D:$D,0)),"Continues") -> Continues | K1424: =IF($J1424="Continues",DATEDIF($B1424,TODAY(),"Y"),INDEX('Lopettaneet 2013->'!$L:$L,MATCH($D1424,'Lopettaneet 2013->'!$D:$D,0))) -> 0 | L1424: 1159
A1425: PEF | B1425: 45627 | C1425: 55153 | D1425: Aktia Rahastoyhtiö Oy Velkarahastot II Rahoittajat Ky | E1425: Non-UCITS | F1425: Closed-end | G1425: Bond fund | H1425: Aktia Rahastoyhtiö Oy | I1425: Not found | J1425: =IF(ISNUMBER(MATCH($D1425,'Lopettaneet 2013->'!$D:$D,0)),INDEX('Lopettaneet 2013->'!$K:$K,MATCH($D1425,'Lopettaneet 2013->'!$D:$D,0)),"Continues") -> Continues | K1425: =IF($J1425="Continues",DATEDIF($B1425,TODAY(),"Y"),INDEX('Lopettaneet 2013->'!$L:$L,MATCH($D1425,'Lopettaneet 2013->'!$D:$D,0))) -> 0 | L1425: 1160
A1426: PEF | B1426: 45627 | C1426: 55153 | D1426: Aktia Rahastoyhtiö Oy Velkarahastot II Sijoittajat 500 Ky | E1426: Non-UCITS | F1426: Closed-end | G1426: Bond fund | H1426: Aktia Rahastoyhtiö Oy | I1426: Not found | J1426: =IF(ISNUMBER(MATCH($D1426,'Lopettaneet 2013->'!$D:$D,0)),INDEX('Lopettaneet 2013->'!$K:$K,MATCH($D1426,'Lopettaneet 2013->'!$D:$D,0)),"Continues") -> Continues | K1426: =IF($J1426="Continues",DATEDIF($B1426,TODAY(),"Y"),INDEX('Lopettaneet 2013->'!$L:$L,MATCH($D1426,'Lopettaneet 2013->'!$D:$D,0))) -> 0 | L1426: 1161
A1427: PEF | B1427: 45627 | C1427: 55153 | D1427: Aktia Rahastoyhtiö Oy Velkarahastot II Sijoittajat 100 Ky | E1427: Non-UCITS | F1427: Closed-end | G1427: Bond fund | H1427: Aktia Rahastoyhtiö Oy | I1427: Not found | J1427: =IF(ISNUMBER(MATCH($D1427,'Lopettaneet 2013->'!$D:$D,0)),INDEX('Lopettaneet 2013->'!$K:$K,MATCH($D1427,'Lopettaneet 2013->'!$D:$D,0)),"Continues") -> Continues | K1427: =IF($J1427="Continues",DATEDIF($B1427,TODAY(),"Y"),INDEX('Lopettaneet 2013->'!$L:$L,MATCH($D1427,'Lopettaneet 2013->'!$D:$D,0))) -> 0 | L1427: 1162
A1428: PEF | B1428: 45627 | C1428: 55153 | D1428: Aktia Rahastoyhtiö Oy Velkarahastot II Omistajat Ky | E1428: Non-UCITS | F1428: Closed-end | G1428: Bond fund | H1428: Aktia Rahastoyhtiö Oy | I1428: Not found | J1428: =IF(ISNUMBER(MATCH($D1428,'Lopettaneet 2013->'!$D:$D,0)),INDEX('Lopettaneet 2013->'!$K:$K,MATCH($D1428,'Lopettaneet 2013->'!$D:$D,0)),"Continues") -> Continues | K1428: =IF($J1428="Continues",DATEDIF($B1428,TODAY(),"Y"),INDEX('Lopettaneet 2013->'!$L:$L,MATCH($D1428,'Lopettaneet 2013->'!$D:$D,0))) -> 0 | L1428: 1163
A1429: PEF | B1429: 45627 | C1429: 55153 | D1429: eQ PE XVI North Ky | E1429: Non-UCITS | F1429: Closed-end | G1429: Other fund | H1429: eQ Rahastoyhtiö Oy | I1429: Not found | J1429: =IF(ISNUMBER(MATCH($D1429,'Lopettaneet 2013->'!$D:$D,0)),INDEX('Lopettaneet 2013->'!$K:$K,MATCH($D1429,'Lopettaneet 2013->'!$D:$D,0)),"Continues") -> Continues | K1429: =IF($J1429="Continues",DATEDIF($B1429,TODAY(),"Y"),INDEX('Lopettaneet 2013->'!$L:$L,MATCH($D1429,'Lopettaneet 2013->'!$D:$D,0))) -> 0 | L1429: 1164
A1430: IVF | B1430: 45627 | C1430: 55153 | D1430: Erikoissijoitusrahasto eQ PE XVI North Feeder | E1430: Non-UCITS | F1430: Open-end | G1430: Other fund | H1430: eQ Rahastoyhtiö Oy | I1430: Not found | J1430: =IF(ISNUMBER(MATCH($D1430,'Lopettaneet 2013->'!$D:$D,0)),INDEX('Lopettaneet 2013->'!$K:$K,MATCH($D1430,'Lopettaneet 2013->'!$D:$D,0)),"Continues") -> Continues | K1430: =IF($J1430="Continues",DATEDIF($B1430,TODAY(),"Y"),INDEX('Lopettaneet 2013->'!$L:$L,MATCH($D1430,'Lopettaneet 2013->'!$D:$D,0))) -> 0 | L1430: 1165
... A1434: IVF | B1434: 45627 | C1434: 55153 | D1434: Erikoissijoitusrahasto CW Investment Partners Fund IV | E1434: Non-UCITS | F1434: Closed-end | G1434: Buy-out fund | H1434: CW | I1434: Not found | J1434: =IF(ISNUMBER(MATCH($D1434,'Lopettaneet 2013->'!$D:$D,0)),INDEX('Lopettaneet 2013->'!$K:$K,MATCH($D1434,'Lopettaneet 2013->'!$D:$D,0)),"Continues") -> Continues | K1434: =IF($J1434="Continues",DATEDIF($B1434,TODAY(),"Y"),INDEX('Lopettaneet 2013->'!$L:$L,MATCH($D1434,'Lopettaneet 2013->'!$D:$D,0))) -> 0 | L1434: 1169
A1435: IVF | B1435: 39783 | C1435: 45626 | D1435: Sijoitusrahasto Danske Invest India | E1435: UCITS | F1435: Open-end | G1435: Stock fund | H1435: Danske Invest | I1435: =IFERROR(INDEX([2]Sheet1!$B:$B,MATCH($D1435,[2]Sheet1!$A:$A,0)),"Not found") -> Retail | J1435: Merged | K1435: =IF($J1435="Continues",DATEDIF($B1435,TODAY(),"Y"),INDEX('Lopettaneet 2013->'!$L:$L,MATCH($D1435,'Lopettaneet 2013->'!$D:$D,0))) -> 15 | L1435: 1170
A1436: IVF | B1436: 39783 | C1436: 45626 | D1436: Sijoitusrahasto Danske Invest Itä-Eurooppa Konvergenssi | E1436: UCITS | F1436: Open-end | G1436: Stock fund | H1436: Danske Invest | I1436: =IFERROR(INDEX([2]Sheet1!$B:$B,MATCH($D1436,[2]Sheet1!$A:$A,0)),"Not found") -> Retail | J1436: Merged | K1436: =IF($J1436="Continues",DATEDIF($B1436,TODAY(),"Y"),INDEX('Lopettaneet 2013->'!$L:$L,MATCH($D1436,'Lopettaneet 2013->'!$D:$D,0))) -> 15 | L1436: 1171
A1437: PEF | B1437: 45717 | C1437: 55153 | D1437: Wave III KY | E1437: Non-UCITS | F1437: Closed-end | G1437: Venture Capital fund | H1437: Wave Ventures Oy | I1437: Not found | J1437: Continues | K1437: =IF($J1437="Continues",DATEDIF($B1437,TODAY(),"Y"),INDEX('Lopettaneet 2013->'!$L:$L,MATCH($D1437,'Lopettaneet 2013->'!$D:$D,0))) -> 0 | L1437: 1172
A1438: PEF | B1438: 45717 | C1438: 55153 | D1438: UB Asuntorahasto I Ky | E1438: Non-UCITS | F1438: Closed-end | G1438: Real-estate fund | H1438: UB | I1438: Not found | J1438: Continues | K1438: =IF($J1438="Continues",DATEDIF($B1438,TODAY(),"Y"),INDEX('Lopettaneet 2013->'!$L:$L,MATCH($D1438,'Lopettaneet 2013->'!$D:$D,0))) -> 0 | L1438: 1173
A1439: PEF | B1439: 45717 | C1439: 55153 | D1439: UB Asuntorahasto I Syöttörahasto Ky | E1439: Non-UCITS | F1439: Closed-end | G1439: Real-estate fund | H1439: UB | I1439: Not found | J1439: Continues | K1439: =IF($J1439="Continues",DATEDIF($B1439,TODAY(),"Y"),INDEX('Lopettaneet 2013->'!$L:$L,MATCH($D1439,'Lopettaneet 2013->'!$D:$D,0))) -> 0 | L1439: 1174
A1440: IVF | B1440: 45658 | C1440: 55153 | D1440: Erikoissijoitusrahasto eQ Eurooppa Indeksi ESG | E1440: Non-UCITS | F1440: Open-end | G1440: Stock fund | H1440: eQ Rahastoyhtiö Oy | I1440: Not found | J1440: Continues | K1440: =IF($J1440="Continues",DATEDIF($B1440,TODAY(),"Y"),INDEX('Lopettaneet 2013->'!$L:$L,MATCH($D1440,'Lopettaneet 2013->'!$D:$D,0))) -> 0 | L1440: 1175
A1441: IVF | B1441: 45658 | C1441: 55153 | D1441: Erikoissijoitusrahasto eQ Maailma Indeksi ESG | E1441: Non-UCITS | F1441: Open-end | G1441: Stock fund | H1441: eQ Rahastoyhtiö Oy | I1441: Not found | J1441: Continues | K1441: =IF($J1441="Continues",DATEDIF($B1441,TODAY(),"Y"),INDEX('Lopettaneet 2013->'!$L:$L,MATCH($D1441,'Lopettaneet 2013->'!$D:$D,0))) -> 0 | L1441: 1176
A1442: IVF | B1442: 45717 | C1442: 55153 | D1442: Sijoitusrahasto Nordea USA Passiivinen | E1442: UCITS | F1442: Open-end | G1442: Stock fund | H1442: Nordea | I1442: Not found | J1442: Continues | K1442: =IF($J1442="Continues",DATEDIF($B1442,TODAY(),"Y"),INDEX('Lopettaneet 2013->'!$L:$L,MATCH($D1442,'Lopettaneet 2013->'!$D:$D,0))) -> 0 | L1442: 1177
A1443: PEF | B1443: 45717 | C1443: 55153 | D1443: Icebreaker Fund III Ky | E1443: Non-UCITS | F1443: Closed-end | G1443: Venture Capital fund | H1443: Icebreaker | I1443: Not found | J1443: Continues | K1443: =IF($J1443="Continues",DATEDIF($B1443,TODAY(),"Y"),INDEX('Lopettaneet 2013->'!$L:$L,MATCH($D1443,'Lopettaneet 2013->'!$D:$D,0))) -> 0 | L1443: 1178
A1444: PEF | B1444: 45717 | C1444: 55153 | D1444: Terwarahasto 2 Ky | E1444: Non-UCITS | F1444: Closed-end | G1444: Real-estate fund | H1444: Terwa Management Oy | I1444: Not found | J1444: Continues | K1444: =IF($J1444="Continues",DATEDIF($B1444,TODAY(),"Y"),INDEX('Lopettaneet 2013->'!$L:$L,MATCH($D1444,'Lopettaneet 2013->'!$D:$D,0))) -> 0 | L1444: 1179
A1445: IVF | B1445: 45717 | C1445: 55153 | D1445: Sijoitusrahasto Aktia European Smaller Companies | E1445: UCITS | F1445: Open-end | G1445: Stock fund | H1445: Aktia Rahastoyhtiö Oy | I1445: Not found | J1445: Continues | K1445: =IF($J1445="Continues",DATEDIF($B1445,TODAY(),"Y"),INDEX('Lopettaneet 2013->'!$L:$L,MATCH($D1445,'Lopettaneet 2013->'!$D:$D,0))) -> 0 | L1445: 1180
A1446: IVF | B1446: 45689 | C1446: 55153 | D1446: Erikoissijoitusrahasto eQ Asunnot III | E1446: Non-UCITS | F1446: Closed-end | G1446: Real-estate fund | H1446: eQ Rahastoyhtiö Oy | I1446: Not found | J1446: Continues | K1446: =IF($J1446="Continues",DATEDIF($B1446,TODAY(),"Y"),INDEX('Lopettaneet 2013->'!$L:$L,MATCH($D1446,'Lopettaneet 2013->'!$D:$D,0))) -> 0 | L1446: 1181

Sheet Aloittaneet 2013->
A1: Kysely | B1: RaportoinninAloitusPvm | C1: RaportoinninLopetusPvm | D1: Raportoija | E1: RaportoijanRahastotunnus | F1: Y_tunnus | G1: UCITS_erikoissijoitusrahastotyyppi | H1: Pääomanvaihtelevuus | I1: Rahastotyyppi | J1: Status | K1: Elinaika (y) | L1: Hallinnointiyhtiö | M1: AIF | N1: AIF - retail | O1: AIF - non-retail
A2: PEF | B2: 41974 | C2: 43100 | D2: Oy Wedeco Ab | E2: 15318791#001 | F2: 6798092 | G2: Non-UCITS | H2: Closed-end | I2: Buyout-rahasto | J2: =IF(ISNUMBER(MATCH($D2,'Lopettaneet 2013->'!$D:$D,0)),INDEX('Lopettaneet 2013->'!$K:$K,MATCH($D2,'Lopettaneet 2013->'!$D:$D,0)),"Continues") -> Closed | K2: =IF($J2="Continues",DATEDIF($B2,TODAY(),"Y"),INDEX('Lopettaneet 2013->'!$L:$L,MATCH($D2,'Lopettaneet 2013->'!$D:$D,0))) -> 3 | L2: =IFERROR(INDEX('[1]30.06.2024'!$H:$H,MATCH($E2,'[1]30.06.2024'!$B:$B,0)),"Not found") -> Not found | M2: =IFERROR(INDEX([2]Sheet1!$B:$B,MATCH($D2,[2]Sheet1!$A:$A,0)),"Not found") -> Not found | N2: =IF($M2="Retail",1,0) -> 0 | O2: =IF($M2="Non-Retail",1,0) -> 0
A3: PEF | B3: 41974 | C3: 42735 | D3: Finnventure Rahasto V Ky | E3: 07490276#006 | F3: 15657523 | G3: Non-UCITS | H3: Closed-end | I3: Buyout-rahasto | J3: =IF(ISNUMBER(MATCH($D3,'Lopettaneet 2013->'!$D:$D,0)),INDEX('Lopettaneet 2013->'!$K:$K,MATCH($D3,'Lopettaneet 2013->'!$D:$D,0)),"Continues") -> Closed | K3: =IF($J3="Continues",DATEDIF($B3,TODAY(),"Y"),INDEX('Lopettaneet 2013->'!$L:$L,MATCH($D3,'Lopettaneet 2013->'!$D:$D,0))) -> 2 | L3: =IFERROR(INDEX('[1]30.06.2024'!$H:$H,MATCH($E3,'[1]30.06.2024'!$B:$B,0)),"Not found") -> Not found | M3: =IFERROR(INDEX([2]Sheet1!$B:$B,MATCH($D3,[2]Sheet1!$A:$A,0)),"Not found") -> Not found | N3: =IF($M3="Retail",1,0) -> 0 | O3: =IF($M3="Non-Retail",1,0) -> 0
A4: PEF | B4: 41974 | C4: 42369 | D4: Maneq Fund 2002 Ky | E4: 19011500#009 | F4: 17285698 | G4: Non-UCITS | H4: Closed-end | I4: Buyout-rahasto | J4: =IF(ISNUMBER(MATCH($D4,'Lopettaneet 2013->'!$D:$D,0)),INDEX('Lopettaneet 2013->'!$K:$K,MATCH($D4,'Lopettaneet 2013->'!$D:$D,0)),"Continues") -> Closed | K4: =IF($J4="Continues",DATEDIF($B4,TODAY(),"Y"),INDEX('Lopettaneet 2013->'!$L:$L,MATCH($D4,'Lopettaneet 2013->'!$D:$D,0))) -> 1 | L4: =IFERROR(INDEX('[1]30.06.2024'!$H:$H,MATCH($E4,'[1]30.06.2024'!$B:$B,0)),"Not found") -> Not found | M4: =IFERROR(INDEX([2]Sheet1!$B:$B,MATCH($D4,[2]Sheet1!$A:$A,0)),"Not found") -> Not found | N4: =IF($M4="Retail",1,0) -> 0 | O4: =IF($M4="Non-Retail",1,0) -> 0
A5: PEF | B5: 41974 | C5: 43738 | D5: Finnmezzanine Rahasto III A Ky | E5: 07490276#008 | F5: 16020110 | G5: Non-UCITS | H5: Closed-end | I5: Buyout-rahasto | J5: =IF(ISNUMBER(MATCH($D5,'Lopettaneet 2013->'!$D:$D,0)),INDEX('Lopettaneet 2013->'!$K:$K,MATCH($D5,'Lopettaneet 2013->'!$D:$D,0)),"Continues") -> Closed | K5: =IF($J5="Continues",DATEDIF($B5,TODAY(),"Y"),INDEX('Lopettaneet 2013->'!$L:$L,MATCH($D5,'Lopettaneet 2013->'!$D:$D,0))) -> 4 | L5: =IFERROR(INDEX('[1]30.06.2024'!$H:$H,MATCH($E5,'[1]30.06.2024'!$B:$B,0)),"Not found") -> Not found | M5: =IFERROR(INDEX([2]Sheet1!$B:$B,MATCH($D5,[2]Sheet1!$A:$A,0)),"Not found") -> Not found | N5: =IF($M5="Retail",1,0) -> 0 | O5: =IF($M5="Non-Retail",1,0) -> 0
A6: PEF | B6: 41974 | C6: 42369 | D6: Finnmezzanine Rahasto III C Ky | E6: 07490276#011 | F6: 16069002 | G6: Non-UCITS | H6: Closed-end | I6: Buyout-rahasto | J6: =IF(ISNUMBER(MATCH($D6,'Lopettaneet 2013->'!$D:$D,0)),INDEX('Lopettaneet 2013->'!$K:$K,MATCH($D6,'Lopettaneet 2013->'!$D:$D,0)),"Continues") -> Closed | K6: =IF($J6="Continues",DATEDIF($B6,TODAY(),"Y"),INDEX('Lopettaneet 2013->'!$L:$L,MATCH($D6,'Lopettaneet 2013->'!$D:$D,0))) -> 1 | L6: =IFERROR(INDEX('[1]30.06.2024'!$H:$H,MATCH($E6,'[1]30.06.2024'!$B:$B,0)),"Not found") -> Not found | M6: =IFERROR(INDEX([2]Sheet1!$B:$B,MATCH($D6,[2]Sheet1!$A:$A,0)),"Not found") -> Not found | N6: =IF($M6="Retail",1,0) -> 0 | O6: =IF($M6="Non-Retail",1,0) -> 0
A7: PEF | B7: 41974 | C7: 43738 | D7: Finnmezzanine Rahasto III B Ky | E7: 07490276#009 | F7: 16020137 | G7: Non-UCITS | H7: Closed-end | I7: Buyout-rahasto | J7: =IF(ISNUMBER(MATCH($D7,'Lopettaneet 2013->'!$D:$D,0)),INDEX('Lopettaneet 2013->'!$K:$K,MATCH($D7,'Lopettaneet 2013->'!$D:$D,0)),"Continues") -> Closed | K7: =IF($J7="Continues",DATEDIF($B7,TODAY(),"Y"),INDEX('Lopettaneet 2013->'!$L:$L,MATCH($D7,'Lopettaneet 2013->'!$D:$D,0))) -> 4 | L7: =IFERROR(INDEX('[1]30.06.2024'!$H:$H,MATCH($E7,'[1]30.06.2024'!$B:$B,0)),"Not found") -> Not found | M7: =IFERROR(INDEX([2]Sheet1!$B:$B,MATCH($D7,[2]Sheet1!$A:$A,0)),"Not found") -> Not found | N7: =IF($M7="Retail",1,0) -> 0 | O7: =IF($M7="Non-Retail",1,0) -> 0
A8: PEF | B8: 41974 | C8: 44196 | D8: CapMan Real Estate I Ky | E8: 07491762#001 | F8: 19720366 | G8: Non-UCITS | H8: Closed-end | I8: Kiinteistörahasto | J8: =IF(ISNUMBER(MATCH($D8,'Lopettaneet 2013->'!$D:$D,0)),INDEX('Lopettaneet 2013->'!$K:$K,MATCH($D8,'Lopettaneet 2013->'!$D:$D,0)),"Continues") -> Closed | K8: =IF($J8="Continues",DATEDIF($B8,TODAY(),"Y"),INDEX('Lopettaneet 2013->'!$L:$L,MATCH($D8,'Lopettaneet 2013->'!$D:$D,0))) -> 6 | L8: =IFERROR(INDEX('[1]30.06.2024'!$H:$H,MATCH($E8,'[1]30.06.2024'!$B:$B,0)),"Not found") -> Not found | M8: =IFERROR(INDEX([2]Sheet1!$B:$B,MATCH($D8,[2]Sheet1!$A:$A,0)),"Not found") -> Not found | N8: =IF($M8="Retail",1,0) -> 0 | O8: =IF($M8="Non-Retail",1,0) -> 0
A9: IVF | B9: 43466 | C9: 55153 | D9: OP-Euro -sijoitusrahasto | E9: 07439622#016 | F9: 11024008 | G9: UCITS | H9: Open-end | I9: Korkorahasto | J9: =IF(ISNUMBER(MATCH($D9,'Lopettaneet 2013->'!$D:$D,0)),INDEX('Lopettaneet 2013->'!$K:$K,MATCH($D9,'Lopettaneet 2013->'!$D:$D,0)),"Continues") -> Closed | K9: =IF($J9="Continues",DATEDIF($B9,TODAY(),"Y"),INDEX('Lopettaneet 2013->'!$L:$L,MATCH($D9,'Lopettaneet 2013->'!$D:$D,0))) -> 10 | L9: =IFERROR(INDEX('[1]30.06.2024'!$H:$H,MATCH($E9,'[1]30.06.2024'!$B:$B,0)),"Not found") -> OP-Rahastoyhtiö Oy | M9: =IFERROR(INDEX([2]Sheet1!$B:$B,MATCH($D9,[2]Sheet1!$A:$A,0)),"Not found") -> Retail | N9: =IF($M9="Retail",1,0) -> 1 | O9: =IF($M9="Non-Retail",1,0) -> 0
A10: IVF | B10: 43466 | C10: 55153 | D10: S-Pankki Lyhyt Korko Sijoitusrahasto | E10: 09791339#004 | F10: 20667232 | G10: UCITS | H10: Open-end | I10: Korkorahasto | J10: =IF(ISNUMBER(MATCH($D10,'Lopettaneet 2013->'!$D:$D,0)),INDEX('Lopettaneet 2013->'!$K:$K,MATCH($D10,'Lopettaneet 2013->'!$D:$D,0)),"Continues") -> Closed | K10: =IF($J10="Continues",DATEDIF($B10,TODAY(),"Y"),INDEX('Lopettaneet 2013->'!$L:$L,MATCH($D10,'Lopettaneet 2013->'!$D:$D,0))) -> 6 | L10: =IFERROR(INDEX('[1]30.06.2024'!$H:$H,MATCH($E10,'[1]30.06.2024'!$B:$B,0)),"Not found") -> S-Pankki Rahastoyhtiö Oy | M10: =IFERROR(INDEX([2]Sheet1!$B:$B,MATCH($D10,[2]Sheet1!$A:$A,0)),"Not found") -> Retail | N10: =IF($M10="Retail",1,0) -> 1 | O10: =IF($M10="Non-Retail",1,0) -> 0
A11: PEF | B11: 41974 | C11: 44469 | D11: Veraventure Oy | E11: 08425222#002 | F11: 8425222 | G11: Non-UCITS | H11: Closed-end | I11: Venture Capital -rahasto | J11: =IF(ISNUMBER(MATCH($D11,'Lopettaneet 2013->'!$D:$D,0)),INDEX('Lopettaneet 2013->'!$K:$K,MATCH($D11,'Lopettaneet 2013->'!$D:$D,0)),"Continues") -> Closed | K11: =IF($J11="Continues",DATEDIF($B11,TODAY(),"Y"),INDEX('Lopettaneet 2013->'!$L:$L,MATCH($D11,'Lopettaneet 2013->'!$D:$D,0))) -> 6 | L11: =IFERROR(INDEX('[1]30.06.2024'!$H:$H,MATCH($E11,'[1]30.06.2024'!$B:$B,0)),"Not found") -> Not found | M11: =IFERROR(INDEX([2]Sheet1!$B:$B,MATCH($D11,[2]Sheet1!$A:$A,0)),"Not found") -> Not found | N11: =IF($M11="Retail",1,0) -> 0 | O11: =IF($M11="Non-Retail",1,0) -> 0
A12: PEF | B12: 41974 | C12: 43100 | D12: Aloitusrahasto Vera Oy | E12: 08425222#001 | F12: 8425142 | G12: Non-UCITS | H12: Closed-end | I12: Venture Capital -rahasto | J12: =IF(ISNUMBER(MATCH($D12,'Lopettaneet 2013->'!$D:$D,0)),INDEX('Lopettaneet 2013->'!$K:$K,MATCH($D12,'Lopettaneet 2013->'!$D:$D,0)),"Continues") -> Closed | K12: =IF($J12="Continues",DATEDIF($B12,TODAY(),"Y"),INDEX('Lopettaneet 2013->'!$L:$L,MATCH($D12,'Lopettaneet 2013->'!$D:$D,0))) -> 3 | L12: =IFERROR(INDEX('[1]30.06.2024'!$H:$H,MATCH($E12,'[1]30.06.2024'!$B:$B,0)),"Not found") -> Not found | M12: =IFERROR(INDEX([2]Sheet1!$B:$B,MATCH($D12,[2]Sheet1!$A:$A,0)),"Not found") -> Not found | N12: =IF($M12="Retail",1,0) -> 0 | O12: =IF($M12="Non-Retail",1,0) -> 0
A13: IVF | B13: 43466 | C13: 55153 | D13: Sijoitusrahasto eQ Lyhyt Korko | E13: 07360527#007 | F13: 18001415 | G13: UCITS | H13: Open-end | I13: Korkorahasto | J13: =IF(ISNUMBER(MATCH($D13,'Lopettaneet 2013->'!$D:$D,0)),INDEX('Lopettaneet 2013->'!$K:$K,MATCH($D13,'Lopettaneet 2013->'!$D:$D,0)),"Continues") -> Closed | K13: =IF($J13="Continues",DATEDIF($B13,TODAY(),"Y"),INDEX('Lopettaneet 2013->'!$L:$L,MATCH($D13,'Lopettaneet 2013->'!$D:$D,0))) -> 10 | L13: =IFERROR(INDEX('[1]30.06.2024'!$H:$H,MATCH($E13,'[1]30.06.2024'!$B:$B,0)),"Not found") -> eQ Rahastoyhtiö Oy | M13: =IFERROR(INDEX([2]Sheet1!$B:$B,MATCH($D13,[2]Sheet1!$A:$A,0)),"Not found") -> Retail | N13: =IF($M13="Retail",1,0) -> 1 | O13: =IF($M13="Non-Retail",1,0) -> 0
... A292: PEF | B292: 41974 | C292: 42460 | D292: EPI Baltic I Oy | E292: 19331184#002 | F292: 19488085 | G292: Non-UCITS | H292: Closed-end | I292: Kiinteistörahasto | J292: =IF(ISNUMBER(MATCH($D292,'Lopettaneet 2013->'!$D:$D,0)),INDEX('Lopettaneet 2013->'!$K:$K,MATCH($D292,'Lopettaneet 2013->'!$D:$D,0)),"Continues") -> Closed | K292: =IF($J292="Continues",DATEDIF($B292,TODAY(),"Y"),INDEX('Lopettaneet 2013->'!$L:$L,MATCH($D292,'Lopettaneet 2013->'!$D:$D,0))) -> 1 | L292: =IFERROR(INDEX('[1]30.06.2024'!$H:$H,MATCH($E292,'[1]30.06.2024'!$B:$B,0)),"Not found") -> Not found | M292: =IFERROR(INDEX([2]Sheet1!$B:$B,MATCH($D292,[2]Sheet1!$A:$A,0)),"Not found") -> Not found | N292: =IF($M292="Retail",1,0) -> 0 | O292: =IF($M292="Non-Retail",1,0) -> 0
A293: PEF | B293: 41974 | C293: 43100 | D293: MultiFire | E293: 19208258#001 | F293: NULL | G293: Non-UCITS | H293: Closed-end | I293: Hedge-rahasto | J293: =IF(ISNUMBER(MATCH($D293,'Lopettaneet 2013->'!$D:$D,0)),INDEX('Lopettaneet 2013->'!$K:$K,MATCH($D293,'Lopettaneet 2013->'!$D:$D,0)),"Continues") -> Closed | K293: =IF($J293="Continues",DATEDIF($B293,TODAY(),"Y"),INDEX('Lopettaneet 2013->'!$L:$L,MATCH($D293,'Lopettaneet 2013->'!$D:$D,0))) -> 3 | L293: =IFERROR(INDEX('[1]30.06.2024'!$H:$H,MATCH($E293,'[1]30.06.2024'!$B:$B,0)),"Not found") -> Not found | M293: =IFERROR(INDEX([2]Sheet1!$B:$B,MATCH($D293,[2]Sheet1!$A:$A,0)),"Not found") -> Not found | N293: =IF($M293="Retail",1,0) -> 0 | O293: =IF($M293="Non-Retail",1,0) -> 0
A294: PEF | B294: 41974 | C294: 43373 | D294: Maneq Fund 2004 Ky | E294: 19011500#008 | F294: 18634351 | G294: Non-UCITS | H294: Closed-end | I294: Buyout-rahasto | J294: =IF(ISNUMBER(MATCH($D294,'Lopettaneet 2013->'!$D:$D,0)),INDEX('Lopettaneet 2013->'!$K:$K,MATCH($D294,'Lopettaneet 2013->'!$D:$D,0)),"Continues") -> Closed | K294: =IF($J294="Continues",DATEDIF($B294,TODAY(),"Y"),INDEX('Lopettaneet 2013->'!$L:$L,MATCH($D294,'Lopettaneet 2013->'!$D:$D,0))) -> 3 | L294: =IFERROR(INDEX('[1]30.06.2024'!$H:$H,MATCH($E294,'[1]30.06.2024'!$B:$B,0)),"Not found") -> Not found | M294: =IFERROR(INDEX([2]Sheet1!$B:$B,MATCH($D294,[2]Sheet1!$A:$A,0)),"Not found") -> Not found | N294: =IF($M294="Retail",1,0) -> 0 | O294: =IF($M294="Non-Retail",1,0) -> 0
A295: PEF | B295: 41974 | C295: 55153 | D295: TKPM Asuntorahasto I Ky | E295: 18212730#001 | F295: 25129345 | G295: Non-UCITS | H295: Closed-end | I295: Kiinteistörahasto | J295: =IF(ISNUMBER(MATCH($D295,'Lopettaneet 2013->'!$D:$D,0)),INDEX('Lopettaneet 2013->'!$K:$K,MATCH($D295,'Lopettaneet 2013->'!$D:$D,0)),"Continues") -> Continues | K295: =IF($J295="Continues",DATEDIF($B295,TODAY(),"Y"),INDEX('Lopettaneet 2013->'!$L:$L,MATCH($D295,'Lopettaneet 2013->'!$D:$D,0))) -> 10 | L295: =IFERROR(INDEX('[1]30.06.2024'!$H:$H,MATCH($E295,'[1]30.06.2024'!$B:$B,0)),"Not found") -> Taitokaari Property Management Oy | M295: =IFERROR(INDEX([2]Sheet1!$B:$B,MATCH($D295,[2]Sheet1!$A:$A,0)),"Not found") -> Non-Retail | N295: =IF($M295="Retail",1,0) -> 0 | O295: =IF($M295="Non-Retail",1,0) -> 1
A296: PEF | B296: 41974 | C296: 55153 | D296: LähiTapiola Asuntorahasto Prime Feeder Oy | E296: 16172050#001 | F296: 25038101 | G296: Non-UCITS | H296: Closed-end | I296: Kiinteistörahasto | J296: =IF(ISNUMBER(MATCH($D296,'Lopettaneet 2013->'!$D:$D,0)),INDEX('Lopettaneet 2013->'!$K:$K,MATCH($D296,'Lopettaneet 2013->'!$D:$D,0)),"Continues") -> Continues | K296: =IF($J296="Continues",DATEDIF($B296,TODAY(),"Y"),INDEX('Lopettaneet 2013->'!$L:$L,MATCH($D296,'Lopettaneet 2013->'!$D:$D,0))) -> 10 | L296: =IFERROR(INDEX('[1]30.06.2024'!$H:$H,MATCH($E296,'[1]30.06.2024'!$B:$B,0)),"Not found") -> LähiTapiola Vaihtoehtorahastot Oy | M296: =IFERROR(INDEX([2]Sheet1!$B:$B,MATCH($D296,[2]Sheet1!$A:$A,0)),"Not found") -> Non-Retail | N296: =IF($M296="Retail",1,0) -> 0 | O296: =IF($M296="Non-Retail",1,0) -> 1
A297: PEF | B297: 41974 | C297: 43646 | D297: TuuliTapiola Ky | E297: 16172050#002 | F297: 20748876 | G297: Non-UCITS | H297: Closed-end | I297: Venture Capital -rahasto | J297: =IF(ISNUMBER(MATCH($D297,'Lopettaneet 2013->'!$D:$D,0)),INDEX('Lopettaneet 2013->'!$K:$K,MATCH($D297,'Lopettaneet 2013->'!$D:$D,0)),"Continues") -> Closed | K297: =IF($J297="Continues",DATEDIF($B297,TODAY(),"Y"),INDEX('Lopettaneet 2013->'!$L:$L,MATCH($D297,'Lopettaneet 2013->'!$D:$D,0))) -> 4 | L297: =IFERROR(INDEX('[1]30.06.2024'!$H:$H,MATCH($E297,'[1]30.06.2024'!$B:$B,0)),"Not found") -> Not found | M297: =IFERROR(INDEX([2]Sheet1!$B:$B,MATCH($D297,[2]Sheet1!$A:$A,0)),"Not found") -> Not found | N297: =IF($M297="Retail",1,0) -> 0 | O297: =IF($M297="Non-Retail",1,0) -> 0
A298: PEF | B298: 41974 | C298: 55153 | D298: LähiTapiola Asuntorahasto Prime Ky | E298: 16172050#003 | F298: 25317098 | G298: Non-UCITS | H298: Closed-end | I298: Kiinteistörahasto | J298: =IF(ISNUMBER(MATCH($D298,'Lopettaneet 2013->'!$D:$D,0)),INDEX('Lopettaneet 2013->'!$K:$K,MATCH($D298,'Lopettaneet 2013->'!$D:$D,0)),"Continues") -> Continues | K298: =IF($J298="Continues",DATEDIF($B298,TODAY(),"Y"),INDEX('Lopettaneet 2013->'!$L:$L,MATCH($D298,'Lopettaneet 2013->'!$D:$D,0))) -> 10 | L298: =IFERROR(INDEX('[1]30.06.2024'!$H:$H,MATCH($E298,'[1]30.06.2024'!$B:$B,0)),"Not found") -> LähiTapiola Vaihtoehtorahastot Oy | M298: =IFERROR(INDEX([2]Sheet1!$B:$B,MATCH($D298,[2]Sheet1!$A:$A,0)),"Not found") -> Non-Retail | N298: =IF($M298="Retail",1,0) -> 0 | O298: =IF($M298="Non-Retail",1,0) -> 1
A299: PEF | B299: 41974 | C299: 42735 | D299: Rival 10 Invest Oy | E299: 16105296#001 | F299: 24297267 | G299: Non-UCITS | H299: Closed-end | I299: Venture Capital -rahasto | J299: =IF(ISNUMBER(MATCH($D299,'Lopettaneet 2013->'!$D:$D,0)),INDEX('Lopettaneet 2013->'!$K:$K,MATCH($D299,'Lopettaneet 2013->'!$D:$D,0)),"Continues") -> Closed | K299: =IF($J299="Continues",DATEDIF($B299,TODAY(),"Y"),INDEX('Lopettaneet 2013->'!$L:$L,MATCH($D299,'Lopettaneet 2013->'!$D:$D,0))) -> 2 | L299: =IFERROR(INDEX('[1]30.06.2024'!$H:$H,MATCH($E299,'[1]30.06.2024'!$B:$B,0)),"Not found") -> Not found | M299: =IFERROR(INDEX([2]Sheet1!$B:$B,MATCH($D299,[2]Sheet1!$A:$A,0)),"Not found") -> Not found | N299: =IF($M299="Retail",1,0) -> 0 | O299: =IF($M299="Non-Retail",1,0) -> 0
A300: PEF | B300: 41974 | C300: 55153 | D300: Selected Private Equity Investment II Ky | E300: 01120872#007 | F300: 23351831 | G300: Non-UCITS | H300: Closed-end | I300: Buyout-rahasto | J300: =IF(ISNUMBER(MATCH($D300,'Lopettaneet 2013->'!$D:$D,0)),INDEX('Lopettaneet 2013->'!$K:$K,MATCH($D300,'Lopettaneet 2013->'!$D:$D,0)),"Continues") -> Continues | K300: =IF($J300="Continues",DATEDIF($B300,TODAY(),"Y"),INDEX('Lopettaneet 2013->'!$L:$L,MATCH($D300,'Lopettaneet 2013->'!$D:$D,0))) -> 10 | L300: =IFERROR(INDEX('[1]30.06.2024'!$H:$H,MATCH($E300,'[1]30.06.2024'!$B:$B,0)),"Not found") -> Access Capital Advisors Finland Oy | M300: =IFERROR(INDEX([2]Sheet1!$B:$B,MATCH($D300,[2]Sheet1!$A:$A,0)),"Not found") -> Non-Retail | N300: =IF($M300="Retail",1,0) -> 0 | O300: =IF($M300="Non-Retail",1,0) -> 1
A301: PEF | B301: 41974 | C301: 42369 | D301: Rival VIII Invest Oy | E301: 16105296#002 | F301: 23591261 | G301: Non-UCITS | H301: Closed-end | I301: Venture Capital -rahasto | J301: =IF(ISNUMBER(MATCH($D301,'Lopettaneet 2013->'!$D:$D,0)),INDEX('Lopettaneet 2013->'!$K:$K,MATCH($D301,'Lopettaneet 2013->'!$D:$D,0)),"Continues") -> Closed | K301: =IF($J301="Continues",DATEDIF($B301,TODAY(),"Y"),INDEX('Lopettaneet 2013->'!$L:$L,MATCH($D301,'Lopettaneet 2013->'!$D:$D,0))) -> 1 | L301: =IFERROR(INDEX('[1]30.06.2024'!$H:$H,MATCH($E301,'[1]30.06.2024'!$B:$B,0)),"Not found") -> Not found | M301: =IFERROR(INDEX([2]Sheet1!$B:$B,MATCH($D301,[2]Sheet1!$A:$A,0)),"Not found") -> Not found | N301: =IF($M301="Retail",1,0) -> 0 | O301: =IF($M301="Non-Retail",1,0) -> 0
A302: PEF | B302: 41974 | C302: 43100 | D302: Rival XIV Invest Oy | E302: 16105296#003 | F302: 25429196 | G302: Non-UCITS | H302: Closed-end | I302: Venture Capital -rahasto | J302: =IF(ISNUMBER(MATCH($D302,'Lopettaneet 2013->'!$D:$D,0)),INDEX('Lopettaneet 2013->'!$K:$K,MATCH($D302,'Lopettaneet 2013->'!$D:$D,0)),"Continues") -> Closed | K302: =IF($J302="Continues",DATEDIF($B302,TODAY(),"Y"),INDEX('Lopettaneet 2013->'!$L:$L,MATCH($D302,'Lopettaneet 2013->'!$D:$D,0))) -> 3 | L302: =IFERROR(INDEX('[1]30.06.2024'!$H:$H,MATCH($E302,'[1]30.06.2024'!$B:$B,0)),"Not found") -> Not found | M302: =IFERROR(INDEX([2]Sheet1!$B:$B,MATCH($D302,[2]Sheet1!$A:$A,0)),"Not found") -> Not found | N302: =IF($M302="Retail",1,0) -> 0 | O302: =IF($M302="Non-Retail",1,0) -> 0
A303: PEF | B303: 41974 | C303: 44742 | D303: Rival XV Invest Oy | E303: 16105296#004 | F303: 25510867 | G303: Non-UCITS | H303: Closed-end | I303: Buyout-rahasto | J303: =IF(ISNUMBER(MATCH($D303,'Lopettaneet 2013->'!$D:$D,0)),INDEX('Lopettaneet 2013->'!$K:$K,MATCH($D303,'Lopettaneet 2013->'!$D:$D,0)),"Continues") -> Closed | K303: =IF($J303="Continues",DATEDIF($B303,TODAY(),"Y"),INDEX('Lopettaneet 2013->'!$L:$L,MATCH($D303,'Lopettaneet 2013->'!$D:$D,0))) -> 7 | L303: =IFERROR(INDEX('[1]30.06.2024'!$H:$H,MATCH($E303,'[1]30.06.2024'!$B:$B,0)),"Not found") -> Not found | M303: =IFERROR(INDEX([2]Sheet1!$B:$B,MATCH($D303,[2]Sheet1!$A:$A,0)),"Not found") -> Not found | N303: =IF($M303="Retail",1,0) -> 0 | O303: =IF($M303="Non-Retail",1,0) -> 0
A304: PEF | B304: 41974 | C304: 43008 | D304: Ursula Invest Oy | E304: 16105296#005 | F304: 20487880 | G304: Non-UCITS | H304: Closed-end | I304: Venture Capital -rahasto | J304: =IF(ISNUMBER(MATCH($D304,'Lopettaneet 2013->'!$D:$D,0)),INDEX('Lopettaneet 2013->'!$K:$K,MATCH($D304,'Lopettaneet 2013->'!$D:$D,0)),"Continues") -> Closed | K304: =IF($J304="Continues",DATEDIF($B304,TODAY(),"Y"),INDEX('Lopettaneet 2013->'!$L:$L,MATCH($D304,'Lopettaneet 2013->'!$D:$D,0))) -> 2 | L304: =IFERROR(INDEX('[1]30.06.2024'!$H:$H,MATCH($E304,'[1]30.06.2024'!$B:$B,0)),"Not found") -> Not found | M304: =IFERROR(INDEX([2]Sheet1!$B:$B,MATCH($D304,[2]Sheet1!$A:$A,0)),"Not found") -> Not found | N304: =IF($M304="Retail",1,0) -> 0 | O304: =IF($M304="Non-Retail",1,0) -> 0
A305: PEF | B305: 41974 | C305: 42369 | D305: Rival IX Invest Oy | E305: 16105296#006 | F305: 24006669 | G305: Non-UCITS | H305: Closed-end | I305: Venture Capital -rahasto | J305: =IF(ISNUMBER(MATCH($D305,'Lopettaneet 2013->'!$D:$D,0)),INDEX('Lopettaneet 2013->'!$K:$K,MATCH($D305,'Lopettaneet 2013->'!$D:$D,0)),"Continues") -> Closed | K305: =IF($J305="Continues",DATEDIF($B305,TODAY(),"Y"),INDEX('Lopettaneet 2013->'!$L:$L,MATCH($D305,'Lopettaneet 2013->'!$D:$D,0))) -> 1 | L305: =IFERROR(INDEX('[1]30.06.2024'!$H:$H,MATCH($E305,'[1]30.06.2024'!$B:$B,0)),"Not found") -> Not found | M305: =IFERROR(INDEX([2]Sheet1!$B:$B,MATCH($D305,[2]Sheet1!$A:$A,0)),"Not found") -> Not found | N305: =IF($M305="Retail",1,0) -> 0 | O305: =IF($M305="Non-Retail",1,0) -> 0
... A359: PEF | B359: 42186 | C359: 42551 | D359: MedTECH Rahasto Pre-Exit Ky | E359: 20831856#002 | F359: 26783525 | G359: Non-UCITS | H359: Closed-end | I359: Venture Capital -rahasto | J359: =IF(ISNUMBER(MATCH($D359,'Lopettaneet 2013->'!$D:$D,0)),INDEX('Lopettaneet 2013->'!$K:$K,MATCH($D359,'Lopettaneet 2013->'!$D:$D,0)),"Continues") -> Closed | K359: =IF($J359="Continues",DATEDIF($B359,TODAY(),"Y"),INDEX('Lopettaneet 2013->'!$L:$L,MATCH($D359,'Lopettaneet 2013->'!$D:$D,0))) -> 0 | L359: =IFERROR(INDEX('[1]30.06.2024'!$H:$H,MATCH($E359,'[1]30.06.2024'!$B:$B,0)),"Not found") -> Not found | M359: =IFERROR(INDEX([2]Sheet1!$B:$B,MATCH($D359,[2]Sheet1!$A:$A,0)),"Not found") -> Not found | N359: =IF($M359="Retail",1,0) -> 0 | O359: =IF($M359="Non-Retail",1,0) -> 0
A360: PEF | B360: 42186 | C360: 42521 | D360: Posse Fund I Ky | E360: 26593748#001 | F360: NULL | G360: Non-UCITS | H360: Closed-end | I360: Venture Capital -rahasto | J360: =IF(ISNUMBER(MATCH($D360,'Lopettaneet 2013->'!$D:$D,0)),INDEX('Lopettaneet 2013->'!$K:$K,MATCH($D360,'Lopettaneet 2013->'!$D:$D,0)),"Continues") -> Closed | K360: =IF($J360="Continues",DATEDIF($B360,TODAY(),"Y"),INDEX('Lopettaneet 2013->'!$L:$L,MATCH($D360,'Lopettaneet 2013->'!$D:$D,0))) -> 0 | L360: =IFERROR(INDEX('[1]30.06.2024'!$H:$H,MATCH($E360,'[1]30.06.2024'!$B:$B,0)),"Not found") -> Not found | M360: =IFERROR(INDEX([2]Sheet1!$B:$B,MATCH($D360,[2]Sheet1!$A:$A,0)),"Not found") -> Not found | N360: =IF($M360="Retail",1,0) -> 0 | O360: =IF($M360="Non-Retail",1,0) -> 0
A361: PEF | B361: 42156 | C361: 55153 | D361: Kasvattajarahasto Ky | E361: 08718295#004 | F361: 26992837 | G361: Non-UCITS | H361: Closed-end | I361: Buyout-rahasto | J361: =IF(ISNUMBER(MATCH($D361,'Lopettaneet 2013->'!$D:$D,0)),INDEX('Lopettaneet 2013->'!$K:$K,MATCH($D361,'Lopettaneet 2013->'!$D:$D,0)),"Continues") -> Continues | K361: =IF($J361="Continues",DATEDIF($B361,TODAY(),"Y"),INDEX('Lopettaneet 2013->'!$L:$L,MATCH($D361,'Lopettaneet 2013->'!$D:$D,0))) -> 9 | L361: =IFERROR(INDEX('[1]30.06.2024'!$H:$H,MATCH($E361,'[1]30.06.2024'!$B:$B,0)),"Not found") -> Aboa Venture Management Oy | M361: =IFERROR(INDEX([2]Sheet1!$B:$B,MATCH($D361,[2]Sheet1!$A:$A,0)),"Not found") -> Non-Retail | N361: =IF($M361="Retail",1,0) -> 0 | O361: =IF($M361="Non-Retail",1,0) -> 1
A362: PEF | B362: 42248 | C362: 55153 | D362: Open Ocean Fund 2015 Ky | E362: 26638993#001 | F362: 27050315 | G362: Non-UCITS | H362: Closed-end | I362: Venture Capital -rahasto | J362: =IF(ISNUMBER(MATCH($D362,'Lopettaneet 2013->'!$D:$D,0)),INDEX('Lopettaneet 2013->'!$K:$K,MATCH($D362,'Lopettaneet 2013->'!$D:$D,0)),"Continues") -> Continues | K362: =IF($J362="Continues",DATEDIF($B362,TODAY(),"Y"),INDEX('Lopettaneet 2013->'!$L:$L,MATCH($D362,'Lopettaneet 2013->'!$D:$D,0))) -> 9 | L362: =IFERROR(INDEX('[1]30.06.2024'!$H:$H,MATCH($E362,'[1]30.06.2024'!$B:$B,0)),"Not found") -> Open Ocean Partners Oy | M362: =IFERROR(INDEX([2]Sheet1!$B:$B,MATCH($D362,[2]Sheet1!$A:$A,0)),"Not found") -> Non-Retail | N362: =IF($M362="Retail",1,0) -> 0 | O362: =IF($M362="Non-Retail",1,0) -> 1
A363: IVF | B363: 42186 | C363: 55153 | D363: Specialplaceringsfonden Aktia SLS | E363: 06725133#040 | F363: 26980107 | G363: Non-UCITS | H363: Open-end | I363: Osakerahasto | J363: =IF(ISNUMBER(MATCH($D363,'Lopettaneet 2013->'!$D:$D,0)),INDEX('Lopettaneet 2013->'!$K:$K,MATCH($D363,'Lopettaneet 2013->'!$D:$D,0)),"Continues") -> Closed | K363: =IF($J363="Continues",DATEDIF($B363,TODAY(),"Y"),INDEX('Lopettaneet 2013->'!$L:$L,MATCH($D363,'Lopettaneet 2013->'!$D:$D,0))) -> 8 | L363: =IFERROR(INDEX('[1]30.06.2024'!$H:$H,MATCH($E363,'[1]30.06.2024'!$B:$B,0)),"Not found") -> Not found | M363: =IFERROR(INDEX([2]Sheet1!$B:$B,MATCH($D363,[2]Sheet1!$A:$A,0)),"Not found") -> Non-Retail | N363: =IF($M363="Retail",1,0) -> 0 | O363: =IF($M363="Non-Retail",1,0) -> 1
A364: PEF | B364: 42217 | C364: 55153 | D364: WasaGroup Fund III Ky | E364: 25416942#002 | F364: 26870493 | G364: Non-UCITS | H364: Closed-end | I364: Kiinteistörahasto | J364: =IF(ISNUMBER(MATCH($D364,'Lopettaneet 2013->'!$D:$D,0)),INDEX('Lopettaneet 2013->'!$K:$K,MATCH($D364,'Lopettaneet 2013->'!$D:$D,0)),"Continues") -> Continues | K364: =IF($J364="Continues",DATEDIF($B364,TODAY(),"Y"),INDEX('Lopettaneet 2013->'!$L:$L,MATCH($D364,'Lopettaneet 2013->'!$D:$D,0))) -> 9 | L364: =IFERROR(INDEX('[1]30.06.2024'!$H:$H,MATCH($E364,'[1]30.06.2024'!$B:$B,0)),"Not found") -> WasaGroup Funds Oy | M364: =IFERROR(INDEX([2]Sheet1!$B:$B,MATCH($D364,[2]Sheet1!$A:$A,0)),"Not found") -> Non-Retail | N364: =IF($M364="Retail",1,0) -> 0 | O364: =IF($M364="Non-Retail",1,0) -> 1
A365: PEF | B365: 42217 | C365: 55153 | D365: WasaGroup Fund II Ky | E365: 25416942#003 | F365: 26870418 | G365: Non-UCITS | H365: Closed-end | I365: Kiinteistörahasto | J365: =IF(ISNUMBER(MATCH($D365,'Lopettaneet 2013->'!$D:$D,0)),INDEX('Lopettaneet 2013->'!$K:$K,MATCH($D365,'Lopettaneet 2013->'!$D:$D,0)),"Continues") -> Continues | K365: =IF($J365="Continues",DATEDIF($B365,TODAY(),"Y"),INDEX('Lopettaneet 2013->'!$L:$L,MATCH($D365,'Lopettaneet 2013->'!$D:$D,0))) -> 9 | L365: =IFERROR(INDEX('[1]30.06.2024'!$H:$H,MATCH($E365,'[1]30.06.2024'!$B:$B,0)),"Not found") -> WasaGroup Funds Oy | M365: =IFERROR(INDEX([2]Sheet1!$B:$B,MATCH($D365,[2]Sheet1!$A:$A,0)),"Not found") -> Non-Retail | N365: =IF($M365="Retail",1,0) -> 0 | O365: =IF($M365="Non-Retail",1,0) -> 1
A366: PEF | B366: 42217 | C366: 55153 | D366: Taaleri Kiinteistökehitys C-Sarja Ky | E366: 22643277#027 | F366: 26975746 | G366: Non-UCITS | H366: Closed-end | I366: Kiinteistörahasto | J366: =IF(ISNUMBER(MATCH($D366,'Lopettaneet 2013->'!$D:$D,0)),INDEX('Lopettaneet 2013->'!$K:$K,MATCH($D366,'Lopettaneet 2013->'!$D:$D,0)),"Continues") -> Continues | K366: =IF($J366="Continues",DATEDIF($B366,TODAY(),"Y"),INDEX('Lopettaneet 2013->'!$L:$L,MATCH($D366,'Lopettaneet 2013->'!$D:$D,0))) -> 9 | L366: =IFERROR(INDEX('[1]30.06.2024'!$H:$H,MATCH($E366,'[1]30.06.2024'!$B:$B,0)),"Not found") -> Taaleri Pääomarahastot Oy | M366: =IFERROR(INDEX([2]Sheet1!$B:$B,MATCH($D366,[2]Sheet1!$A:$A,0)),"Not found") -> Retail | N366: =IF($M366="Retail",1,0) -> 1 | O366: =IF($M366="Non-Retail",1,0) -> 0
A367: IVF | B367: 42248 | C367: 43434 | D367: Ålandsbanken Kort Ränta SEK Placeringsfond | E367: 14713626#028 | F367: 27068806 | G367: UCITS | H367: Open-end | I367: Korkorahasto | J367: =IF(ISNUMBER(MATCH($D367,'Lopettaneet 2013->'!$D:$D,0)),INDEX('Lopettaneet 2013->'!$K:$K,MATCH($D367,'Lopettaneet 2013->'!$D:$D,0)),"Continues") -> Merged | K367: =IF($J367="Continues",DATEDIF($B367,TODAY(),"Y"),INDEX('Lopettaneet 2013->'!$L:$L,MATCH($D367,'Lopettaneet 2013->'!$D:$D,0))) -> 3 | L367: =IFERROR(INDEX('[1]30.06.2024'!$H:$H,MATCH($E367,'[1]30.06.2024'!$B:$B,0)),"Not found") -> Not found | M367: =IFERROR(INDEX([2]Sheet1!$B:$B,MATCH($D367,[2]Sheet1!$A:$A,0)),"Not found") -> Not found | N367: =IF($M367="Retail",1,0) -> 0 | O367: =IF($M367="Non-Retail",1,0) -> 0
A368: IVF | B368: 42309 | C368: 43404 | D368: Ålandsbanken Obligation Sverige Placeringsfond | E368: 14713626#029 | F368: 27068865 | G368: UCITS | H368: Open-end | I368: Korkorahasto | J368: =IF(ISNUMBER(MATCH($D368,'Lopettaneet 2013->'!$D:$D,0)),INDEX('Lopettaneet 2013->'!$K:$K,MATCH($D368,'Lopettaneet 2013->'!$D:$D,0)),"Continues") -> Merged | K368: =IF($J368="Continues",DATEDIF($B368,TODAY(),"Y"),INDEX('Lopettaneet 2013->'!$L:$L,MATCH($D368,'Lopettaneet 2013->'!$D:$D,0))) -> 2 | L368: =IFERROR(INDEX('[1]30.06.2024'!$H:$H,MATCH($E368,'[1]30.06.2024'!$B:$B,0)),"Not found") -> Not found | M368: =IFERROR(INDEX([2]Sheet1!$B:$B,MATCH($D368,[2]Sheet1!$A:$A,0)),"Not found") -> Not found | N368: =IF($M368="Retail",1,0) -> 0 | O368: =IF($M368="Non-Retail",1,0) -> 0
A369: IVF | B369: 42309 | C369: 55153 | D369: Sijoitusrahasto LähiTapiola Pohjoismaat ESG | E369: 09791339#076 | F369: 27148398 | G369: UCITS | H369: Open-end | I369: Osakerahasto | J369: =IF(ISNUMBER(MATCH($D369,'Lopettaneet 2013->'!$D:$D,0)),INDEX('Lopettaneet 2013->'!$K:$K,MATCH($D369,'Lopettaneet 2013->'!$D:$D,0)),"Continues") -> Continues | K369: =IF($J369="Continues",DATEDIF($B369,TODAY(),"Y"),INDEX('Lopettaneet 2013->'!$L:$L,MATCH($D369,'Lopettaneet 2013->'!$D:$D,0))) -> 9 | L369: =IFERROR(INDEX('[1]30.06.2024'!$H:$H,MATCH($E369,'[1]30.06.2024'!$B:$B,0)),"Not found") -> Not found | M369: =IFERROR(INDEX([2]Sheet1!$B:$B,MATCH($D369,[2]Sheet1!$A:$A,0)),"Not found") -> Retail | N369: =IF($M369="Retail",1,0) -> 1 | O369: =IF($M369="Non-Retail",1,0) -> 0
A370: PEF | B370: 42278 | C370: 55153 | D370: EAI Residential I Ky | E370: 07446590#084 | F370: 26904753 | G370: Non-UCITS | H370: Closed-end | I370: Kiinteistörahasto | J370: =IF(ISNUMBER(MATCH($D370,'Lopettaneet 2013->'!$D:$D,0)),INDEX('Lopettaneet 2013->'!$K:$K,MATCH($D370,'Lopettaneet 2013->'!$D:$D,0)),"Continues") -> Continues | K370: =IF($J370="Continues",DATEDIF($B370,TODAY(),"Y"),INDEX('Lopettaneet 2013->'!$L:$L,MATCH($D370,'Lopettaneet 2013->'!$D:$D,0))) -> 9 | L370: =IFERROR(INDEX('[1]30.06.2024'!$H:$H,MATCH($E370,'[1]30.06.2024'!$B:$B,0)),"Not found") -> Evli-Rahastoyhtiö Oy | M370: =IFERROR(INDEX([2]Sheet1!$B:$B,MATCH($D370,[2]Sheet1!$A:$A,0)),"Not found") -> Non-Retail | N370: =IF($M370="Retail",1,0) -> 0 | O370: =IF($M370="Non-Retail",1,0) -> 1
A371: PEF | B371: 42278 | C371: 55153 | D371: EAI Residential Feeder Fund I Ky | E371: 07446590#085 | F371: 27013303 | G371: Non-UCITS | H371: Closed-end | I371: Kiinteistörahasto | J371: =IF(ISNUMBER(MATCH($D371,'Lopettaneet 2013->'!$D:$D,0)),INDEX('Lopettaneet 2013->'!$K:$K,MATCH($D371,'Lopettaneet 2013->'!$D:$D,0)),"Continues") -> Continues | K371: =IF($J371="Continues",DATEDIF($B371,TODAY(),"Y"),INDEX('Lopettaneet 2013->'!$L:$L,MATCH($D371,'Lopettaneet 2013->'!$D:$D,0))) -> 9 | L371: =IFERROR(INDEX('[1]30.06.2024'!$H:$H,MATCH($E371,'[1]30.06.2024'!$B:$B,0)),"Not found") -> Evli-Rahastoyhtiö Oy | M371: =IFERROR(INDEX([2]Sheet1!$B:$B,MATCH($D371,[2]Sheet1!$A:$A,0)),"Not found") -> Non-Retail | N371: =IF($M371="Retail",1,0) -> 0 | O371: =IF($M371="Non-Retail",1,0) -> 1
A372: PEF | B372: 42278 | C372: 55153 | D372: MB Equity Fund V Ky | E372: 26997152#001 | F372: 27336794 | G372: Non-UCITS | H372: Closed-end | I372: Buyout-rahasto | J372: =IF(ISNUMBER(MATCH($D372,'Lopettaneet 2013->'!$D:$D,0)),INDEX('Lopettaneet 2013->'!$K:$K,MATCH($D372,'Lopettaneet 2013->'!$D:$D,0)),"Continues") -> Continues | K372: =IF($J372="Continues",DATEDIF($B372,TODAY(),"Y"),INDEX('Lopettaneet 2013->'!$L:$L,MATCH($D372,'Lopettaneet 2013->'!$D:$D,0))) -> 9 | L372: =IFERROR(INDEX('[1]30.06.2024'!$H:$H,MATCH($E372,'[1]30.06.2024'!$B:$B,0)),"Not found") -> MB Partners V Oy | M372: =IFERROR(INDEX([2]Sheet1!$B:$B,MATCH($D372,[2]Sheet1!$A:$A,0)),"Not found") -> Non-Retail | N372: =IF($M372="Retail",1,0) -> 0 | O372: =IF($M372="Non-Retail",1,0) -> 1
... A382: PEF | B382: 42278 | C382: 43830 | D382: ICON Real Estate Fund III - Suurpelto Ky (hoitaminen ja markkinointi kielletty 17.12.2019) | E382: 25361865#002 | F382: 26570757 | G382: Non-UCITS | H382: Closed-end | I382: Kiinteistörahasto | J382: =IF(ISNUMBER(MATCH($D382,'Lopettaneet 2013->'!$D:$D,0)),INDEX('Lopettaneet 2013->'!$K:$K,MATCH($D382,'Lopettaneet 2013->'!$D:$D,0)),"Continues") -> Closed | K382: =IF($J382="Continues",DATEDIF($B382,TODAY(),"Y"),INDEX('Lopettaneet 2013->'!$L:$L,MATCH($D382,'Lopettaneet 2013->'!$D:$D,0))) -> 4 | L382: =IFERROR(INDEX('[1]30.06.2024'!$H:$H,MATCH($E382,'[1]30.06.2024'!$B:$B,0)),"Not found") -> Not found | M382: =IFERROR(INDEX([2]Sheet1!$B:$B,MATCH($D382,[2]Sheet1!$A:$A,0)),"Not found") -> Not found | N382: =IF($M382="Retail",1,0) -> 0 | O382: =IF($M382="Non-Retail",1,0) -> 0
A383: PEF | B383: 42278 | C383: 44742 | D383: Midinvest Fund III Ky | E383: 16447843#008 | F383: NULL | G383: Non-UCITS | H383: Closed-end | I383: Buyout-rahasto | J383: =IF(ISNUMBER(MATCH($D383,'Lopettaneet 2013->'!$D:$D,0)),INDEX('Lopettaneet 2013->'!$K:$K,MATCH($D383,'Lopettaneet 2013->'!$D:$D,0)),"Continues") -> Closed | K383: =IF($J383="Continues",DATEDIF($B383,TODAY(),"Y"),INDEX('Lopettaneet 2013->'!$L:$L,MATCH($D383,'Lopettaneet 2013->'!$D:$D,0))) -> 6 | L383: =IFERROR(INDEX('[1]30.06.2024'!$H:$H,MATCH($E383,'[1]30.06.2024'!$B:$B,0)),"Not found") -> Not found | M383: =IFERROR(INDEX([2]Sheet1!$B:$B,MATCH($D383,[2]Sheet1!$A:$A,0)),"Not found") -> Not found | N383: =IF($M383="Retail",1,0) -> 0 | O383: =IF($M383="Non-Retail",1,0) -> 0
A384: PEF | B384: 42278 | C384: 55153 | D384: Certior Credit Investments I Ky | E384: 24169855#002 | F384: 27288753 | G384: Non-UCITS | H384: Closed-end | I384: Muu rahasto | J384: =IF(ISNUMBER(MATCH($D384,'Lopettaneet 2013->'!$D:$D,0)),INDEX('Lopettaneet 2013->'!$K:$K,MATCH($D384,'Lopettaneet 2013->'!$D:$D,0)),"Continues") -> Continues | K384: =IF($J384="Continues",DATEDIF($B384,TODAY(),"Y"),INDEX('Lopettaneet 2013->'!$L:$L,MATCH($D384,'Lopettaneet 2013->'!$D:$D,0))) -> 9 | L384: =IFERROR(INDEX('[1]30.06.2024'!$H:$H,MATCH($E384,'[1]30.06.2024'!$B:$B,0)),"Not found") -> Certior Capital Oy | M384: =IFERROR(INDEX([2]Sheet1!$B:$B,MATCH($D384,[2]Sheet1!$A:$A,0)),"Not found") -> Non-Retail | N384: =IF($M384="Retail",1,0) -> 0 | O384: =IF($M384="Non-Retail",1,0) -> 1
A385: PEF | B385: 42370 | C385: 55153 | D385: eQ PE VIII North Ky | E385: 07360527#079 | F385: 27341235 | G385: Non-UCITS | H385: Closed-end | I385: Buyout-rahasto | J385: =IF(ISNUMBER(MATCH($D385,'Lopettaneet 2013->'!$D:$D,0)),INDEX('Lopettaneet 2013->'!$K:$K,MATCH($D385,'Lopettaneet 2013->'!$D:$D,0)),"Continues") -> Continues | K385: =IF($J385="Continues",DATEDIF($B385,TODAY(),"Y"),INDEX('Lopettaneet 2013->'!$L:$L,MATCH($D385,'Lopettaneet 2013->'!$D:$D,0))) -> 9 | L385: =IFERROR(INDEX('[1]30.06.2024'!$H:$H,MATCH($E385,'[1]30.06.2024'!$B:$B,0)),"Not found") -> eQ Rahastoyhtiö Oy | M385: =IFERROR(INDEX([2]Sheet1!$B:$B,MATCH($D385,[2]Sheet1!$A:$A,0)),"Not found") -> Non-Retail | N385: =IF($M385="Retail",1,0) -> 0 | O385: =IF($M385="Non-Retail",1,0) -> 1
A386: IVF | B386: 42339 | C386: 55153 | D386: Placeringsfonden Aktia Emerging Market Local Currency Frontier Bond+ | E386: 06725133#041 | F386: 27236195 | G386: UCITS | H386: Open-end | I386: Korkorahasto | J386: =IF(ISNUMBER(MATCH($D386,'Lopettaneet 2013->'!$D:$D,0)),INDEX('Lopettaneet 2013->'!$K:$K,MATCH($D386,'Lopettaneet 2013->'!$D:$D,0)),"Continues") -> Continues | K386: =IF($J386="Continues",DATEDIF($B386,TODAY(),"Y"),INDEX('Lopettaneet 2013->'!$L:$L,MATCH($D386,'Lopettaneet 2013->'!$D:$D,0))) -> 9 | L386: =IFERROR(INDEX('[1]30.06.2024'!$H:$H,MATCH($E386,'[1]30.06.2024'!$B:$B,0)),"Not found") -> Not found | M386: =IFERROR(INDEX([2]Sheet1!$B:$B,MATCH($D386,[2]Sheet1!$A:$A,0)),"Not found") -> Retail | N386: =IF($M386="Retail",1,0) -> 1 | O386: =IF($M386="Non-Retail",1,0) -> 0
A387: PEF | B387: 42064 | C387: 43465 | D387: BPT Healthcare II Feeder A Ky | E387: 25870598#003 | F387: 25878223 | G387: Non-UCITS | H387: Closed-end | I387: Kiinteistörahasto | J387: =IF(ISNUMBER(MATCH($D387,'Lopettaneet 2013->'!$D:$D,0)),INDEX('Lopettaneet 2013->'!$K:$K,MATCH($D387,'Lopettaneet 2013->'!$D:$D,0)),"Continues") -> Closed | K387: =IF($J387="Continues",DATEDIF($B387,TODAY(),"Y"),INDEX('Lopettaneet 2013->'!$L:$L,MATCH($D387,'Lopettaneet 2013->'!$D:$D,0))) -> 3 | L387: =IFERROR(INDEX('[1]30.06.2024'!$H:$H,MATCH($E387,'[1]30.06.2024'!$B:$B,0)),"Not found") -> Not found | M387: =IFERROR(INDEX([2]Sheet1!$B:$B,MATCH($D387,[2]Sheet1!$A:$A,0)),"Not found") -> Not found | N387: =IF($M387="Retail",1,0) -> 0 | O387: =IF($M387="Non-Retail",1,0) -> 0
A388: PEF | B388: 42795 | C388: 43465 | D388: BPT Healthcare II Feeder B Ky | E388: 25870598#004 | F388: 26066745 | G388: Non-UCITS | H388: Closed-end | I388: Kiinteistörahasto | J388: =IF(ISNUMBER(MATCH($D388,'Lopettaneet 2013->'!$D:$D,0)),INDEX('Lopettaneet 2013->'!$K:$K,MATCH($D388,'Lopettaneet 2013->'!$D:$D,0)),"Continues") -> Closed | K388: =IF($J388="Continues",DATEDIF($B388,TODAY(),"Y"),INDEX('Lopettaneet 2013->'!$L:$L,MATCH($D388,'Lopettaneet 2013->'!$D:$D,0))) -> 1 | L388: =IFERROR(INDEX('[1]30.06.2024'!$H:$H,MATCH($E388,'[1]30.06.2024'!$B:$B,0)),"Not found") -> Not found | M388: =IFERROR(INDEX([2]Sheet1!$B:$B,MATCH($D388,[2]Sheet1!$A:$A,0)),"Not found") -> Not found | N388: =IF($M388="Retail",1,0) -> 0 | O388: =IF($M388="Non-Retail",1,0) -> 0
A389: IVF | B389: 42339 | C389: 44074 | D389: OP-Private Tavoitetuotto -erikoissijoitusrahasto | E389: 07439622#124 | F389: 27155141 | G389: Non-UCITS | H389: Open-end | I389: Yhdistelmärahasto | J389: =IF(ISNUMBER(MATCH($D389,'Lopettaneet 2013->'!$D:$D,0)),INDEX('Lopettaneet 2013->'!$K:$K,MATCH($D389,'Lopettaneet 2013->'!$D:$D,0)),"Continues") -> Merged | K389: =IF($J389="Continues",DATEDIF($B389,TODAY(),"Y"),INDEX('Lopettaneet 2013->'!$L:$L,MATCH($D389,'Lopettaneet 2013->'!$D:$D,0))) -> 4 | L389: =IFERROR(INDEX('[1]30.06.2024'!$H:$H,MATCH($E389,'[1]30.06.2024'!$B:$B,0)),"Not found") -> Not found | M389: =IFERROR(INDEX([2]Sheet1!$B:$B,MATCH($D389,[2]Sheet1!$A:$A,0)),"Not found") -> Not found | N389: =IF($M389="Retail",1,0) -> 0 | O389: =IF($M389="Non-Retail",1,0) -> 0
A390: IVF | B390: 42339 | C390: 44074 | D390: OP-Private Tavoitetuotto Plus -erikoissijoitusrahasto | E390: 07439622#125 | F390: 27155678 | G390: Non-UCITS | H390: Open-end | I390: Yhdistelmärahasto | J390: =IF(ISNUMBER(MATCH($D390,'Lopettaneet 2013->'!$D:$D,0)),INDEX('Lopettaneet 2013->'!$K:$K,MATCH($D390,'Lopettaneet 2013->'!$D:$D,0)),"Continues") -> Merged | K390: =IF($J390="Continues",DATEDIF($B390,TODAY(),"Y"),INDEX('Lopettaneet 2013->'!$L:$L,MATCH($D390,'Lopettaneet 2013->'!$D:$D,0))) -> 4 | L390: =IFERROR(INDEX('[1]30.06.2024'!$H:$H,MATCH($E390,'[1]30.06.2024'!$B:$B,0)),"Not found") -> Not found | M390: =IFERROR(INDEX([2]Sheet1!$B:$B,MATCH($D390,[2]Sheet1!$A:$A,0)),"Not found") -> Not found | N390: =IF($M390="Retail",1,0) -> 0 | O390: =IF($M390="Non-Retail",1,0) -> 0
A391: PEF | B391: 42339 | C391: 55153 | D391: Real Estate Fund of Funds V Ky | E391: 05991018#010 | F391: 27713916 | G391: Non-UCITS | H391: Closed-end | I391: Kiinteistörahasto | J391: =IF(ISNUMBER(MATCH($D391,'Lopettaneet 2013->'!$D:$D,0)),INDEX('Lopettaneet 2013->'!$K:$K,MATCH($D391,'Lopettaneet 2013->'!$D:$D,0)),"Continues") -> Continues | K391: =IF($J391="Continues",DATEDIF($B391,TODAY(),"Y"),INDEX('Lopettaneet 2013->'!$L:$L,MATCH($D391,'Lopettaneet 2013->'!$D:$D,0))) -> 9 | L391: =IFERROR(INDEX('[1]30.06.2024'!$H:$H,MATCH($E391,'[1]30.06.2024'!$B:$B,0)),"Not found") -> OP Kiinteistösijoitus Oy | M391: =IFERROR(INDEX([2]Sheet1!$B:$B,MATCH($D391,[2]Sheet1!$A:$A,0)),"Not found") -> Non-Retail | N391: =IF($M391="Retail",1,0) -> 0 | O391: =IF($M391="Non-Retail",1,0) -> 1
A392: PEF | B392: 42339 | C392: 55153 | D392: OP Tonttirahasto Ky | E392: 05991018#011 | F392: 27313613 | G392: Non-UCITS | H392: Closed-end | I392: Kiinteistörahasto | J392: =IF(ISNUMBER(MATCH($D392,'Lopettaneet 2013->'!$D:$D,0)),INDEX('Lopettaneet 2013->'!$K:$K,MATCH($D392,'Lopettaneet 2013->'!$D:$D,0)),"Continues") -> Continues | K392: =IF($J392="Continues",DATEDIF($B392,TODAY(),"Y"),INDEX('Lopettaneet 2013->'!$L:$L,MATCH($D392,'Lopettaneet 2013->'!$D:$D,0))) -> 9 | L392: =IFERROR(INDEX('[1]30.06.2024'!$H:$H,MATCH($E392,'[1]30.06.2024'!$B:$B,0)),"Not found") -> OP Kiinteistösijoitus Oy | M392: =IFERROR(INDEX([2]Sheet1!$B:$B,MATCH($D392,[2]Sheet1!$A:$A,0)),"Not found") -> Non-Retail | N392: =IF($M392="Retail",1,0) -> 0 | O392: =IF($M392="Non-Retail",1,0) -> 1
A393: IVF | B393: 42370 | C393: 55153 | D393: Sijoitusrahasto Zenito Silver and Gold | E393: 07446590#126 | F393: 27335724 | G393: UCITS | H393: Open-end | I393: Osakerahasto | J393: =IF(ISNUMBER(MATCH($D393,'Lopettaneet 2013->'!$D:$D,0)),INDEX('Lopettaneet 2013->'!$K:$K,MATCH($D393,'Lopettaneet 2013->'!$D:$D,0)),"Continues") -> Continues | K393: =IF($J393="Continues",DATEDIF($B393,TODAY(),"Y"),INDEX('Lopettaneet 2013->'!$L:$L,MATCH($D393,'Lopettaneet 2013->'!$D:$D,0))) -> 9 | L393: =IFERROR(INDEX('[1]30.06.2024'!$H:$H,MATCH($E393,'[1]30.06.2024'!$B:$B,0)),"Not found") -> Evli-Rahastoyhtiö Oy | M393: =IFERROR(INDEX([2]Sheet1!$B:$B,MATCH($D393,[2]Sheet1!$A:$A,0)),"Not found") -> Retail | N393: =IF($M393="Retail",1,0) -> 1 | O393: =IF($M393="Non-Retail",1,0) -> 0
A394: PEF | B394: 42430 | C394: 55153 | D394: Korona Fund III Ky | E394: 20377374#003 | F394: 27873821 | G394: Non-UCITS | H394: Closed-end | I394: Buyout-rahasto | J394: =IF(ISNUMBER(MATCH($D394,'Lopettaneet 2013->'!$D:$D,0)),INDEX('Lopettaneet 2013->'!$K:$K,MATCH($D394,'Lopettaneet 2013->'!$D:$D,0)),"Continues") -> Continues | K394: =IF($J394="Continues",DATEDIF($B394,TODAY(),"Y"),INDEX('Lopettaneet 2013->'!$L:$L,MATCH($D394,'Lopettaneet 2013->'!$D:$D,0))) -> 9 | L394: =IFERROR(INDEX('[1]30.06.2024'!$H:$H,MATCH($E394,'[1]30.06.2024'!$B:$B,0)),"Not found") -> Korona Invest Oy | M394: =IFERROR(INDEX([2]Sheet1!$B:$B,MATCH($D394,[2]Sheet1!$A:$A,0)),"Not found") -> Non-Retail | N394: =IF($M394="Retail",1,0) -> 0 | O394: =IF($M394="Non-Retail",1,0) -> 1
A395: PEF | B395: 42339 | C395: 43830 | D395: ICON Real Estate Fund II - Syöttörahasto I Ky | E395: 25361865#003 | F395: 26836914 | G395: Non-UCITS | H395: Closed-end | I395: Kiinteistörahasto | J395: =IF(ISNUMBER(MATCH($D395,'Lopettaneet 2013->'!$D:$D,0)),INDEX('Lopettaneet 2013->'!$K:$K,MATCH($D395,'Lopettaneet 2013->'!$D:$D,0)),"Continues") -> Closed | K395: =IF($J395="Continues",DATEDIF($B395,TODAY(),"Y"),INDEX('Lopettaneet 2013->'!$L:$L,MATCH($D395,'Lopettaneet 2013->'!$D:$D,0))) -> 4 | L395: =IFERROR(INDEX('[1]30.06.2024'!$H:$H,MATCH($E395,'[1]30.06.2024'!$B:$B,0)),"Not found") -> Not found | M395: =IFERROR(INDEX([2]Sheet1!$B:$B,MATCH($D395,[2]Sheet1!$A:$A,0)),"Not found") -> Not found | N395: =IF($M395="Retail",1,0) -> 0 | O395: =IF($M395="Non-Retail",1,0) -> 0
... A461: PEF | B461: 42705 | C461: 44926 | D461: Finhoiva Ky | E461: 27526045#002 | F461: 27780414 | G461: Non-UCITS | H461: Closed-end | I461: Kiinteistörahasto | J461: =IF(ISNUMBER(MATCH($D461,'Lopettaneet 2013->'!$D:$D,0)),INDEX('Lopettaneet 2013->'!$K:$K,MATCH($D461,'Lopettaneet 2013->'!$D:$D,0)),"Continues") -> Closed | K461: =IF($J461="Continues",DATEDIF($B461,TODAY(),"Y"),INDEX('Lopettaneet 2013->'!$L:$L,MATCH($D461,'Lopettaneet 2013->'!$D:$D,0))) -> 6 | L461: =IFERROR(INDEX('[1]30.06.2024'!$H:$H,MATCH($E461,'[1]30.06.2024'!$B:$B,0)),"Not found") -> Not found | M461: =IFERROR(INDEX([2]Sheet1!$B:$B,MATCH($D461,[2]Sheet1!$A:$A,0)),"Not found") -> Not found | N461: =IF($M461="Retail",1,0) -> 0 | O461: =IF($M461="Non-Retail",1,0) -> 0
A462: PEF | B462: 42826 | C462: 42827 | D462: Obsido Yritysrahasto I Ky | E462: 24489795#010 | F462: NULL | G462: Non-UCITS | H462: Closed-end | I462: Venture Capital -rahasto | J462: =IF(ISNUMBER(MATCH($D462,'Lopettaneet 2013->'!$D:$D,0)),INDEX('Lopettaneet 2013->'!$K:$K,MATCH($D462,'Lopettaneet 2013->'!$D:$D,0)),"Continues") -> Closed | K462: =IF($J462="Continues",DATEDIF($B462,TODAY(),"Y"),INDEX('Lopettaneet 2013->'!$L:$L,MATCH($D462,'Lopettaneet 2013->'!$D:$D,0))) -> 0 | L462: =IFERROR(INDEX('[1]30.06.2024'!$H:$H,MATCH($E462,'[1]30.06.2024'!$B:$B,0)),"Not found") -> Not found | M462: =IFERROR(INDEX([2]Sheet1!$B:$B,MATCH($D462,[2]Sheet1!$A:$A,0)),"Not found") -> Not found | N462: =IF($M462="Retail",1,0) -> 0 | O462: =IF($M462="Non-Retail",1,0) -> 0
A463: PEF | B463: 42705 | C463: 55153 | D463: Sentica Buyout V Ky | E463: 19076208#010 | F463: 27980037 | G463: Non-UCITS | H463: Closed-end | I463: Buyout-rahasto | J463: =IF(ISNUMBER(MATCH($D463,'Lopettaneet 2013->'!$D:$D,0)),INDEX('Lopettaneet 2013->'!$K:$K,MATCH($D463,'Lopettaneet 2013->'!$D:$D,0)),"Continues") -> Continues | K463: =IF($J463="Continues",DATEDIF($B463,TODAY(),"Y"),INDEX('Lopettaneet 2013->'!$L:$L,MATCH($D463,'Lopettaneet 2013->'!$D:$D,0))) -> 8 | L463: =IFERROR(INDEX('[1]30.06.2024'!$H:$H,MATCH($E463,'[1]30.06.2024'!$B:$B,0)),"Not found") -> Sentica Partners Oy | M463: =IFERROR(INDEX([2]Sheet1!$B:$B,MATCH($D463,[2]Sheet1!$A:$A,0)),"Not found") -> Non-Retail | N463: =IF($M463="Retail",1,0) -> 0 | O463: =IF($M463="Non-Retail",1,0) -> 1
A464: PEF | B464: 42705 | C464: 55153 | D464: Korona Fund III SR Ky | E464: 20377374#004 | F464: 27853791 | G464: Non-UCITS | H464: Closed-end | I464: Buyout-rahasto | J464: =IF(ISNUMBER(MATCH($D464,'Lopettaneet 2013->'!$D:$D,0)),INDEX('Lopettaneet 2013->'!$K:$K,MATCH($D464,'Lopettaneet 2013->'!$D:$D,0)),"Continues") -> Continues | K464: =IF($J464="Continues",DATEDIF($B464,TODAY(),"Y"),INDEX('Lopettaneet 2013->'!$L:$L,MATCH($D464,'Lopettaneet 2013->'!$D:$D,0))) -> 8 | L464: =IFERROR(INDEX('[1]30.06.2024'!$H:$H,MATCH($E464,'[1]30.06.2024'!$B:$B,0)),"Not found") -> Korona Invest Oy | M464: =IFERROR(INDEX([2]Sheet1!$B:$B,MATCH($D464,[2]Sheet1!$A:$A,0)),"Not found") -> Non-Retail | N464: =IF($M464="Retail",1,0) -> 0 | O464: =IF($M464="Non-Retail",1,0) -> 1
A465: PEF | B465: 42614 | C465: 55153 | D465: Epiqus Kotouttaminen I Ky | E465: 26536188#002 | F465: 27771358 | G465: Non-UCITS | H465: Closed-end | I465: Muu rahasto | J465: =IF(ISNUMBER(MATCH($D465,'Lopettaneet 2013->'!$D:$D,0)),INDEX('Lopettaneet 2013->'!$K:$K,MATCH($D465,'Lopettaneet 2013->'!$D:$D,0)),"Continues") -> Closed | K465: =IF($J465="Continues",DATEDIF($B465,TODAY(),"Y"),INDEX('Lopettaneet 2013->'!$L:$L,MATCH($D465,'Lopettaneet 2013->'!$D:$D,0))) -> 7 | L465: =IFERROR(INDEX('[1]30.06.2024'!$H:$H,MATCH($E465,'[1]30.06.2024'!$B:$B,0)),"Not found") -> S-Pankki Vaikuttavuussijoitukset Oy | M465: =IFERROR(INDEX([2]Sheet1!$B:$B,MATCH($D465,[2]Sheet1!$A:$A,0)),"Not found") -> Non-Retail | N465: =IF($M465="Retail",1,0) -> 0 | O465: =IF($M465="Non-Retail",1,0) -> 1
A466: IVF | B466: 42675 | C466: 55153 | D466: Placeringsfonden Aktia Nordic Micro Cap | E466: 06725133#044 | F466: 27864191 | G466: UCITS | H466: Open-end | I466: Osakerahasto | J466: =IF(ISNUMBER(MATCH($D466,'Lopettaneet 2013->'!$D:$D,0)),INDEX('Lopettaneet 2013->'!$K:$K,MATCH($D466,'Lopettaneet 2013->'!$D:$D,0)),"Continues") -> Continues | K466: =IF($J466="Continues",DATEDIF($B466,TODAY(),"Y"),INDEX('Lopettaneet 2013->'!$L:$L,MATCH($D466,'Lopettaneet 2013->'!$D:$D,0))) -> 8 | L466: =IFERROR(INDEX('[1]30.06.2024'!$H:$H,MATCH($E466,'[1]30.06.2024'!$B:$B,0)),"Not found") -> Not found | M466: =IFERROR(INDEX([2]Sheet1!$B:$B,MATCH($D466,[2]Sheet1!$A:$A,0)),"Not found") -> Retail | N466: =IF($M466="Retail",1,0) -> 1 | O466: =IF($M466="Non-Retail",1,0) -> 0
A467: IVF | B467: 42705 | C467: 55153 | D467: S-Pankki Metsä Erikoissijoitusrahasto | E467: 09791339#077 | F467: 27796168 | G467: Non-UCITS | H467: Open-end | I467: Muu rahasto | J467: =IF(ISNUMBER(MATCH($D467,'Lopettaneet 2013->'!$D:$D,0)),INDEX('Lopettaneet 2013->'!$K:$K,MATCH($D467,'Lopettaneet 2013->'!$D:$D,0)),"Continues") -> Continues | K467: =IF($J467="Continues",DATEDIF($B467,TODAY(),"Y"),INDEX('Lopettaneet 2013->'!$L:$L,MATCH($D467,'Lopettaneet 2013->'!$D:$D,0))) -> 8 | L467: =IFERROR(INDEX('[1]30.06.2024'!$H:$H,MATCH($E467,'[1]30.06.2024'!$B:$B,0)),"Not found") -> S-Pankki Rahastoyhtiö Oy | M467: =IFERROR(INDEX([2]Sheet1!$B:$B,MATCH($D467,[2]Sheet1!$A:$A,0)),"Not found") -> Retail | N467: =IF($M467="Retail",1,0) -> 1 | O467: =IF($M467="Non-Retail",1,0) -> 0
A468: PEF | B468: 42552 | C468: 44469 | D468: EAKR-Aloitusrahasto Oy | E468: 08425222#003 | F468: 27321576 | G468: Non-UCITS | H468: Closed-end | I468: Buyout-rahasto | J468: =IF(ISNUMBER(MATCH($D468,'Lopettaneet 2013->'!$D:$D,0)),INDEX('Lopettaneet 2013->'!$K:$K,MATCH($D468,'Lopettaneet 2013->'!$D:$D,0)),"Continues") -> Closed | K468: =IF($J468="Continues",DATEDIF($B468,TODAY(),"Y"),INDEX('Lopettaneet 2013->'!$L:$L,MATCH($D468,'Lopettaneet 2013->'!$D:$D,0))) -> 5 | L468: =IFERROR(INDEX('[1]30.06.2024'!$H:$H,MATCH($E468,'[1]30.06.2024'!$B:$B,0)),"Not found") -> Not found | M468: =IFERROR(INDEX([2]Sheet1!$B:$B,MATCH($D468,[2]Sheet1!$A:$A,0)),"Not found") -> Not found | N468: =IF($M468="Retail",1,0) -> 0 | O468: =IF($M468="Non-Retail",1,0) -> 0
A469: PEF | B469: 42644 | C469: 45199 | D469: WS Solar Energy Fund I Ky | E469: 25997361#001 | F469: 28702725 | G469: Non-UCITS | H469: Closed-end | I469: Muu rahasto | J469: =IF(ISNUMBER(MATCH($D469,'Lopettaneet 2013->'!$D:$D,0)),INDEX('Lopettaneet 2013->'!$K:$K,MATCH($D469,'Lopettaneet 2013->'!$D:$D,0)),"Continues") -> Closed | K469: =IF($J469="Continues",DATEDIF($B469,TODAY(),"Y"),INDEX('Lopettaneet 2013->'!$L:$L,MATCH($D469,'Lopettaneet 2013->'!$D:$D,0))) -> 6 | L469: =IFERROR(INDEX('[1]30.06.2024'!$H:$H,MATCH($E469,'[1]30.06.2024'!$B:$B,0)),"Not found") -> Not found | M469: =IFERROR(INDEX([2]Sheet1!$B:$B,MATCH($D469,[2]Sheet1!$A:$A,0)),"Not found") -> Not found | N469: =IF($M469="Retail",1,0) -> 0 | O469: =IF($M469="Non-Retail",1,0) -> 0
A470: PEF | B470: 42644 | C470: 55153 | D470: Taaleri Tonttirahasto II Ky | E470: 22643277#035 | F470: 27821757 | G470: Non-UCITS | H470: Closed-end | I470: Kiinteistörahasto | J470: =IF(ISNUMBER(MATCH($D470,'Lopettaneet 2013->'!$D:$D,0)),INDEX('Lopettaneet 2013->'!$K:$K,MATCH($D470,'Lopettaneet 2013->'!$D:$D,0)),"Continues") -> Continues | K470: =IF($J470="Continues",DATEDIF($B470,TODAY(),"Y"),INDEX('Lopettaneet 2013->'!$L:$L,MATCH($D470,'Lopettaneet 2013->'!$D:$D,0))) -> 8 | L470: =IFERROR(INDEX('[1]30.06.2024'!$H:$H,MATCH($E470,'[1]30.06.2024'!$B:$B,0)),"Not found") -> Taaleri Pääomarahastot Oy | M470: =IFERROR(INDEX([2]Sheet1!$B:$B,MATCH($D470,[2]Sheet1!$A:$A,0)),"Not found") -> Retail | N470: =IF($M470="Retail",1,0) -> 1 | O470: =IF($M470="Non-Retail",1,0) -> 0
A471: PEF | B471: 42705 | C471: 55153 | D471: Taaleri Tonttirahasto II Syöttörahasto Ky | E471: 22643277#036 | F471: 27821714 | G471: Non-UCITS | H471: Closed-end | I471: Kiinteistörahasto | J471: =IF(ISNUMBER(MATCH($D471,'Lopettaneet 2013->'!$D:$D,0)),INDEX('Lopettaneet 2013->'!$K:$K,MATCH($D471,'Lopettaneet 2013->'!$D:$D,0)),"Continues") -> Continues | K471: =IF($J471="Continues",DATEDIF($B471,TODAY(),"Y"),INDEX('Lopettaneet 2013->'!$L:$L,MATCH($D471,'Lopettaneet 2013->'!$D:$D,0))) -> 8 | L471: =IFERROR(INDEX('[1]30.06.2024'!$H:$H,MATCH($E471,'[1]30.06.2024'!$B:$B,0)),"Not found") -> Taaleri Pääomarahastot Oy | M471: =IFERROR(INDEX([2]Sheet1!$B:$B,MATCH($D471,[2]Sheet1!$A:$A,0)),"Not found") -> Retail | N471: =IF($M471="Retail",1,0) -> 1 | O471: =IF($M471="Non-Retail",1,0) -> 0
A472: PEF | B472: 42644 | C472: 55153 | D472: Taaleri Tonttirahasto II Sijoittajat Ky | E472: 22643277#037 | F472: 27821722 | G472: Non-UCITS | H472: Closed-end | I472: Kiinteistörahasto | J472: =IF(ISNUMBER(MATCH($D472,'Lopettaneet 2013->'!$D:$D,0)),INDEX('Lopettaneet 2013->'!$K:$K,MATCH($D472,'Lopettaneet 2013->'!$D:$D,0)),"Continues") -> Continues | K472: =IF($J472="Continues",DATEDIF($B472,TODAY(),"Y"),INDEX('Lopettaneet 2013->'!$L:$L,MATCH($D472,'Lopettaneet 2013->'!$D:$D,0))) -> 8 | L472: =IFERROR(INDEX('[1]30.06.2024'!$H:$H,MATCH($E472,'[1]30.06.2024'!$B:$B,0)),"Not found") -> Taaleri Pääomarahastot Oy | M472: =IFERROR(INDEX([2]Sheet1!$B:$B,MATCH($D472,[2]Sheet1!$A:$A,0)),"Not found") -> Retail | N472: =IF($M472="Retail",1,0) -> 1 | O472: =IF($M472="Non-Retail",1,0) -> 0
A473: PEF | B473: 42644 | C473: 55153 | D473: Taaleri Tonttirahasto II Omistajat Ky | E473: 22643277#038 | F473: 27821706 | G473: Non-UCITS | H473: Closed-end | I473: Kiinteistörahasto | J473: =IF(ISNUMBER(MATCH($D473,'Lopettaneet 2013->'!$D:$D,0)),INDEX('Lopettaneet 2013->'!$K:$K,MATCH($D473,'Lopettaneet 2013->'!$D:$D,0)),"Continues") -> Continues | K473: =IF($J473="Continues",DATEDIF($B473,TODAY(),"Y"),INDEX('Lopettaneet 2013->'!$L:$L,MATCH($D473,'Lopettaneet 2013->'!$D:$D,0))) -> 8 | L473: =IFERROR(INDEX('[1]30.06.2024'!$H:$H,MATCH($E473,'[1]30.06.2024'!$B:$B,0)),"Not found") -> Taaleri Pääomarahastot Oy | M473: =IFERROR(INDEX([2]Sheet1!$B:$B,MATCH($D473,[2]Sheet1!$A:$A,0)),"Not found") -> Retail | N473: =IF($M473="Retail",1,0) -> 1 | O473: =IF($M473="Non-Retail",1,0) -> 0
A474: IVF | B474: 42705 | C474: 43830 | D474: Elite Alfred Berg Eurooppa Faktorit Sijoitusrahasto | E474: 21793994#041 | F474: 27943543 | G474: UCITS | H474: Open-end | I474: Osakerahasto | J474: =IF(ISNUMBER(MATCH($D474,'Lopettaneet 2013->'!$D:$D,0)),INDEX('Lopettaneet 2013->'!$K:$K,MATCH($D474,'Lopettaneet 2013->'!$D:$D,0)),"Continues") -> Merged | K474: =IF($J474="Continues",DATEDIF($B474,TODAY(),"Y"),INDEX('Lopettaneet 2013->'!$L:$L,MATCH($D474,'Lopettaneet 2013->'!$D:$D,0))) -> 3 | L474: =IFERROR(INDEX('[1]30.06.2024'!$H:$H,MATCH($E474,'[1]30.06.2024'!$B:$B,0)),"Not found") -> Not found | M474: =IFERROR(INDEX([2]Sheet1!$B:$B,MATCH($D474,[2]Sheet1!$A:$A,0)),"Not found") -> Not found | N474: =IF($M474="Retail",1,0) -> 0 | O474: =IF($M474="Non-Retail",1,0) -> 0
... A853: IVF | B853: 44075 | C853: 44712 | D853: Erikoissijoitusrahasto LähiTapiola Osaketähdet | E853: 16172050#029 | F853: 31403515 | G853: Non-UCITS | H853: Open-end | I853: Osakerahasto | J853: =IF(ISNUMBER(MATCH($D853,'Lopettaneet 2013->'!$D:$D,0)),INDEX('Lopettaneet 2013->'!$K:$K,MATCH($D853,'Lopettaneet 2013->'!$D:$D,0)),"Continues") -> Closed | K853: =IF($J853="Continues",DATEDIF($B853,TODAY(),"Y"),INDEX('Lopettaneet 2013->'!$L:$L,MATCH($D853,'Lopettaneet 2013->'!$D:$D,0))) -> 1 | L853: =IFERROR(INDEX('[1]30.06.2024'!$H:$H,MATCH($E853,'[1]30.06.2024'!$B:$B,0)),"Not found") -> Not found | M853: =IFERROR(INDEX([2]Sheet1!$B:$B,MATCH($D853,[2]Sheet1!$A:$A,0)),"Not found") -> Not found | N853: =IF($M853="Retail",1,0) -> 0 | O853: =IF($M853="Non-Retail",1,0) -> 0
A854: PEF | B854: 44896 | C854: 44926 | D854: Minoria Fund I Ky | E854: 31385118#001 | F854: NULL | G854: Non-UCITS | H854: Closed-end | I854: Buyout-rahasto | J854: =IF(ISNUMBER(MATCH($D854,'Lopettaneet 2013->'!$D:$D,0)),INDEX('Lopettaneet 2013->'!$K:$K,MATCH($D854,'Lopettaneet 2013->'!$D:$D,0)),"Continues") -> Closed | K854: =IF($J854="Continues",DATEDIF($B854,TODAY(),"Y"),INDEX('Lopettaneet 2013->'!$L:$L,MATCH($D854,'Lopettaneet 2013->'!$D:$D,0))) -> 0 | L854: =IFERROR(INDEX('[1]30.06.2024'!$H:$H,MATCH($E854,'[1]30.06.2024'!$B:$B,0)),"Not found") -> Not found | M854: =IFERROR(INDEX([2]Sheet1!$B:$B,MATCH($D854,[2]Sheet1!$A:$A,0)),"Not found") -> Not found | N854: =IF($M854="Retail",1,0) -> 0 | O854: =IF($M854="Non-Retail",1,0) -> 0
A855: PEF | B855: 44896 | C855: 44926 | D855: Minoria Feeder Fund I Ky | E855: 31385118#002 | F855: NULL | G855: Non-UCITS | H855: Closed-end | I855: Buyout-rahasto | J855: =IF(ISNUMBER(MATCH($D855,'Lopettaneet 2013->'!$D:$D,0)),INDEX('Lopettaneet 2013->'!$K:$K,MATCH($D855,'Lopettaneet 2013->'!$D:$D,0)),"Continues") -> Closed | K855: =IF($J855="Continues",DATEDIF($B855,TODAY(),"Y"),INDEX('Lopettaneet 2013->'!$L:$L,MATCH($D855,'Lopettaneet 2013->'!$D:$D,0))) -> 0 | L855: =IFERROR(INDEX('[1]30.06.2024'!$H:$H,MATCH($E855,'[1]30.06.2024'!$B:$B,0)),"Not found") -> Not found | M855: =IFERROR(INDEX([2]Sheet1!$B:$B,MATCH($D855,[2]Sheet1!$A:$A,0)),"Not found") -> Not found | N855: =IF($M855="Retail",1,0) -> 0 | O855: =IF($M855="Non-Retail",1,0) -> 0
A856: PEF | B856: 44348 | C856: 55153 | D856: North Karelia Growth Fund Ky | E856: 28619307#001 | F856: 31672934 | G856: Non-UCITS | H856: Closed-end | I856: Venture Capital -rahasto | J856: =IF(ISNUMBER(MATCH($D856,'Lopettaneet 2013->'!$D:$D,0)),INDEX('Lopettaneet 2013->'!$K:$K,MATCH($D856,'Lopettaneet 2013->'!$D:$D,0)),"Continues") -> Continues | K856: =IF($J856="Continues",DATEDIF($B856,TODAY(),"Y"),INDEX('Lopettaneet 2013->'!$L:$L,MATCH($D856,'Lopettaneet 2013->'!$D:$D,0))) -> 3 | L856: =IFERROR(INDEX('[1]30.06.2024'!$H:$H,MATCH($E856,'[1]30.06.2024'!$B:$B,0)),"Not found") -> Redstone Nordics Oy | M856: =IFERROR(INDEX([2]Sheet1!$B:$B,MATCH($D856,[2]Sheet1!$A:$A,0)),"Not found") -> Non-Retail | N856: =IF($M856="Retail",1,0) -> 0 | O856: =IF($M856="Non-Retail",1,0) -> 1
A857: PEF | B857: 44348 | C857: 55153 | D857: South Savo Growth Fund Ky | E857: 28619307#002 | F857: 31705994 | G857: Non-UCITS | H857: Closed-end | I857: Venture Capital -rahasto | J857: =IF(ISNUMBER(MATCH($D857,'Lopettaneet 2013->'!$D:$D,0)),INDEX('Lopettaneet 2013->'!$K:$K,MATCH($D857,'Lopettaneet 2013->'!$D:$D,0)),"Continues") -> Continues | K857: =IF($J857="Continues",DATEDIF($B857,TODAY(),"Y"),INDEX('Lopettaneet 2013->'!$L:$L,MATCH($D857,'Lopettaneet 2013->'!$D:$D,0))) -> 3 | L857: =IFERROR(INDEX('[1]30.06.2024'!$H:$H,MATCH($E857,'[1]30.06.2024'!$B:$B,0)),"Not found") -> Redstone Nordics Oy | M857: =IFERROR(INDEX([2]Sheet1!$B:$B,MATCH($D857,[2]Sheet1!$A:$A,0)),"Not found") -> Non-Retail | N857: =IF($M857="Retail",1,0) -> 0 | O857: =IF($M857="Non-Retail",1,0) -> 1
A858: PEF | B858: 44166 | C858: 55153 | D858: BOA Rantakäärme Ky | E858: 31225771#001 | F858: 31579078 | G858: Non-UCITS | H858: Closed-end | I858: Buyout-rahasto | J858: =IF(ISNUMBER(MATCH($D858,'Lopettaneet 2013->'!$D:$D,0)),INDEX('Lopettaneet 2013->'!$K:$K,MATCH($D858,'Lopettaneet 2013->'!$D:$D,0)),"Continues") -> Continues | K858: =IF($J858="Continues",DATEDIF($B858,TODAY(),"Y"),INDEX('Lopettaneet 2013->'!$L:$L,MATCH($D858,'Lopettaneet 2013->'!$D:$D,0))) -> 4 | L858: =IFERROR(INDEX('[1]30.06.2024'!$H:$H,MATCH($E858,'[1]30.06.2024'!$B:$B,0)),"Not found") -> BOA Capital Oy | M858: =IFERROR(INDEX([2]Sheet1!$B:$B,MATCH($D858,[2]Sheet1!$A:$A,0)),"Not found") -> Non-Retail | N858: =IF($M858="Retail",1,0) -> 0 | O858: =IF($M858="Non-Retail",1,0) -> 1
A859: IVF | B859: 44166 | C859: 55153 | D859: Erikoissijoitusrahasto Asilo Argo | E859: 21181015#047 | F859: 31548167 | G859: Non-UCITS | H859: Open-end | I859: Osakerahasto | J859: =IF(ISNUMBER(MATCH($D859,'Lopettaneet 2013->'!$D:$D,0)),INDEX('Lopettaneet 2013->'!$K:$K,MATCH($D859,'Lopettaneet 2013->'!$D:$D,0)),"Continues") -> Continues | K859: =IF($J859="Continues",DATEDIF($B859,TODAY(),"Y"),INDEX('Lopettaneet 2013->'!$L:$L,MATCH($D859,'Lopettaneet 2013->'!$D:$D,0))) -> 4 | L859: =IFERROR(INDEX('[1]30.06.2024'!$H:$H,MATCH($E859,'[1]30.06.2024'!$B:$B,0)),"Not found") -> UB Rahastoyhtiö Oy | M859: =IFERROR(INDEX([2]Sheet1!$B:$B,MATCH($D859,[2]Sheet1!$A:$A,0)),"Not found") -> Retail | N859: =IF($M859="Retail",1,0) -> 1 | O859: =IF($M859="Non-Retail",1,0) -> 0
A860: IVF | B860: 44166 | C860: 55153 | D860: Säästöpankki Kiinteistö –erikoissijoitusrahasto | E860: 17956316#037 | F860: 31182927 | G860: Non-UCITS | H860: Open-end | I860: Kiinteistörahasto | J860: =IF(ISNUMBER(MATCH($D860,'Lopettaneet 2013->'!$D:$D,0)),INDEX('Lopettaneet 2013->'!$K:$K,MATCH($D860,'Lopettaneet 2013->'!$D:$D,0)),"Continues") -> Continues | K860: =IF($J860="Continues",DATEDIF($B860,TODAY(),"Y"),INDEX('Lopettaneet 2013->'!$L:$L,MATCH($D860,'Lopettaneet 2013->'!$D:$D,0))) -> 4 | L860: =IFERROR(INDEX('[1]30.06.2024'!$H:$H,MATCH($E860,'[1]30.06.2024'!$B:$B,0)),"Not found") -> Sp-Rahastoyhtiö Oy | M860: =IFERROR(INDEX([2]Sheet1!$B:$B,MATCH($D860,[2]Sheet1!$A:$A,0)),"Not found") -> Retail | N860: =IF($M860="Retail",1,0) -> 1 | O860: =IF($M860="Non-Retail",1,0) -> 0
A861: PEF | B861: 44166 | C861: 55153 | D861: ICECAPITAL Housing Fund VI Ky | E861: 22032150#016 | F861: 31775036 | G861: Non-UCITS | H861: Closed-end | I861: Kiinteistörahasto | J861: =IF(ISNUMBER(MATCH($D861,'Lopettaneet 2013->'!$D:$D,0)),INDEX('Lopettaneet 2013->'!$K:$K,MATCH($D861,'Lopettaneet 2013->'!$D:$D,0)),"Continues") -> Continues | K861: =IF($J861="Continues",DATEDIF($B861,TODAY(),"Y"),INDEX('Lopettaneet 2013->'!$L:$L,MATCH($D861,'Lopettaneet 2013->'!$D:$D,0))) -> 4 | L861: =IFERROR(INDEX('[1]30.06.2024'!$H:$H,MATCH($E861,'[1]30.06.2024'!$B:$B,0)),"Not found") -> ICECAPITAL REAM Oy | M861: =IFERROR(INDEX([2]Sheet1!$B:$B,MATCH($D861,[2]Sheet1!$A:$A,0)),"Not found") -> Retail | N861: =IF($M861="Retail",1,0) -> 1 | O861: =IF($M861="Non-Retail",1,0) -> 0
A862: PEF | B862: 44166 | C862: 55153 | D862: IC Housing Feeder VI Ky | E862: 22032150#017 | F862: 31773647 | G862: Non-UCITS | H862: Closed-end | I862: Kiinteistörahasto | J862: =IF(ISNUMBER(MATCH($D862,'Lopettaneet 2013->'!$D:$D,0)),INDEX('Lopettaneet 2013->'!$K:$K,MATCH($D862,'Lopettaneet 2013->'!$D:$D,0)),"Continues") -> Continues | K862: =IF($J862="Continues",DATEDIF($B862,TODAY(),"Y"),INDEX('Lopettaneet 2013->'!$L:$L,MATCH($D862,'Lopettaneet 2013->'!$D:$D,0))) -> 4 | L862: =IFERROR(INDEX('[1]30.06.2024'!$H:$H,MATCH($E862,'[1]30.06.2024'!$B:$B,0)),"Not found") -> ICECAPITAL REAM Oy | M862: =IFERROR(INDEX([2]Sheet1!$B:$B,MATCH($D862,[2]Sheet1!$A:$A,0)),"Not found") -> Retail | N862: =IF($M862="Retail",1,0) -> 1 | O862: =IF($M862="Non-Retail",1,0) -> 0
A863: IVF | B863: 44136 | C863: 55153 | D863: Erikoissijoitusrahasto Obsido Global Balanced | E863: 28233658#007 | F863: 31638568 | G863: Non-UCITS | H863: Open-end | I863: Yhdistelmärahasto | J863: =IF(ISNUMBER(MATCH($D863,'Lopettaneet 2013->'!$D:$D,0)),INDEX('Lopettaneet 2013->'!$K:$K,MATCH($D863,'Lopettaneet 2013->'!$D:$D,0)),"Continues") -> Continues | K863: =IF($J863="Continues",DATEDIF($B863,TODAY(),"Y"),INDEX('Lopettaneet 2013->'!$L:$L,MATCH($D863,'Lopettaneet 2013->'!$D:$D,0))) -> 4 | L863: =IFERROR(INDEX('[1]30.06.2024'!$H:$H,MATCH($E863,'[1]30.06.2024'!$B:$B,0)),"Not found") -> Obsido Rahastoyhtiö Oy | M863: =IFERROR(INDEX([2]Sheet1!$B:$B,MATCH($D863,[2]Sheet1!$A:$A,0)),"Not found") -> Retail | N863: =IF($M863="Retail",1,0) -> 1 | O863: =IF($M863="Non-Retail",1,0) -> 0
A864: IVF | B864: 44136 | C864: 55153 | D864: Erikoissijoitusrahasto Obsido Global Aggressive | E864: 28233658#008 | F864: 31638576 | G864: Non-UCITS | H864: Open-end | I864: Osakerahasto | J864: =IF(ISNUMBER(MATCH($D864,'Lopettaneet 2013->'!$D:$D,0)),INDEX('Lopettaneet 2013->'!$K:$K,MATCH($D864,'Lopettaneet 2013->'!$D:$D,0)),"Continues") -> Continues | K864: =IF($J864="Continues",DATEDIF($B864,TODAY(),"Y"),INDEX('Lopettaneet 2013->'!$L:$L,MATCH($D864,'Lopettaneet 2013->'!$D:$D,0))) -> 4 | L864: =IFERROR(INDEX('[1]30.06.2024'!$H:$H,MATCH($E864,'[1]30.06.2024'!$B:$B,0)),"Not found") -> Obsido Rahastoyhtiö Oy | M864: =IFERROR(INDEX([2]Sheet1!$B:$B,MATCH($D864,[2]Sheet1!$A:$A,0)),"Not found") -> Retail | N864: =IF($M864="Retail",1,0) -> 1 | O864: =IF($M864="Non-Retail",1,0) -> 0
A865: PEF | B865: 44348 | C865: 55153 | D865: Evli Impact Forest Fund I Ky | E865: 07446590#106 | F865: 31670437 | G865: Non-UCITS | H865: Closed-end | I865: Muu rahasto | J865: =IF(ISNUMBER(MATCH($D865,'Lopettaneet 2013->'!$D:$D,0)),INDEX('Lopettaneet 2013->'!$K:$K,MATCH($D865,'Lopettaneet 2013->'!$D:$D,0)),"Continues") -> Continues | K865: =IF($J865="Continues",DATEDIF($B865,TODAY(),"Y"),INDEX('Lopettaneet 2013->'!$L:$L,MATCH($D865,'Lopettaneet 2013->'!$D:$D,0))) -> 3 | L865: =IFERROR(INDEX('[1]30.06.2024'!$H:$H,MATCH($E865,'[1]30.06.2024'!$B:$B,0)),"Not found") -> Evli-Rahastoyhtiö Oy | M865: =IFERROR(INDEX([2]Sheet1!$B:$B,MATCH($D865,[2]Sheet1!$A:$A,0)),"Not found") -> Retail | N865: =IF($M865="Retail",1,0) -> 1 | O865: =IF($M865="Non-Retail",1,0) -> 0
A866: PEF | B866: 44348 | C866: 55153 | D866: Evli Impact Forest I Feeder A Ky | E866: 07446590#107 | F866: 31670429 | G866: Non-UCITS | H866: Closed-end | I866: Muu rahasto | J866: =IF(ISNUMBER(MATCH($D866,'Lopettaneet 2013->'!$D:$D,0)),INDEX('Lopettaneet 2013->'!$K:$K,MATCH($D866,'Lopettaneet 2013->'!$D:$D,0)),"Continues") -> Continues | K866: =IF($J866="Continues",DATEDIF($B866,TODAY(),"Y"),INDEX('Lopettaneet 2013->'!$L:$L,MATCH($D866,'Lopettaneet 2013->'!$D:$D,0))) -> 3 | L866: =IFERROR(INDEX('[1]30.06.2024'!$H:$H,MATCH($E866,'[1]30.06.2024'!$B:$B,0)),"Not found") -> Evli-Rahastoyhtiö Oy | M866: =IFERROR(INDEX([2]Sheet1!$B:$B,MATCH($D866,[2]Sheet1!$A:$A,0)),"Not found") -> Retail | N866: =IF($M866="Retail",1,0) -> 1 | O866: =IF($M866="Non-Retail",1,0) -> 0
A867: PEF | B867: 44256 | C867: 55153 | D867: Eduimpact Fund Feeder II Ky | E867: 28665274#003 | F867: 31587246 | G867: Non-UCITS | H867: Closed-end | I867: Venture Capital -rahasto | J867: =IF(ISNUMBER(MATCH($D867,'Lopettaneet 2013->'!$D:$D,0)),INDEX('Lopettaneet 2013->'!$K:$K,MATCH($D867,'Lopettaneet 2013->'!$D:$D,0)),"Continues") -> Continues | K867: =IF($J867="Continues",DATEDIF($B867,TODAY(),"Y"),INDEX('Lopettaneet 2013->'!$L:$L,MATCH($D867,'Lopettaneet 2013->'!$D:$D,0))) -> 4 | L867: =IFERROR(INDEX('[1]30.06.2024'!$H:$H,MATCH($E867,'[1]30.06.2024'!$B:$B,0)),"Not found") -> EduImpact Venture Capital Oy | M867: =IFERROR(INDEX([2]Sheet1!$B:$B,MATCH($D867,[2]Sheet1!$A:$A,0)),"Not found") -> Retail | N867: =IF($M867="Retail",1,0) -> 1 | O867: =IF($M867="Non-Retail",1,0) -> 0
... A1105: IVF | B1105: 45383 | C1105: 55153 | D1105: Forea Korkosijoitukset Plus Erikoissijoitusrahasto | E1105: 18300220#043 | F1105: 34298204 | G1105: Non-UCITS | H1105: Open-end | I1105: Korkorahasto | J1105: =IF(ISNUMBER(MATCH($D1105,'Lopettaneet 2013->'!$D:$D,0)),INDEX('Lopettaneet 2013->'!$K:$K,MATCH($D1105,'Lopettaneet 2013->'!$D:$D,0)),"Continues") -> Continues | K1105: =IF($J1105="Continues",DATEDIF($B1105,TODAY(),"Y"),INDEX('Lopettaneet 2013->'!$L:$L,MATCH($D1105,'Lopettaneet 2013->'!$D:$D,0))) -> 1 | L1105: =IFERROR(INDEX('[1]30.06.2024'!$H:$H,MATCH($E1105,'[1]30.06.2024'!$B:$B,0)),"Not found") -> GRIT Rahastoyhtiö Oy | M1105: =IFERROR(INDEX([2]Sheet1!$B:$B,MATCH($D1105,[2]Sheet1!$A:$A,0)),"Not found") -> Not found | N1105: =IF($M1105="Retail",1,0) -> 0 | O1105: =IF($M1105="Non-Retail",1,0) -> 0
A1106: IVF | B1106: 45413 | C1106: 55153 | D1106: OP-Kestävä Yrityslaina -sijoitusrahasto | E1106: 07439622#153 | F1106: NULL | G1106: UCITS | H1106: Open-end | I1106: Korkorahasto | J1106: =IF(ISNUMBER(MATCH($D1106,'Lopettaneet 2013->'!$D:$D,0)),INDEX('Lopettaneet 2013->'!$K:$K,MATCH($D1106,'Lopettaneet 2013->'!$D:$D,0)),"Continues") -> Continues | K1106: =IF($J1106="Continues",DATEDIF($B1106,TODAY(),"Y"),INDEX('Lopettaneet 2013->'!$L:$L,MATCH($D1106,'Lopettaneet 2013->'!$D:$D,0))) -> 1 | L1106: =IFERROR(INDEX('[3]30.09.2024'!$H:$H,MATCH($E1106,'[3]30.09.2024'!$B:$B,0)),"Not found") -> OP-Rahastoyhtiö Oy | M1106: =IFERROR(INDEX([2]Sheet1!$B:$B,MATCH($D1106,[2]Sheet1!$A:$A,0)),"Not found") -> Not found | N1106: =IF($M1106="Retail",1,0) -> 0 | O1106: =IF($M1106="Non-Retail",1,0) -> 0
A1107: PEF | B1107: 45536 | C1107: 55153 | D1107: Suomen Kuntakiinteistöt 1 Ky | E1107: 31336148#001 | F1107: 31975142 | G1107: Non-UCITS | H1107: Closed-end | I1107: Kiinteistörahasto | J1107: =IF(ISNUMBER(MATCH($D1107,'Lopettaneet 2013->'!$D:$D,0)),INDEX('Lopettaneet 2013->'!$K:$K,MATCH($D1107,'Lopettaneet 2013->'!$D:$D,0)),"Continues") -> Continues | K1107: =IF($J1107="Continues",DATEDIF($B1107,TODAY(),"Y"),INDEX('Lopettaneet 2013->'!$L:$L,MATCH($D1107,'Lopettaneet 2013->'!$D:$D,0))) -> 0 | L1107: =IFERROR(INDEX('[3]30.09.2024'!$H:$H,MATCH($E1107,'[3]30.09.2024'!$B:$B,0)),"Not found") -> YKS Management Oy | M1107: =IFERROR(INDEX([2]Sheet1!$B:$B,MATCH($D1107,[2]Sheet1!$A:$A,0)),"Not found") -> Not found | N1107: =IF($M1107="Retail",1,0) -> 0 | O1107: =IF($M1107="Non-Retail",1,0) -> 0
A1108: PEF | B1108: 45536 | C1108: 55153 | D1108: Equilibrium Fund A Ky | E1108: 32660863#001 | F1108: 34084265 | G1108: Non-UCITS | H1108: Closed-end | I1108: Muu rahasto | J1108: =IF(ISNUMBER(MATCH($D1108,'Lopettaneet 2013->'!$D:$D,0)),INDEX('Lopettaneet 2013->'!$K:$K,MATCH($D1108,'Lopettaneet 2013->'!$D:$D,0)),"Continues") -> Continues | K1108: =IF($J1108="Continues",DATEDIF($B1108,TODAY(),"Y"),INDEX('Lopettaneet 2013->'!$L:$L,MATCH($D1108,'Lopettaneet 2013->'!$D:$D,0))) -> 0 | L1108: =IFERROR(INDEX('[3]30.09.2024'!$H:$H,MATCH($E1108,'[3]30.09.2024'!$B:$B,0)),"Not found") -> Equilibrium Funds Oy | M1108: =IFERROR(INDEX([2]Sheet1!$B:$B,MATCH($D1108,[2]Sheet1!$A:$A,0)),"Not found") -> Not found | N1108: =IF($M1108="Retail",1,0) -> 0 | O1108: =IF($M1108="Non-Retail",1,0) -> 0
A1109: IVF | B1109: 45536 | C1109: 55153 | D1109: Placeringsfond Nordea Stabile Aksjer Global Valutasikret | E1109: 17377859#260 | F1109: 34111323 | G1109: UCITS | H1109: Open-end | I1109: Osakerahasto | J1109: =IF(ISNUMBER(MATCH($D1109,'Lopettaneet 2013->'!$D:$D,0)),INDEX('Lopettaneet 2013->'!$K:$K,MATCH($D1109,'Lopettaneet 2013->'!$D:$D,0)),"Continues") -> Continues | K1109: =IF($J1109="Continues",DATEDIF($B1109,TODAY(),"Y"),INDEX('Lopettaneet 2013->'!$L:$L,MATCH($D1109,'Lopettaneet 2013->'!$D:$D,0))) -> 0 | L1109: =IFERROR(INDEX('[3]30.09.2024'!$H:$H,MATCH($E1109,'[3]30.09.2024'!$B:$B,0)),"Not found") -> Nordea Funds Oy | M1109: =IFERROR(INDEX([2]Sheet1!$B:$B,MATCH($D1109,[2]Sheet1!$A:$A,0)),"Not found") -> Not found | N1109: =IF($M1109="Retail",1,0) -> 0 | O1109: =IF($M1109="Non-Retail",1,0) -> 0
A1110: IVF | B1110: 45536 | C1110: 55153 | D1110: Placeringsfond Nordea Stabile Aksjer Global | E1110: 17377859#261 | F1110: 34111454 | G1110: UCITS | H1110: Open-end | I1110: Osakerahasto | J1110: =IF(ISNUMBER(MATCH($D1110,'Lopettaneet 2013->'!$D:$D,0)),INDEX('Lopettaneet 2013->'!$K:$K,MATCH($D1110,'Lopettaneet 2013->'!$D:$D,0)),"Continues") -> Continues | K1110: =IF($J1110="Continues",DATEDIF($B1110,TODAY(),"Y"),INDEX('Lopettaneet 2013->'!$L:$L,MATCH($D1110,'Lopettaneet 2013->'!$D:$D,0))) -> 0 | L1110: =IFERROR(INDEX('[3]30.09.2024'!$H:$H,MATCH($E1110,'[3]30.09.2024'!$B:$B,0)),"Not found") -> Nordea Funds Oy | M1110: =IFERROR(INDEX([2]Sheet1!$B:$B,MATCH($D1110,[2]Sheet1!$A:$A,0)),"Not found") -> Not found | N1110: =IF($M1110="Retail",1,0) -> 0 | O1110: =IF($M1110="Non-Retail",1,0) -> 0
A1111: IVF | B1111: 45536 | C1111: 55153 | D1111: Placeringsfond Nordea Norge Verdi | E1111: 17377859#262 | F1111: 34111446 | G1111: UCITS | H1111: Open-end | I1111: Osakerahasto | J1111: =IF(ISNUMBER(MATCH($D1111,'Lopettaneet 2013->'!$D:$D,0)),INDEX('Lopettaneet 2013->'!$K:$K,MATCH($D1111,'Lopettaneet 2013->'!$D:$D,0)),"Continues") -> Continues | K1111: =IF($J1111="Continues",DATEDIF($B1111,TODAY(),"Y"),INDEX('Lopettaneet 2013->'!$L:$L,MATCH($D1111,'Lopettaneet 2013->'!$D:$D,0))) -> 0 | L1111: =IFERROR(INDEX('[3]30.09.2024'!$H:$H,MATCH($E1111,'[3]30.09.2024'!$B:$B,0)),"Not found") -> Nordea Funds Oy | M1111: =IFERROR(INDEX([2]Sheet1!$B:$B,MATCH($D1111,[2]Sheet1!$A:$A,0)),"Not found") -> Not found | N1111: =IF($M1111="Retail",1,0) -> 0 | O1111: =IF($M1111="Non-Retail",1,0) -> 0
A1112: IVF | B1112: 45536 | C1112: 55153 | D1112: Placeringsfond Nordea Kort Obligasjon | E1112: 17377859#264 | F1112: 34111411 | G1112: UCITS | H1112: Open-end | I1112: Korkorahasto | J1112: =IF(ISNUMBER(MATCH($D1112,'Lopettaneet 2013->'!$D:$D,0)),INDEX('Lopettaneet 2013->'!$K:$K,MATCH($D1112,'Lopettaneet 2013->'!$D:$D,0)),"Continues") -> Continues | K1112: =IF($J1112="Continues",DATEDIF($B1112,TODAY(),"Y"),INDEX('Lopettaneet 2013->'!$L:$L,MATCH($D1112,'Lopettaneet 2013->'!$D:$D,0))) -> 0 | L1112: =IFERROR(INDEX('[3]30.09.2024'!$H:$H,MATCH($E1112,'[3]30.09.2024'!$B:$B,0)),"Not found") -> Nordea Funds Oy | M1112: =IFERROR(INDEX([2]Sheet1!$B:$B,MATCH($D1112,[2]Sheet1!$A:$A,0)),"Not found") -> Not found | N1112: =IF($M1112="Retail",1,0) -> 0 | O1112: =IF($M1112="Non-Retail",1,0) -> 0
A1113: IVF | B1113: 45536 | C1113: 55153 | D1113: Placeringsfond Nordea Plan Konservativ | E1113: 17377859#269 | F1113: 34111403 | G1113: UCITS | H1113: Open-end | I1113: Yhdistelmärahasto | J1113: =IF(ISNUMBER(MATCH($D1113,'Lopettaneet 2013->'!$D:$D,0)),INDEX('Lopettaneet 2013->'!$K:$K,MATCH($D1113,'Lopettaneet 2013->'!$D:$D,0)),"Continues") -> Continues | K1113: =IF($J1113="Continues",DATEDIF($B1113,TODAY(),"Y"),INDEX('Lopettaneet 2013->'!$L:$L,MATCH($D1113,'Lopettaneet 2013->'!$D:$D,0))) -> 0 | L1113: =IFERROR(INDEX('[3]30.09.2024'!$H:$H,MATCH($E1113,'[3]30.09.2024'!$B:$B,0)),"Not found") -> Nordea Funds Oy | M1113: =IFERROR(INDEX([2]Sheet1!$B:$B,MATCH($D1113,[2]Sheet1!$A:$A,0)),"Not found") -> Not found | N1113: =IF($M1113="Retail",1,0) -> 0 | O1113: =IF($M1113="Non-Retail",1,0) -> 0
A1114: IVF | B1114: 45536 | C1114: 55153 | D1114: Placeringsfond Nordea Plan Moderat | E1114: 17377859#270 | F1114: 34111577 | G1114: UCITS | H1114: Open-end | I1114: Yhdistelmärahasto | J1114: =IF(ISNUMBER(MATCH($D1114,'Lopettaneet 2013->'!$D:$D,0)),INDEX('Lopettaneet 2013->'!$K:$K,MATCH($D1114,'Lopettaneet 2013->'!$D:$D,0)),"Continues") -> Continues | K1114: =IF($J1114="Continues",DATEDIF($B1114,TODAY(),"Y"),INDEX('Lopettaneet 2013->'!$L:$L,MATCH($D1114,'Lopettaneet 2013->'!$D:$D,0))) -> 0 | L1114: =IFERROR(INDEX('[3]30.09.2024'!$H:$H,MATCH($E1114,'[3]30.09.2024'!$B:$B,0)),"Not found") -> Nordea Funds Oy | M1114: =IFERROR(INDEX([2]Sheet1!$B:$B,MATCH($D1114,[2]Sheet1!$A:$A,0)),"Not found") -> Not found | N1114: =IF($M1114="Retail",1,0) -> 0 | O1114: =IF($M1114="Non-Retail",1,0) -> 0
A1115: IVF | B1115: 45536 | C1115: 55153 | D1115: Placeringsfond Nordea Plan Balansert | E1115: 17377859#271 | F1115: 34111374 | G1115: UCITS | H1115: Open-end | I1115: Yhdistelmärahasto | J1115: =IF(ISNUMBER(MATCH($D1115,'Lopettaneet 2013->'!$D:$D,0)),INDEX('Lopettaneet 2013->'!$K:$K,MATCH($D1115,'Lopettaneet 2013->'!$D:$D,0)),"Continues") -> Continues | K1115: =IF($J1115="Continues",DATEDIF($B1115,TODAY(),"Y"),INDEX('Lopettaneet 2013->'!$L:$L,MATCH($D1115,'Lopettaneet 2013->'!$D:$D,0))) -> 0 | L1115: =IFERROR(INDEX('[3]30.09.2024'!$H:$H,MATCH($E1115,'[3]30.09.2024'!$B:$B,0)),"Not found") -> Nordea Funds Oy | M1115: =IFERROR(INDEX([2]Sheet1!$B:$B,MATCH($D1115,[2]Sheet1!$A:$A,0)),"Not found") -> Not found | N1115: =IF($M1115="Retail",1,0) -> 0 | O1115: =IF($M1115="Non-Retail",1,0) -> 0
A1116: IVF | B1116: 45536 | C1116: 55153 | D1116: Placeringsfond Nordea Plan Vekstorientert | E1116: 17377859#272 | F1116: 34111331 | G1116: UCITS | H1116: Open-end | I1116: Yhdistelmärahasto | J1116: =IF(ISNUMBER(MATCH($D1116,'Lopettaneet 2013->'!$D:$D,0)),INDEX('Lopettaneet 2013->'!$K:$K,MATCH($D1116,'Lopettaneet 2013->'!$D:$D,0)),"Continues") -> Continues | K1116: =IF($J1116="Continues",DATEDIF($B1116,TODAY(),"Y"),INDEX('Lopettaneet 2013->'!$L:$L,MATCH($D1116,'Lopettaneet 2013->'!$D:$D,0))) -> 0 | L1116: =IFERROR(INDEX('[3]30.09.2024'!$H:$H,MATCH($E1116,'[3]30.09.2024'!$B:$B,0)),"Not found") -> Nordea Funds Oy | M1116: =IFERROR(INDEX([2]Sheet1!$B:$B,MATCH($D1116,[2]Sheet1!$A:$A,0)),"Not found") -> Not found | N1116: =IF($M1116="Retail",1,0) -> 0 | O1116: =IF($M1116="Non-Retail",1,0) -> 0
A1117: IVF | B1117: 45536 | C1117: 55153 | D1117: Placeringsfond Nordea Plan Offensiv | E1117: 17377859#273 | F1117: 34111366 | G1117: UCITS | H1117: Open-end | I1117: Yhdistelmärahasto | J1117: =IF(ISNUMBER(MATCH($D1117,'Lopettaneet 2013->'!$D:$D,0)),INDEX('Lopettaneet 2013->'!$K:$K,MATCH($D1117,'Lopettaneet 2013->'!$D:$D,0)),"Continues") -> Continues | K1117: =IF($J1117="Continues",DATEDIF($B1117,TODAY(),"Y"),INDEX('Lopettaneet 2013->'!$L:$L,MATCH($D1117,'Lopettaneet 2013->'!$D:$D,0))) -> 0 | L1117: =IFERROR(INDEX('[3]30.09.2024'!$H:$H,MATCH($E1117,'[3]30.09.2024'!$B:$B,0)),"Not found") -> Nordea Funds Oy | M1117: =IFERROR(INDEX([2]Sheet1!$B:$B,MATCH($D1117,[2]Sheet1!$A:$A,0)),"Not found") -> Not found | N1117: =IF($M1117="Retail",1,0) -> 0 | O1117: =IF($M1117="Non-Retail",1,0) -> 0
A1118: PEF | B1118: 45536 | C1118: 55153 | D1118: Superhero Venture Fund 2024 Ky | E1118: 26963091#005 | F1118: 34637413 | G1118: Non-UCITS | H1118: Closed-end | I1118: Venture Capital -rahasto | J1118: =IF(ISNUMBER(MATCH($D1118,'Lopettaneet 2013->'!$D:$D,0)),INDEX('Lopettaneet 2013->'!$K:$K,MATCH($D1118,'Lopettaneet 2013->'!$D:$D,0)),"Continues") -> Continues | K1118: =IF($J1118="Continues",DATEDIF($B1118,TODAY(),"Y"),INDEX('Lopettaneet 2013->'!$L:$L,MATCH($D1118,'Lopettaneet 2013->'!$D:$D,0))) -> 0 | L1118: =IFERROR(INDEX('[3]30.09.2024'!$H:$H,MATCH($E1118,'[3]30.09.2024'!$B:$B,0)),"Not found") -> Superhero Capital Oy | M1118: =IFERROR(INDEX([2]Sheet1!$B:$B,MATCH($D1118,[2]Sheet1!$A:$A,0)),"Not found") -> Not found | N1118: =IF($M1118="Retail",1,0) -> 0 | O1118: =IF($M1118="Non-Retail",1,0) -> 0
... A1133: IVF | B1133: 45536 | C1133: 55153 | D1133: Alexandria Pääomasijoitukset Erikoissijoitusrahasto | E1133: 16039364#013 | F1133: 34595946 | G1133: Non-UCITS | H1133: Open-end | I1133: Muu rahasto | J1133: =IF(ISNUMBER(MATCH($D1133,'Lopettaneet 2013->'!$D:$D,0)),INDEX('Lopettaneet 2013->'!$K:$K,MATCH($D1133,'Lopettaneet 2013->'!$D:$D,0)),"Continues") -> Continues | K1133: =IF($J1133="Continues",DATEDIF($B1133,TODAY(),"Y"),INDEX('Lopettaneet 2013->'!$L:$L,MATCH($D1133,'Lopettaneet 2013->'!$D:$D,0))) -> 0 | L1133: =IFERROR(INDEX('[3]30.09.2024'!$H:$H,MATCH($E1133,'[3]30.09.2024'!$B:$B,0)),"Not found") -> Alexandria Rahastoyhtiö Oy | M1133: =IFERROR(INDEX([2]Sheet1!$B:$B,MATCH($D1133,[2]Sheet1!$A:$A,0)),"Not found") -> Not found | N1133: =IF($M1133="Retail",1,0) -> 0 | O1133: =IF($M1133="Non-Retail",1,0) -> 0
A1134: PEF | B1134: 45627 | C1134: 55153 | D1134: BOA Kyy Ky | E1134: 31225771#002 | F1134: NULL | G1134: Non-UCITS | H1134: Closed-end | I1134: Buyout-rahasto | J1134: =IF(ISNUMBER(MATCH($D1134,'Lopettaneet 2013->'!$D:$D,0)),INDEX('Lopettaneet 2013->'!$K:$K,MATCH($D1134,'Lopettaneet 2013->'!$D:$D,0)),"Continues") -> Continues | K1134: =IF($J1134="Continues",DATEDIF($B1134,TODAY(),"Y"),INDEX('Lopettaneet 2013->'!$L:$L,MATCH($D1134,'Lopettaneet 2013->'!$D:$D,0))) -> 0 | L1134: =IFERROR(INDEX('[3]30.09.2024'!$H:$H,MATCH($E1134,'[3]30.09.2024'!$B:$B,0)),"Not found") -> BOA Capital Oy | M1134: =IFERROR(INDEX([2]Sheet1!$B:$B,MATCH($D1134,[2]Sheet1!$A:$A,0)),"Not found") -> Not found | N1134: =IF($M1134="Retail",1,0) -> 0 | O1134: =IF($M1134="Non-Retail",1,0) -> 0
...

Sheet Lopettaneet 2013->
A1: Kysely | B1: RaportoinninAloitusPvm | C1: RaportoinninLopetusPvm | D1: Raportoija | E1: RaportoijanRahastotunnus | F1: YksikkoId | G1: Y_tunnus | H1: UCITS_erikoissijoitusrahastotyyppi | I1: Pääomanvaihtelevuus | J1: Rahastotyyppi | K1: Status | L1: Elinaika (y) | M1: Hallinnointiyhtiö | N1: AIF | O1: AIF - retail | P1: AIF - non-retail
A2: PEF | B2: 41974 | C2: 43100 | D2: Oy Wedeco Ab | E2: 15318791#001 | F2: 7218 | G2: 6798092 | H2: Non-UCITS | I2: Closed-end | J2: Buyout-rahasto | K2: Closed | L2: =IF($K2="Continues",DATEDIF($B2,TODAY(),"Y"),DATEDIF($B2,$C2,"Y")) -> 3 | M2: =IFERROR(INDEX('[4]31.03.2024'!$H:$H,MATCH($E2,'[4]31.03.2024'!$B:$B,0)),"Not found") -> Not found | N2: =IFERROR(INDEX([2]Sheet1!$B:$B,MATCH($D2,[2]Sheet1!$A:$A,0)),"Not found") -> Not found | O2: =IF($N2="Retail",1,0) -> 0 | P2: =IF($N2="Non-Retail",1,0) -> 0
A3: PEF | B3: 41974 | C3: 42735 | D3: Finnventure Rahasto V Ky | E3: 07490276#006 | F3: 8486 | G3: 15657523 | H3: Non-UCITS | I3: Closed-end | J3: Buyout-rahasto | K3: Closed | L3: =IF($K3="Continues",DATEDIF($B3,TODAY(),"Y"),DATEDIF($B3,$C3,"Y")) -> 2 | M3: =IFERROR(INDEX('[4]31.03.2024'!$H:$H,MATCH($E3,'[4]31.03.2024'!$B:$B,0)),"Not found") -> Not found | N3: =IFERROR(INDEX([2]Sheet1!$B:$B,MATCH($D3,[2]Sheet1!$A:$A,0)),"Not found") -> Not found | O3: =IF($N3="Retail",1,0) -> 0 | P3: =IF($N3="Non-Retail",1,0) -> 0
A4: PEF | B4: 41974 | C4: 42369 | D4: Maneq Fund 2002 Ky | E4: 19011500#009 | F4: 10400 | G4: 17285698 | H4: Non-UCITS | I4: Closed-end | J4: Buyout-rahasto | K4: Closed | L4: =IF($K4="Continues",DATEDIF($B4,TODAY(),"Y"),DATEDIF($B4,$C4,"Y")) -> 1 | M4: =IFERROR(INDEX('[4]31.03.2024'!$H:$H,MATCH($E4,'[4]31.03.2024'!$B:$B,0)),"Not found") -> Not found | N4: =IFERROR(INDEX([2]Sheet1!$B:$B,MATCH($D4,[2]Sheet1!$A:$A,0)),"Not found") -> Not found | O4: =IF($N4="Retail",1,0) -> 0 | P4: =IF($N4="Non-Retail",1,0) -> 0
A5: PEF | B5: 41974 | C5: 43738 | D5: Finnmezzanine Rahasto III A Ky | E5: 07490276#008 | F5: 10402 | G5: 16020110 | H5: Non-UCITS | I5: Closed-end | J5: Buyout-rahasto | K5: Closed | L5: =IF($K5="Continues",DATEDIF($B5,TODAY(),"Y"),DATEDIF($B5,$C5,"Y")) -> 4 | M5: =IFERROR(INDEX('[4]31.03.2024'!$H:$H,MATCH($E5,'[4]31.03.2024'!$B:$B,0)),"Not found") -> Not found | N5: =IFERROR(INDEX([2]Sheet1!$B:$B,MATCH($D5,[2]Sheet1!$A:$A,0)),"Not found") -> Not found | O5: =IF($N5="Retail",1,0) -> 0 | P5: =IF($N5="Non-Retail",1,0) -> 0
A6: PEF | B6: 41974 | C6: 42369 | D6: Finnmezzanine Rahasto III C Ky | E6: 07490276#011 | F6: 10403 | G6: 16069002 | H6: Non-UCITS | I6: Closed-end | J6: Buyout-rahasto | K6: Closed | L6: =IF($K6="Continues",DATEDIF($B6,TODAY(),"Y"),DATEDIF($B6,$C6,"Y")) -> 1 | M6: =IFERROR(INDEX('[4]31.03.2024'!$H:$H,MATCH($E6,'[4]31.03.2024'!$B:$B,0)),"Not found") -> Not found | N6: =IFERROR(INDEX([2]Sheet1!$B:$B,MATCH($D6,[2]Sheet1!$A:$A,0)),"Not found") -> Not found | O6: =IF($N6="Retail",1,0) -> 0 | P6: =IF($N6="Non-Retail",1,0) -> 0
A7: PEF | B7: 41974 | C7: 43738 | D7: Finnmezzanine Rahasto III B Ky | E7: 07490276#009 | F7: 11037 | G7: 16020137 | H7: Non-UCITS | I7: Closed-end | J7: Buyout-rahasto | K7: Closed | L7: =IF($K7="Continues",DATEDIF($B7,TODAY(),"Y"),DATEDIF($B7,$C7,"Y")) -> 4 | M7: =IFERROR(INDEX('[4]31.03.2024'!$H:$H,MATCH($E7,'[4]31.03.2024'!$B:$B,0)),"Not found") -> Not found | N7: =IFERROR(INDEX([2]Sheet1!$B:$B,MATCH($D7,[2]Sheet1!$A:$A,0)),"Not found") -> Not found | O7: =IF($N7="Retail",1,0) -> 0 | P7: =IF($N7="Non-Retail",1,0) -> 0
A8: PEF | B8: 41974 | C8: 44196 | D8: CapMan Real Estate I Ky | E8: 07491762#001 | F8: 11685 | G8: 19720366 | H8: Non-UCITS | I8: Closed-end | J8: Kiinteistörahasto | K8: Closed | L8: =IF($K8="Continues",DATEDIF($B8,TODAY(),"Y"),DATEDIF($B8,$C8,"Y")) -> 6 | M8: =IFERROR(INDEX('[4]31.03.2024'!$H:$H,MATCH($E8,'[4]31.03.2024'!$B:$B,0)),"Not found") -> Not found | N8: =IFERROR(INDEX([2]Sheet1!$B:$B,MATCH($D8,[2]Sheet1!$A:$A,0)),"Not found") -> Not found | O8: =IF($N8="Retail",1,0) -> 0 | P8: =IF($N8="Non-Retail",1,0) -> 0
A9: PEF | B9: 39783 | C9: 43496 | D9: Placeringsfond SEB Money Manager | E9: 08151401#010 | F9: 11716 | G9: 18799199 | H9: UCITS | I9: Open-end | J9: Rahamarkkinarahasto | K9: Merged | L9: =IF($K9="Continues",DATEDIF($B9,TODAY(),"Y"),DATEDIF($B9,$C9,"Y")) -> 10 | M9: =IFERROR(INDEX('[4]31.03.2024'!$H:$H,MATCH($E9,'[4]31.03.2024'!$B:$B,0)),"Not found") -> Not found | N9: =IFERROR(INDEX([2]Sheet1!$B:$B,MATCH($D9,[2]Sheet1!$A:$A,0)),"Not found") -> Not found | O9: =IF($N9="Retail",1,0) -> 0 | P9: =IF($N9="Non-Retail",1,0) -> 0
A10: MMF | B10: 39783 | C10: 43465 | D10: OP-Euro -sijoitusrahasto | E10: 07439622#016 | F10: 11719 | G10: 11024008 | H10: UCITS | I10: Open-end | J10: Korkorahasto | K10: Closed | L10: =IF($K10="Continues",DATEDIF($B10,TODAY(),"Y"),DATEDIF($B10,$C10,"Y")) -> 10 | M10: =IFERROR(INDEX('[4]31.03.2024'!$H:$H,MATCH($E10,'[4]31.03.2024'!$B:$B,0)),"Not found") -> OP-Rahastoyhtiö Oy | N10: =IFERROR(INDEX([2]Sheet1!$B:$B,MATCH($D10,[2]Sheet1!$A:$A,0)),"Not found") -> Retail | O10: =IF($N10="Retail",1,0) -> 1 | P10: =IF($N10="Non-Retail",1,0) -> 0
A11: MMF | B11: 41122 | C11: 43465 | D11: S-Pankki Lyhyt Korko Sijoitusrahasto | E11: 09791339#004 | F11: 11721 | G11: 20667232 | H11: UCITS | I11: Open-end | J11: Korkorahasto | K11: Closed | L11: =IF($K11="Continues",DATEDIF($B11,TODAY(),"Y"),DATEDIF($B11,$C11,"Y")) -> 6 | M11: =IFERROR(INDEX('[4]31.03.2024'!$H:$H,MATCH($E11,'[4]31.03.2024'!$B:$B,0)),"Not found") -> S-Pankki Rahastoyhtiö Oy | N11: =IFERROR(INDEX([2]Sheet1!$B:$B,MATCH($D11,[2]Sheet1!$A:$A,0)),"Not found") -> Retail | O11: =IF($N11="Retail",1,0) -> 1 | P11: =IF($N11="Non-Retail",1,0) -> 0
A12: MMF | B12: 39783 | C12: 40908 | D12: Placeringsfonden Handelsbanken Euroränta | E12: 11050193#004 | F12: 11723 | G12: 18694434 | H12: UCITS | I12: Open-end | J12: Korkorahasto | K12: Closed | L12: =IF($K12="Continues",DATEDIF($B12,TODAY(),"Y"),DATEDIF($B12,$C12,"Y")) -> 3 | M12: =IFERROR(INDEX('[4]31.03.2024'!$H:$H,MATCH($E12,'[4]31.03.2024'!$B:$B,0)),"Not found") -> Not found | N12: =IFERROR(INDEX([2]Sheet1!$B:$B,MATCH($D12,[2]Sheet1!$A:$A,0)),"Not found") -> Not found | O12: =IF($N12="Retail",1,0) -> 0 | P12: =IF($N12="Non-Retail",1,0) -> 0
A13: MMF | B13: 40909 | C13: 41912 | D13: Placeringsfonden Handelsbanken Euroränta | E13: 11050193#004 | F13: 11723 | G13: 18694434 | H13: UCITS | I13: Open-end | J13: Korkorahasto | K13: Closed | L13: =IF($K13="Continues",DATEDIF($B13,TODAY(),"Y"),DATEDIF($B13,$C13,"Y")) -> 2 | M13: =IFERROR(INDEX('[4]31.03.2024'!$H:$H,MATCH($E13,'[4]31.03.2024'!$B:$B,0)),"Not found") -> Not found | N13: =IFERROR(INDEX([2]Sheet1!$B:$B,MATCH($D13,[2]Sheet1!$A:$A,0)),"Not found") -> Not found | O13: =IF($N13="Retail",1,0) -> 0 | P13: =IF($N13="Non-Retail",1,0) -> 0
A14: MMF | B14: 39783 | C14: 42277 | D14: Sijoitusrahasto Alfred Berg Korko | E14: 09137804#012 | F14: 11727 | G14: 18665836 | H14: UCITS | I14: Open-end | J14: Rahamarkkinarahasto | K14: Merged | L14: =IF($K14="Continues",DATEDIF($B14,TODAY(),"Y"),DATEDIF($B14,$C14,"Y")) -> 6 | M14: =IFERROR(INDEX('[4]31.03.2024'!$H:$H,MATCH($E14,'[4]31.03.2024'!$B:$B,0)),"Not found") -> Not found | N14: =IFERROR(INDEX([2]Sheet1!$B:$B,MATCH($D14,[2]Sheet1!$A:$A,0)),"Not found") -> Not found | O14: =IF($N14="Retail",1,0) -> 0 | P14: =IF($N14="Non-Retail",1,0) -> 0
A15: MMF | B15: 39783 | C15: 40908 | D15: Placeringsfond SEB Likviditetsfond | E15: 08151401#019 | F15: 11734 | G15: NULL | H15: UCITS | I15: Open-end | J15: Korkorahasto | K15: Closed | L15: =IF($K15="Continues",DATEDIF($B15,TODAY(),"Y"),DATEDIF($B15,$C15,"Y")) -> 3 | M15: =IFERROR(INDEX('[4]31.03.2024'!$H:$H,MATCH($E15,'[4]31.03.2024'!$B:$B,0)),"Not found") -> Not found | N15: =IFERROR(INDEX([2]Sheet1!$B:$B,MATCH($D15,[2]Sheet1!$A:$A,0)),"Not found") -> Not found | O15: =IF($N15="Retail",1,0) -> 0 | P15: =IF($N15="Non-Retail",1,0) -> 0
A16: MMF | B16: 40909 | C16: 42704 | D16: Placeringsfond SEB Likviditetsfond | E16: 08151401#019 | F16: 11734 | G16: NULL | H16: UCITS | I16: Open-end | J16: Korkorahasto | K16: Closed | L16: =IF($K16="Continues",DATEDIF($B16,TODAY(),"Y"),DATEDIF($B16,$C16,"Y")) -> 4 | M16: =IFERROR(INDEX('[4]31.03.2024'!$H:$H,MATCH($E16,'[4]31.03.2024'!$B:$B,0)),"Not found") -> Not found | N16: =IFERROR(INDEX([2]Sheet1!$B:$B,MATCH($D16,[2]Sheet1!$A:$A,0)),"Not found") -> Not found | O16: =IF($N16="Retail",1,0) -> 0 | P16: =IF($N16="Non-Retail",1,0) -> 0
A17: MMF | B17: 41974 | C17: 44469 | D17: Veraventure Oy | E17: 08425222#002 | F17: 12364 | G17: 8425222 | H17: Non-UCITS | I17: Closed-end | J17: Venture Capital -rahasto | K17: Closed | L17: =IF($K17="Continues",DATEDIF($B17,TODAY(),"Y"),DATEDIF($B17,$C17,"Y")) -> 6 | M17: =IFERROR(INDEX('[4]31.03.2024'!$H:$H,MATCH($E17,'[4]31.03.2024'!$B:$B,0)),"Not found") -> Not found | N17: =IFERROR(INDEX([2]Sheet1!$B:$B,MATCH($D17,[2]Sheet1!$A:$A,0)),"Not found") -> Not found | O17: =IF($N17="Retail",1,0) -> 0 | P17: =IF($N17="Non-Retail",1,0) -> 0
A18: MMF | B18: 41974 | C18: 43100 | D18: Aloitusrahasto Vera Oy | E18: 08425222#001 | F18: 12372 | G18: 8425142 | H18: Non-UCITS | I18: Closed-end | J18: Venture Capital -rahasto | K18: Closed | L18: =IF($K18="Continues",DATEDIF($B18,TODAY(),"Y"),DATEDIF($B18,$C18,"Y")) -> 3 | M18: =IFERROR(INDEX('[4]31.03.2024'!$H:$H,MATCH($E18,'[4]31.03.2024'!$B:$B,0)),"Not found") -> Not found | N18: =IFERROR(INDEX([2]Sheet1!$B:$B,MATCH($D18,[2]Sheet1!$A:$A,0)),"Not found") -> Not found | O18: =IF($N18="Retail",1,0) -> 0 | P18: =IF($N18="Non-Retail",1,0) -> 0
A19: IVF | B19: 39783 | C19: 41608 | D19: Sijoitusrahasto eQ Lyhyt Rahamarkkinarahasto | E19: 07360527#057 | F19: 12424 | G19: 22343899 | H19: UCITS | I19: Open-end | J19: Rahamarkkinarahasto | K19: Merged | L19: =IF($K19="Continues",DATEDIF($B19,TODAY(),"Y"),DATEDIF($B19,$C19,"Y")) -> 4 | M19: =IFERROR(INDEX('[4]31.03.2024'!$H:$H,MATCH($E19,'[4]31.03.2024'!$B:$B,0)),"Not found") -> Not found | N19: =IFERROR(INDEX([2]Sheet1!$B:$B,MATCH($D19,[2]Sheet1!$A:$A,0)),"Not found") -> Not found | O19: =IF($N19="Retail",1,0) -> 0 | P19: =IF($N19="Non-Retail",1,0) -> 0
A20: MMF | B20: 39783 | C20: 40908 | D20: Placeringsfond SEB Euro Short Rate | E20: 08151401#024 | F20: 12425 | G20: 21644729 | H20: UCITS | I20: Open-end | J20: Korkorahasto | K20: Closed | L20: =IF($K20="Continues",DATEDIF($B20,TODAY(),"Y"),DATEDIF($B20,$C20,"Y")) -> 3 | M20: =IFERROR(INDEX('[4]31.03.2024'!$H:$H,MATCH($E20,'[4]31.03.2024'!$B:$B,0)),"Not found") -> Not found | N20: =IFERROR(INDEX([2]Sheet1!$B:$B,MATCH($D20,[2]Sheet1!$A:$A,0)),"Not found") -> Not found | O20: =IF($N20="Retail",1,0) -> 0 | P20: =IF($N20="Non-Retail",1,0) -> 0
A21: MMF | B21: 40909 | C21: 44712 | D21: Placeringsfond SEB Euro Short Rate | E21: 08151401#024 | F21: 12425 | G21: 21644729 | H21: UCITS | I21: Open-end | J21: Korkorahasto | K21: Closed | L21: =IF($K21="Continues",DATEDIF($B21,TODAY(),"Y"),DATEDIF($B21,$C21,"Y")) -> 10 | M21: =IFERROR(INDEX('[4]31.03.2024'!$H:$H,MATCH($E21,'[4]31.03.2024'!$B:$B,0)),"Not found") -> Not found | N21: =IFERROR(INDEX([2]Sheet1!$B:$B,MATCH($D21,[2]Sheet1!$A:$A,0)),"Not found") -> Not found | O21: =IF($N21="Retail",1,0) -> 0 | P21: =IF($N21="Non-Retail",1,0) -> 0
A22: MMF | B22: 39783 | C22: 40908 | D22: Sijoitusrahasto LähiTapiola Kassakorko | E22: 09791339#058 | F22: 12555 | G22: 21869143 | H22: UCITS | I22: Open-end | J22: Rahamarkkinarahasto | K22: Merged | L22: =IF($K22="Continues",DATEDIF($B22,TODAY(),"Y"),DATEDIF($B22,$C22,"Y")) -> 3 | M22: =IFERROR(INDEX('[4]31.03.2024'!$H:$H,MATCH($E22,'[4]31.03.2024'!$B:$B,0)),"Not found") -> Not found | N22: =IFERROR(INDEX([2]Sheet1!$B:$B,MATCH($D22,[2]Sheet1!$A:$A,0)),"Not found") -> Not found | O22: =IF($N22="Retail",1,0) -> 0 | P22: =IF($N22="Non-Retail",1,0) -> 0
A23: IVF | B23: 40909 | C23: 41121 | D23: Sijoitusrahasto LähiTapiola Kassakorko | E23: 09791339#058 | F23: 12555 | G23: 21869143 | H23: UCITS | I23: Open-end | J23: Rahamarkkinarahasto | K23: Merged | L23: =IF($K23="Continues",DATEDIF($B23,TODAY(),"Y"),DATEDIF($B23,$C23,"Y")) -> 0 | M23: =IFERROR(INDEX('[4]31.03.2024'!$H:$H,MATCH($E23,'[4]31.03.2024'!$B:$B,0)),"Not found") -> Not found | N23: =IFERROR(INDEX([2]Sheet1!$B:$B,MATCH($D23,[2]Sheet1!$A:$A,0)),"Not found") -> Not found | O23: =IF($N23="Retail",1,0) -> 0 | P23: =IF($N23="Non-Retail",1,0) -> 0
A24: PEF | B24: 41122 | C24: 43008 | D24: Sijoitusrahasto LähiTapiola Kassakorko | E24: 09791339#058 | F24: 12555 | G24: 21869143 | H24: UCITS | I24: Open-end | J24: Rahamarkkinarahasto | K24: Merged | L24: =IF($K24="Continues",DATEDIF($B24,TODAY(),"Y"),DATEDIF($B24,$C24,"Y")) -> 5 | M24: =IFERROR(INDEX('[4]31.03.2024'!$H:$H,MATCH($E24,'[4]31.03.2024'!$B:$B,0)),"Not found") -> Not found | N24: =IFERROR(INDEX([2]Sheet1!$B:$B,MATCH($D24,[2]Sheet1!$A:$A,0)),"Not found") -> Not found | O24: =IF($N24="Retail",1,0) -> 0 | P24: =IF($N24="Non-Retail",1,0) -> 0
A25: PEF | B25: 39783 | C25: 43465 | D25: Sijoitusrahasto eQ Lyhyt Korko | E25: 07360527#007 | F25: 12933 | G25: 18001415 | H25: UCITS | I25: Open-end | J25: Korkorahasto | K25: Closed | L25: =IF($K25="Continues",DATEDIF($B25,TODAY(),"Y"),DATEDIF($B25,$C25,"Y")) -> 10 | M25: =IFERROR(INDEX('[4]31.03.2024'!$H:$H,MATCH($E25,'[4]31.03.2024'!$B:$B,0)),"Not found") -> eQ Rahastoyhtiö Oy | N25: =IFERROR(INDEX([2]Sheet1!$B:$B,MATCH($D25,[2]Sheet1!$A:$A,0)),"Not found") -> Retail | O25: =IF($N25="Retail",1,0) -> 1 | P25: =IF($N25="Non-Retail",1,0) -> 0
A26: PEF | B26: 39783 | C26: 43404 | D26: Sijoitusrahasto Danske Invest Rahamarkkina | E26: 06716026#098 | F26: 12936 | G26: 21305882 | H26: UCITS | I26: Open-end | J26: Rahamarkkinarahasto | K26: Merged | L26: =IF($K26="Continues",DATEDIF($B26,TODAY(),"Y"),DATEDIF($B26,$C26,"Y")) -> 9 | M26: =IFERROR(INDEX('[4]31.03.2024'!$H:$H,MATCH($E26,'[4]31.03.2024'!$B:$B,0)),"Not found") -> Not found | N26: =IFERROR(INDEX([2]Sheet1!$B:$B,MATCH($D26,[2]Sheet1!$A:$A,0)),"Not found") -> Not found | O26: =IF($N26="Retail",1,0) -> 0 | P26: =IF($N26="Non-Retail",1,0) -> 0
A27: MMF | B27: 39783 | C27: 44926 | D27: Elite Alfred Berg Suomi Fokus Sijoitusrahasto | E27: 07446590#129 | F27: 12965 | G27: 18665983 | H27: UCITS | I27: Open-end | J27: Osakerahasto | K27: Merged | L27: =IF($K27="Continues",DATEDIF($B27,TODAY(),"Y"),DATEDIF($B27,$C27,"Y")) -> 14 | M27: =IFERROR(INDEX('[4]31.03.2024'!$H:$H,MATCH($E27,'[4]31.03.2024'!$B:$B,0)),"Not found") -> Not found | N27: =IFERROR(INDEX([2]Sheet1!$B:$B,MATCH($D27,[2]Sheet1!$A:$A,0)),"Not found") -> Not found | O27: =IF($N27="Retail",1,0) -> 0 | P27: =IF($N27="Non-Retail",1,0) -> 0
A28: MMF | B28: 39783 | C28: 42277 | D28: Sijoitusrahasto Alfred Berg Obligaatio | E28: 09137804#003 | F28: 12966 | G28: 18665852 | H28: UCITS | I28: Open-end | J28: Korkorahasto | K28: Merged | L28: =IF($K28="Continues",DATEDIF($B28,TODAY(),"Y"),DATEDIF($B28,$C28,"Y")) -> 6 | M28: =IFERROR(INDEX('[4]31.03.2024'!$H:$H,MATCH($E28,'[4]31.03.2024'!$B:$B,0)),"Not found") -> Not found | N28: =IFERROR(INDEX([2]Sheet1!$B:$B,MATCH($D28,[2]Sheet1!$A:$A,0)),"Not found") -> Not found | O28: =IF($N28="Retail",1,0) -> 0 | P28: =IF($N28="Non-Retail",1,0) -> 0
... A425: IVF | B425: 41974 | C425: 42460 | D425: EPI Baltic I Oy | E425: 19331184#002 | F425: 24506 | G425: 19488085 | H425: Non-UCITS | I425: Closed-end | J425: Kiinteistörahasto | K425: Closed | L425: =IF($K425="Continues",DATEDIF($B425,TODAY(),"Y"),DATEDIF($B425,$C425,"Y")) -> 1 | M425: =IFERROR(INDEX('[4]31.03.2024'!$H:$H,MATCH($E425,'[4]31.03.2024'!$B:$B,0)),"Not found") -> Not found | N425: =IFERROR(INDEX([2]Sheet1!$B:$B,MATCH($D425,[2]Sheet1!$A:$A,0)),"Not found") -> Not found | O425: =IF($N425="Retail",1,0) -> 0 | P425: =IF($N425="Non-Retail",1,0) -> 0
A426: IVF | B426: 41974 | C426: 43100 | D426: MultiFire | E426: 19208258#001 | F426: 24507 | G426: NULL | H426: Non-UCITS | I426: Closed-end | J426: Hedge-rahasto | K426: Closed | L426: =IF($K426="Continues",DATEDIF($B426,TODAY(),"Y"),DATEDIF($B426,$C426,"Y")) -> 3 | M426: =IFERROR(INDEX('[4]31.03.2024'!$H:$H,MATCH($E426,'[4]31.03.2024'!$B:$B,0)),"Not found") -> Not found | N426: =IFERROR(INDEX([2]Sheet1!$B:$B,MATCH($D426,[2]Sheet1!$A:$A,0)),"Not found") -> Not found | O426: =IF($N426="Retail",1,0) -> 0 | P426: =IF($N426="Non-Retail",1,0) -> 0
A427: IVF | B427: 41974 | C427: 43373 | D427: Maneq Fund 2004 Ky | E427: 19011500#008 | F427: 24508 | G427: 18634351 | H427: Non-UCITS | I427: Closed-end | J427: Buyout-rahasto | K427: Closed | L427: =IF($K427="Continues",DATEDIF($B427,TODAY(),"Y"),DATEDIF($B427,$C427,"Y")) -> 3 | M427: =IFERROR(INDEX('[4]31.03.2024'!$H:$H,MATCH($E427,'[4]31.03.2024'!$B:$B,0)),"Not found") -> Not found | N427: =IFERROR(INDEX([2]Sheet1!$B:$B,MATCH($D427,[2]Sheet1!$A:$A,0)),"Not found") -> Not found | O427: =IF($N427="Retail",1,0) -> 0 | P427: =IF($N427="Non-Retail",1,0) -> 0
A428: IVF | B428: 41974 | C428: 43646 | D428: TuuliTapiola Ky | E428: 16172050#002 | F428: 24511 | G428: 20748876 | H428: Non-UCITS | I428: Closed-end | J428: Venture Capital -rahasto | K428: Closed | L428: =IF($K428="Continues",DATEDIF($B428,TODAY(),"Y"),DATEDIF($B428,$C428,"Y")) -> 4 | M428: =IFERROR(INDEX('[4]31.03.2024'!$H:$H,MATCH($E428,'[4]31.03.2024'!$B:$B,0)),"Not found") -> Not found | N428: =IFERROR(INDEX([2]Sheet1!$B:$B,MATCH($D428,[2]Sheet1!$A:$A,0)),"Not found") -> Not found | O428: =IF($N428="Retail",1,0) -> 0 | P428: =IF($N428="Non-Retail",1,0) -> 0
A429: IVF | B429: 41974 | C429: 42735 | D429: Rival 10 Invest Oy | E429: 16105296#001 | F429: 24513 | G429: 24297267 | H429: Non-UCITS | I429: Closed-end | J429: Venture Capital -rahasto | K429: Closed | L429: =IF($K429="Continues",DATEDIF($B429,TODAY(),"Y"),DATEDIF($B429,$C429,"Y")) -> 2 | M429: =IFERROR(INDEX('[4]31.03.2024'!$H:$H,MATCH($E429,'[4]31.03.2024'!$B:$B,0)),"Not found") -> Not found | N429: =IFERROR(INDEX([2]Sheet1!$B:$B,MATCH($D429,[2]Sheet1!$A:$A,0)),"Not found") -> Not found | O429: =IF($N429="Retail",1,0) -> 0 | P429: =IF($N429="Non-Retail",1,0) -> 0
A430: IVF | B430: 41974 | C430: 42369 | D430: Rival VIII Invest Oy | E430: 16105296#002 | F430: 24515 | G430: 23591261 | H430: Non-UCITS | I430: Closed-end | J430: Venture Capital -rahasto | K430: Closed | L430: =IF($K430="Continues",DATEDIF($B430,TODAY(),"Y"),DATEDIF($B430,$C430,"Y")) -> 1 | M430: =IFERROR(INDEX('[4]31.03.2024'!$H:$H,MATCH($E430,'[4]31.03.2024'!$B:$B,0)),"Not found") -> Not found | N430: =IFERROR(INDEX([2]Sheet1!$B:$B,MATCH($D430,[2]Sheet1!$A:$A,0)),"Not found") -> Not found | O430: =IF($N430="Retail",1,0) -> 0 | P430: =IF($N430="Non-Retail",1,0) -> 0
A431: IVF | B431: 41974 | C431: 43100 | D431: Rival XIV Invest Oy | E431: 16105296#003 | F431: 24516 | G431: 25429196 | H431: Non-UCITS | I431: Closed-end | J431: Venture Capital -rahasto | K431: Closed | L431: =IF($K431="Continues",DATEDIF($B431,TODAY(),"Y"),DATEDIF($B431,$C431,"Y")) -> 3 | M431: =IFERROR(INDEX('[4]31.03.2024'!$H:$H,MATCH($E431,'[4]31.03.2024'!$B:$B,0)),"Not found") -> Not found | N431: =IFERROR(INDEX([2]Sheet1!$B:$B,MATCH($D431,[2]Sheet1!$A:$A,0)),"Not found") -> Not found | O431: =IF($N431="Retail",1,0) -> 0 | P431: =IF($N431="Non-Retail",1,0) -> 0
A432: IVF | B432: 41974 | C432: 44742 | D432: Rival XV Invest Oy | E432: 16105296#004 | F432: 24517 | G432: 25510867 | H432: Non-UCITS | I432: Closed-end | J432: Buyout-rahasto | K432: Closed | L432: =IF($K432="Continues",DATEDIF($B432,TODAY(),"Y"),DATEDIF($B432,$C432,"Y")) -> 7 | M432: =IFERROR(INDEX('[4]31.03.2024'!$H:$H,MATCH($E432,'[4]31.03.2024'!$B:$B,0)),"Not found") -> Not found | N432: =IFERROR(INDEX([2]Sheet1!$B:$B,MATCH($D432,[2]Sheet1!$A:$A,0)),"Not found") -> Not found | O432: =IF($N432="Retail",1,0) -> 0 | P432: =IF($N432="Non-Retail",1,0) -> 0
A433: IVF | B433: 41974 | C433: 43008 | D433: Ursula Invest Oy | E433: 16105296#005 | F433: 24518 | G433: 20487880 | H433: Non-UCITS | I433: Closed-end | J433: Venture Capital -rahasto | K433: Closed | L433: =IF($K433="Continues",DATEDIF($B433,TODAY(),"Y"),DATEDIF($B433,$C433,"Y")) -> 2 | M433: =IFERROR(INDEX('[4]31.03.2024'!$H:$H,MATCH($E433,'[4]31.03.2024'!$B:$B,0)),"Not found") -> Not found | N433: =IFERROR(INDEX([2]Sheet1!$B:$B,MATCH($D433,[2]Sheet1!$A:$A,0)),"Not found") -> Not found | O433: =IF($N433="Retail",1,0) -> 0 | P433: =IF($N433="Non-Retail",1,0) -> 0
A434: IVF | B434: 41974 | C434: 42369 | D434: Rival IX Invest Oy | E434: 16105296#006 | F434: 24519 | G434: 24006669 | H434: Non-UCITS | I434: Closed-end | J434: Venture Capital -rahasto | K434: Closed | L434: =IF($K434="Continues",DATEDIF($B434,TODAY(),"Y"),DATEDIF($B434,$C434,"Y")) -> 1 | M434: =IFERROR(INDEX('[4]31.03.2024'!$H:$H,MATCH($E434,'[4]31.03.2024'!$B:$B,0)),"Not found") -> Not found | N434: =IFERROR(INDEX([2]Sheet1!$B:$B,MATCH($D434,[2]Sheet1!$A:$A,0)),"Not found") -> Not found | O434: =IF($N434="Retail",1,0) -> 0 | P434: =IF($N434="Non-Retail",1,0) -> 0
A435: IVF | B435: 41974 | C435: 42735 | D435: Rival XII Invest Oy | E435: 16105296#007 | F435: 24520 | G435: 24636791 | H435: Non-UCITS | I435: Closed-end | J435: Venture Capital -rahasto | K435: Closed | L435: =IF($K435="Continues",DATEDIF($B435,TODAY(),"Y"),DATEDIF($B435,$C435,"Y")) -> 2 | M435: =IFERROR(INDEX('[4]31.03.2024'!$H:$H,MATCH($E435,'[4]31.03.2024'!$B:$B,0)),"Not found") -> Not found | N435: =IFERROR(INDEX([2]Sheet1!$B:$B,MATCH($D435,[2]Sheet1!$A:$A,0)),"Not found") -> Not found | O435: =IF($N435="Retail",1,0) -> 0 | P435: =IF($N435="Non-Retail",1,0) -> 0
A436: IVF | B436: 41974 | C436: 42369 | D436: Rival XIII Invest Oy | E436: 16105296#008 | F436: 24521 | G436: 25153847 | H436: Non-UCITS | I436: Closed-end | J436: Venture Capital -rahasto | K436: Closed | L436: =IF($K436="Continues",DATEDIF($B436,TODAY(),"Y"),DATEDIF($B436,$C436,"Y")) -> 1 | M436: =IFERROR(INDEX('[4]31.03.2024'!$H:$H,MATCH($E436,'[4]31.03.2024'!$B:$B,0)),"Not found") -> Not found | N436: =IFERROR(INDEX([2]Sheet1!$B:$B,MATCH($D436,[2]Sheet1!$A:$A,0)),"Not found") -> Not found | O436: =IF($N436="Retail",1,0) -> 0 | P436: =IF($N436="Non-Retail",1,0) -> 0
A437: IVF | B437: 41974 | C437: 42369 | D437: Rival VII Invest Oy | E437: 16105296#009 | F437: 24522 | G437: 23236024 | H437: Non-UCITS | I437: Closed-end | J437: Venture Capital -rahasto | K437: Closed | L437: =IF($K437="Continues",DATEDIF($B437,TODAY(),"Y"),DATEDIF($B437,$C437,"Y")) -> 1 | M437: =IFERROR(INDEX('[4]31.03.2024'!$H:$H,MATCH($E437,'[4]31.03.2024'!$B:$B,0)),"Not found") -> Not found | N437: =IFERROR(INDEX([2]Sheet1!$B:$B,MATCH($D437,[2]Sheet1!$A:$A,0)),"Not found") -> Not found | O437: =IF($N437="Retail",1,0) -> 0 | P437: =IF($N437="Non-Retail",1,0) -> 0
A438: IVF | B438: 41974 | C438: 42369 | D438: Rival VI Invest Oy | E438: 22895490#003 | F438: 24523 | G438: 23236067 | H438: Non-UCITS | I438: Closed-end | J438: Venture Capital -rahasto | K438: Closed | L438: =IF($K438="Continues",DATEDIF($B438,TODAY(),"Y"),DATEDIF($B438,$C438,"Y")) -> 1 | M438: =IFERROR(INDEX('[4]31.03.2024'!$H:$H,MATCH($E438,'[4]31.03.2024'!$B:$B,0)),"Not found") -> Not found | N438: =IFERROR(INDEX([2]Sheet1!$B:$B,MATCH($D438,[2]Sheet1!$A:$A,0)),"Not found") -> Not found | O438: =IF($N438="Retail",1,0) -> 0 | P438: =IF($N438="Non-Retail",1,0) -> 0
... A458: IVF | B458: 42186 | C458: 42551 | D458: MedTECH Rahasto Pre-Exit Ky | E458: 20831856#002 | F458: 25525 | G458: 26783525 | H458: Non-UCITS | I458: Closed-end | J458: Venture Capital -rahasto | K458: Closed | L458: =IF($K458="Continues",DATEDIF($B458,TODAY(),"Y"),DATEDIF($B458,$C458,"Y")) -> 0 | M458: =IFERROR(INDEX('[4]31.03.2024'!$H:$H,MATCH($E458,'[4]31.03.2024'!$B:$B,0)),"Not found") -> Not found | N458: =IFERROR(INDEX([2]Sheet1!$B:$B,MATCH($D458,[2]Sheet1!$A:$A,0)),"Not found") -> Not found | O458: =IF($N458="Retail",1,0) -> 0 | P458: =IF($N458="Non-Retail",1,0) -> 0
A459: IVF | B459: 42186 | C459: 42521 | D459: Posse Fund I Ky | E459: 26593748#001 | F459: 25527 | G459: NULL | H459: Non-UCITS | I459: Closed-end | J459: Venture Capital -rahasto | K459: Closed | L459: =IF($K459="Continues",DATEDIF($B459,TODAY(),"Y"),DATEDIF($B459,$C459,"Y")) -> 0 | M459: =IFERROR(INDEX('[4]31.03.2024'!$H:$H,MATCH($E459,'[4]31.03.2024'!$B:$B,0)),"Not found") -> Not found | N459: =IFERROR(INDEX([2]Sheet1!$B:$B,MATCH($D459,[2]Sheet1!$A:$A,0)),"Not found") -> Not found | O459: =IF($N459="Retail",1,0) -> 0 | P459: =IF($N459="Non-Retail",1,0) -> 0
A460: IVF | B460: 42248 | C460: 43434 | D460: Ålandsbanken Kort Ränta SEK Placeringsfond | E460: 14713626#028 | F460: 25598 | G460: 27068806 | H460: UCITS | I460: Open-end | J460: Korkorahasto | K460: Merged | L460: =IF($K460="Continues",DATEDIF($B460,TODAY(),"Y"),DATEDIF($B460,$C460,"Y")) -> 3 | M460: =IFERROR(INDEX('[4]31.03.2024'!$H:$H,MATCH($E460,'[4]31.03.2024'!$B:$B,0)),"Not found") -> Not found | N460: =IFERROR(INDEX([2]Sheet1!$B:$B,MATCH($D460,[2]Sheet1!$A:$A,0)),"Not found") -> Not found | O460: =IF($N460="Retail",1,0) -> 0 | P460: =IF($N460="Non-Retail",1,0) -> 0
A461: IVF | B461: 42309 | C461: 43404 | D461: Ålandsbanken Obligation Sverige Placeringsfond | E461: 14713626#029 | F461: 25599 | G461: 27068865 | H461: UCITS | I461: Open-end | J461: Korkorahasto | K461: Merged | L461: =IF($K461="Continues",DATEDIF($B461,TODAY(),"Y"),DATEDIF($B461,$C461,"Y")) -> 2 | M461: =IFERROR(INDEX('[4]31.03.2024'!$H:$H,MATCH($E461,'[4]31.03.2024'!$B:$B,0)),"Not found") -> Not found | N461: =IFERROR(INDEX([2]Sheet1!$B:$B,MATCH($D461,[2]Sheet1!$A:$A,0)),"Not found") -> Not found | O461: =IF($N461="Retail",1,0) -> 0 | P461: =IF($N461="Non-Retail",1,0) -> 0
A462: IVF | B462: 42248 | C462: 44742 | D462: Rival Alternative Invest Ky | E462: 16105296#010 | F462: 25685 | G462: 27117241 | H462: Non-UCITS | I462: Closed-end | J462: Buyout-rahasto | K462: Closed | L462: =IF($K462="Continues",DATEDIF($B462,TODAY(),"Y"),DATEDIF($B462,$C462,"Y")) -> 6 | M462: =IFERROR(INDEX('[4]31.03.2024'!$H:$H,MATCH($E462,'[4]31.03.2024'!$B:$B,0)),"Not found") -> Not found | N462: =IFERROR(INDEX([2]Sheet1!$B:$B,MATCH($D462,[2]Sheet1!$A:$A,0)),"Not found") -> Not found | O462: =IF($N462="Retail",1,0) -> 0 | P462: =IF($N462="Non-Retail",1,0) -> 0
A463: IVF | B463: 42278 | C463: 43830 | D463: ICON Real Estate Fund III - Suurpelto Ky (hoitaminen ja markkinointi kielletty 17.12.2019) | E463: 25361865#002 | F463: 25941 | G463: 26570757 | H463: Non-UCITS | I463: Closed-end | J463: Kiinteistörahasto | K463: Closed | L463: =IF($K463="Continues",DATEDIF($B463,TODAY(),"Y"),DATEDIF($B463,$C463,"Y")) -> 4 | M463: =IFERROR(INDEX('[4]31.03.2024'!$H:$H,MATCH($E463,'[4]31.03.2024'!$B:$B,0)),"Not found") -> Not found | N463: =IFERROR(INDEX([2]Sheet1!$B:$B,MATCH($D463,[2]Sheet1!$A:$A,0)),"Not found") -> Not found | O463: =IF($N463="Retail",1,0) -> 0 | P463: =IF($N463="Non-Retail",1,0) -> 0
A464: IVF | B464: 42278 | C464: 44742 | D464: Midinvest Fund III Ky | E464: 16447843#008 | F464: 25953 | G464: NULL | H464: Non-UCITS | I464: Closed-end | J464: Buyout-rahasto | K464: Closed | L464: =IF($K464="Continues",DATEDIF($B464,TODAY(),"Y"),DATEDIF($B464,$C464,"Y")) -> 6 | M464: =IFERROR(INDEX('[4]31.03.2024'!$H:$H,MATCH($E464,'[4]31.03.2024'!$B:$B,0)),"Not found") -> Not found | N464: =IFERROR(INDEX([2]Sheet1!$B:$B,MATCH($D464,[2]Sheet1!$A:$A,0)),"Not found") -> Not found | O464: =IF($N464="Retail",1,0) -> 0 | P464: =IF($N464="Non-Retail",1,0) -> 0
A465: IVF | B465: 42064 | C465: 43465 | D465: BPT Healthcare II Feeder A Ky | E465: 25870598#003 | F465: 26014 | G465: 25878223 | H465: Non-UCITS | I465: Closed-end | J465: Kiinteistörahasto | K465: Closed | L465: =IF($K465="Continues",DATEDIF($B465,TODAY(),"Y"),DATEDIF($B465,$C465,"Y")) -> 3 | M465: =IFERROR(INDEX('[4]31.03.2024'!$H:$H,MATCH($E465,'[4]31.03.2024'!$B:$B,0)),"Not found") -> Not found | N465: =IFERROR(INDEX([2]Sheet1!$B:$B,MATCH($D465,[2]Sheet1!$A:$A,0)),"Not found") -> Not found | O465: =IF($N465="Retail",1,0) -> 0 | P465: =IF($N465="Non-Retail",1,0) -> 0
A466: IVF | B466: 42795 | C466: 43465 | D466: BPT Healthcare II Feeder B Ky | E466: 25870598#004 | F466: 26015 | G466: 26066745 | H466: Non-UCITS | I466: Closed-end | J466: Kiinteistörahasto | K466: Closed | L466: =IF($K466="Continues",DATEDIF($B466,TODAY(),"Y"),DATEDIF($B466,$C466,"Y")) -> 1 | M466: =IFERROR(INDEX('[4]31.03.2024'!$H:$H,MATCH($E466,'[4]31.03.2024'!$B:$B,0)),"Not found") -> Not found | N466: =IFERROR(INDEX([2]Sheet1!$B:$B,MATCH($D466,[2]Sheet1!$A:$A,0)),"Not found") -> Not found | O466: =IF($N466="Retail",1,0) -> 0 | P466: =IF($N466="Non-Retail",1,0) -> 0
A467: IVF | B467: 42339 | C467: 44074 | D467: OP-Private Tavoitetuotto -erikoissijoitusrahasto | E467: 07439622#124 | F467: 26029 | G467: 27155141 | H467: Non-UCITS | I467: Open-end | J467: Yhdistelmärahasto | K467: Merged | L467: =IF($K467="Continues",DATEDIF($B467,TODAY(),"Y"),DATEDIF($B467,$C467,"Y")) -> 4 | M467: =IFERROR(INDEX('[4]31.03.2024'!$H:$H,MATCH($E467,'[4]31.03.2024'!$B:$B,0)),"Not found") -> Not found | N467: =IFERROR(INDEX([2]Sheet1!$B:$B,MATCH($D467,[2]Sheet1!$A:$A,0)),"Not found") -> Not found | O467: =IF($N467="Retail",1,0) -> 0 | P467: =IF($N467="Non-Retail",1,0) -> 0
A468: IVF | B468: 42339 | C468: 44074 | D468: OP-Private Tavoitetuotto Plus -erikoissijoitusrahasto | E468: 07439622#125 | F468: 26030 | G468: 27155678 | H468: Non-UCITS | I468: Open-end | J468: Yhdistelmärahasto | K468: Merged | L468: =IF($K468="Continues",DATEDIF($B468,TODAY(),"Y"),DATEDIF($B468,$C468,"Y")) -> 4 | M468: =IFERROR(INDEX('[4]31.03.2024'!$H:$H,MATCH($E468,'[4]31.03.2024'!$B:$B,0)),"Not found") -> Not found | N468: =IFERROR(INDEX([2]Sheet1!$B:$B,MATCH($D468,[2]Sheet1!$A:$A,0)),"Not found") -> Not found | O468: =IF($N468="Retail",1,0) -> 0 | P468: =IF($N468="Non-Retail",1,0) -> 0
A469: IVF | B469: 42339 | C469: 43830 | D469: ICON Real Estate Fund II - Syöttörahasto I Ky | E469: 25361865#003 | F469: 26149 | G469: 26836914 | H469: Non-UCITS | I469: Closed-end | J469: Kiinteistörahasto | K469: Closed | L469: =IF($K469="Continues",DATEDIF($B469,TODAY(),"Y"),DATEDIF($B469,$C469,"Y")) -> 4 | M469: =IFERROR(INDEX('[4]31.03.2024'!$H:$H,MATCH($E469,'[4]31.03.2024'!$B:$B,0)),"Not found") -> Not found | N469: =IFERROR(INDEX([2]Sheet1!$B:$B,MATCH($D469,[2]Sheet1!$A:$A,0)),"Not found") -> Not found | O469: =IF($N469="Retail",1,0) -> 0 | P469: =IF($N469="Non-Retail",1,0) -> 0
A470: IVF | B470: 42430 | C470: 45199 | D470: Elite Kiinteistökehitysrahasto I Feeder Ky | E470: 07446590#135 | F470: 26201 | G470: 25573606 | H470: Non-UCITS | I470: Closed-end | J470: Kiinteistörahasto | K470: Closed | L470: =IF($K470="Continues",DATEDIF($B470,TODAY(),"Y"),DATEDIF($B470,$C470,"Y")) -> 7 | M470: =IFERROR(INDEX('[4]31.03.2024'!$H:$H,MATCH($E470,'[4]31.03.2024'!$B:$B,0)),"Not found") -> Not found | N470: =IFERROR(INDEX([2]Sheet1!$B:$B,MATCH($D470,[2]Sheet1!$A:$A,0)),"Not found") -> Not found | O470: =IF($N470="Retail",1,0) -> 0 | P470: =IF($N470="Non-Retail",1,0) -> 0
A471: IVF | B471: 42430 | C471: 43251 | D471: Samla Pienyritykset Ky | E471: 26842943#002 | F471: 26243 | G471: 27499104 | H471: Non-UCITS | I471: Closed-end | J471: Buyout-rahasto | K471: Closed | L471: =IF($K471="Continues",DATEDIF($B471,TODAY(),"Y"),DATEDIF($B471,$C471,"Y")) -> 2 | M471: =IFERROR(INDEX('[4]31.03.2024'!$H:$H,MATCH($E471,'[4]31.03.2024'!$B:$B,0)),"Not found") -> Not found | N471: =IFERROR(INDEX([2]Sheet1!$B:$B,MATCH($D471,[2]Sheet1!$A:$A,0)),"Not found") -> Not found | O471: =IF($N471="Retail",1,0) -> 0 | P471: =IF($N471="Non-Retail",1,0) -> 0
A472: IVF | B472: 42401 | C472: 45230 | D472: Specialplaceringsfonden Aktia Commodity | E472: 06725133#042 | F472: 26244 | G472: 27352778 | H472: Non-UCITS | I472: Open-end | J472: Muu rahasto | K472: Merged | L472: =IF($K472="Continues",DATEDIF($B472,TODAY(),"Y"),DATEDIF($B472,$C472,"Y")) -> 7 | M472: =IFERROR(INDEX('[4]31.03.2024'!$H:$H,MATCH($E472,'[4]31.03.2024'!$B:$B,0)),"Not found") -> Not found | N472: =IFERROR(INDEX([2]Sheet1!$B:$B,MATCH($D472,[2]Sheet1!$A:$A,0)),"Not found") -> Not found | O472: =IF($N472="Retail",1,0) -> 0 | P472: =IF($N472="Non-Retail",1,0) -> 0
A473: PEF | B473: 42522 | C473: 43677 | D473: Sijoitusrahasto Titanium Osake | E473: 22888047#003 | F473: 26263 | G473: 27572877 | H473: UCITS | I473: Open-end | J473: Osakerahasto | K473: Closed | L473: =IF($K473="Continues",DATEDIF($B473,TODAY(),"Y"),DATEDIF($B473,$C473,"Y")) -> 3 | M473: =IFERROR(INDEX('[4]31.03.2024'!$H:$H,MATCH($E473,'[4]31.03.2024'!$B:$B,0)),"Not found") -> Not found | N473: =IFERROR(INDEX([2]Sheet1!$B:$B,MATCH($D473,[2]Sheet1!$A:$A,0)),"Not found") -> Not found | O473: =IF($N473="Retail",1,0) -> 0 | P473: =IF($N473="Non-Retail",1,0) -> 0
A474: PEF | B474: 42491 | C474: 43404 | D474: Ålandsbanken Allokeringsportfölj Hög Risk Placeringsfond | E474: 14713626#031 | F474: 26322 | G474: 27534651 | H474: UCITS | I474: Open-end | J474: Osakerahasto | K474: Closed | L474: =IF($K474="Continues",DATEDIF($B474,TODAY(),"Y"),DATEDIF($B474,$C474,"Y")) -> 2 | M474: =IFERROR(INDEX('[4]31.03.2024'!$H:$H,MATCH($E474,'[4]31.03.2024'!$B:$B,0)),"Not found") -> Not found | N474: =IFERROR(INDEX([2]Sheet1!$B:$B,MATCH($D474,[2]Sheet1!$A:$A,0)),"Not found") -> Not found | O474: =IF($N474="Retail",1,0) -> 0 | P474: =IF($N474="Non-Retail",1,0) -> 0
A475: PEF | B475: 42491 | C475: 43404 | D475: Ålandsbanken Allokeringsportfölj Låg Risk Placeringsfond | E475: 14713626#032 | F475: 26323 | G475: 27534643 | H475: UCITS | I475: Open-end | J475: Korkorahasto | K475: Closed | L475: =IF($K475="Continues",DATEDIF($B475,TODAY(),"Y"),DATEDIF($B475,$C475,"Y")) -> 2 | M475: =IFERROR(INDEX('[4]31.03.2024'!$H:$H,MATCH($E475,'[4]31.03.2024'!$B:$B,0)),"Not found") -> Not found | N475: =IFERROR(INDEX([2]Sheet1!$B:$B,MATCH($D475,[2]Sheet1!$A:$A,0)),"Not found") -> Not found | O475: =IF($N475="Retail",1,0) -> 0 | P475: =IF($N475="Non-Retail",1,0) -> 0
A476: PEF | B476: 42461 | C476: 43465 | D476: Elite Alfred Berg Optimi Erikoissijoitusrahasto | E476: 21793994#038 | F476: 26375 | G476: 27524541 | H476: Non-UCITS | I476: Open-end | J476: Muu rahasto | K476: Merged | L476: =IF($K476="Continues",DATEDIF($B476,TODAY(),"Y"),DATEDIF($B476,$C476,"Y")) -> 2 | M476: =IFERROR(INDEX('[4]31.03.2024'!$H:$H,MATCH($E476,'[4]31.03.2024'!$B:$B,0)),"Not found") -> Not found | N476: =IFERROR(INDEX([2]Sheet1!$B:$B,MATCH($D476,[2]Sheet1!$A:$A,0)),"Not found") -> Not found | O476: =IF($N476="Retail",1,0) -> 0 | P476: =IF($N476="Non-Retail",1,0) -> 0
... A487: PEF | B487: 42705 | C487: 44926 | D487: Finhoiva Ky | E487: 27526045#002 | F487: 27374 | G487: 27780414 | H487: Non-UCITS | I487: Closed-end | J487: Kiinteistörahasto | K487: Closed | L487: =IF($K487="Continues",DATEDIF($B487,TODAY(),"Y"),DATEDIF($B487,$C487,"Y")) -> 6 | M487: =IFERROR(INDEX('[4]31.03.2024'!$H:$H,MATCH($E487,'[4]31.03.2024'!$B:$B,0)),"Not found") -> Not found | N487: =IFERROR(INDEX([2]Sheet1!$B:$B,MATCH($D487,[2]Sheet1!$A:$A,0)),"Not found") -> Not found | O487: =IF($N487="Retail",1,0) -> 0 | P487: =IF($N487="Non-Retail",1,0) -> 0
A488: PEF | B488: 42826 | C488: 42827 | D488: Obsido Yritysrahasto I Ky | E488: 24489795#010 | F488: 27375 | G488: NULL | H488: Non-UCITS | I488: Closed-end | J488: Venture Capital -rahasto | K488: Closed | L488: =IF($K488="Continues",DATEDIF($B488,TODAY(),"Y"),DATEDIF($B488,$C488,"Y")) -> 0 | M488: =IFERROR(INDEX('[4]31.03.2024'!$H:$H,MATCH($E488,'[4]31.03.2024'!$B:$B,0)),"Not found") -> Not found | N488: =IFERROR(INDEX([2]Sheet1!$B:$B,MATCH($D488,[2]Sheet1!$A:$A,0)),"Not found") -> Not found | O488: =IF($N488="Retail",1,0) -> 0 | P488: =IF($N488="Non-Retail",1,0) -> 0
A489: PEF | B489: 42552 | C489: 44469 | D489: EAKR-Aloitusrahasto Oy | E489: 08425222#003 | F489: 27479 | G489: 27321576 | H489: Non-UCITS | I489: Closed-end | J489: Buyout-rahasto | K489: Closed | L489: =IF($K489="Continues",DATEDIF($B489,TODAY(),"Y"),DATEDIF($B489,$C489,"Y")) -> 5 | M489: =IFERROR(INDEX('[4]31.03.2024'!$H:$H,MATCH($E489,'[4]31.03.2024'!$B:$B,0)),"Not found") -> Not found | N489: =IFERROR(INDEX([2]Sheet1!$B:$B,MATCH($D489,[2]Sheet1!$A:$A,0)),"Not found") -> Not found | O489: =IF($N489="Retail",1,0) -> 0 | P489: =IF($N489="Non-Retail",1,0) -> 0
A490: PEF | B490: 42644 | C490: 45199 | D490: WS Solar Energy Fund I Ky | E490: 25997361#001 | F490: 27497 | G490: 28702725 | H490: Non-UCITS | I490: Closed-end | J490: Muu rahasto | K490: Closed | L490: =IF($K490="Continues",DATEDIF($B490,TODAY(),"Y"),DATEDIF($B490,$C490,"Y")) -> 6 | M490: =IFERROR(INDEX('[4]31.03.2024'!$H:$H,MATCH($E490,'[4]31.03.2024'!$B:$B,0)),"Not found") -> Not found | N490: =IFERROR(INDEX([2]Sheet1!$B:$B,MATCH($D490,[2]Sheet1!$A:$A,0)),"Not found") -> Not found | O490: =IF($N490="Retail",1,0) -> 0 | P490: =IF($N490="Non-Retail",1,0) -> 0
A491: PEF | B491: 42705 | C491: 43830 | D491: Elite Alfred Berg Eurooppa Faktorit Sijoitusrahasto | E491: 21793994#041 | F491: 27535 | G491: 27943543 | H491: UCITS | I491: Open-end | J491: Osakerahasto | K491: Merged | L491: =IF($K491="Continues",DATEDIF($B491,TODAY(),"Y"),DATEDIF($B491,$C491,"Y")) -> 3 | M491: =IFERROR(INDEX('[4]31.03.2024'!$H:$H,MATCH($E491,'[4]31.03.2024'!$B:$B,0)),"Not found") -> Not found | N491: =IFERROR(INDEX([2]Sheet1!$B:$B,MATCH($D491,[2]Sheet1!$A:$A,0)),"Not found") -> Not found | O491: =IF($N491="Retail",1,0) -> 0 | P491: =IF($N491="Non-Retail",1,0) -> 0
A492: PEF | B492: 42795 | C492: 44255 | D492: OP-Amerikka-sijoitusrahasto | E492: 07439622#128 | F492: 27548 | G492: 27943332 | H492: UCITS | I492: Open-end | J492: Osakerahasto | K492: Merged | L492: =IF($K492="Continues",DATEDIF($B492,TODAY(),"Y"),DATEDIF($B492,$C492,"Y")) -> 3 | M492: =IFERROR(INDEX('[4]31.03.2024'!$H:$H,MATCH($E492,'[4]31.03.2024'!$B:$B,0)),"Not found") -> Not found | N492: =IFERROR(INDEX([2]Sheet1!$B:$B,MATCH($D492,[2]Sheet1!$A:$A,0)),"Not found") -> Not found | O492: =IF($N492="Retail",1,0) -> 0 | P492: =IF($N492="Non-Retail",1,0) -> 0
A493: PEF | B493: 42795 | C493: 43404 | D493: Erikoissijoitusrahasto Estlander & Partners Alpha Trend | E493: 18300220#011 | F493: 27645 | G493: 27938867 | H493: Non-UCITS | I493: Open-end | J493: Hedge-rahasto | K493: Closed | L493: =IF($K493="Continues",DATEDIF($B493,TODAY(),"Y"),DATEDIF($B493,$C493,"Y")) -> 1 | M493: =IFERROR(INDEX('[4]31.03.2024'!$H:$H,MATCH($E493,'[4]31.03.2024'!$B:$B,0)),"Not found") -> Not found | N493: =IFERROR(INDEX([2]Sheet1!$B:$B,MATCH($D493,[2]Sheet1!$A:$A,0)),"Not found") -> Not found | O493: =IF($N493="Retail",1,0) -> 0 | P493: =IF($N493="Non-Retail",1,0) -> 0
A494: PEF | B494: 42767 | C494: 43830 | D494: Elite Alfred Berg Suomi Faktorit Erikoissijoitusrahasto | E494: 21793994#044 | F494: 27648 | G494: 28023749 | H494: Non-UCITS | I494: Open-end | J494: Osakerahasto | K494: Merged | L494: =IF($K494="Continues",DATEDIF($B494,TODAY(),"Y"),DATEDIF($B494,$C494,"Y")) -> 2 | M494: =IFERROR(INDEX('[4]31.03.2024'!$H:$H,MATCH($E494,'[4]31.03.2024'!$B:$B,0)),"Not found") -> Not found | N494: =IFERROR(INDEX([2]Sheet1!$B:$B,MATCH($D494,[2]Sheet1!$A:$A,0)),"Not found") -> Not found | O494: =IF($N494="Retail",1,0) -> 0 | P494: =IF($N494="Non-Retail",1,0) -> 0
A495: PEF | B495: 42795 | C495: 44926 | D495: YCE Housing I Ky | E495: 19610802#002 | F495: 27777 | G495: 28031431 | H495: Non-UCITS | I495: Closed-end | J495: Kiinteistörahasto | K495: Closed | L495: =IF($K495="Continues",DATEDIF($B495,TODAY(),"Y"),DATEDIF($B495,$C495,"Y")) -> 5 | M495: =IFERROR(INDEX('[4]31.03.2024'!$H:$H,MATCH($E495,'[4]31.03.2024'!$B:$B,0)),"Not found") -> Not found | N495: =IFERROR(INDEX([2]Sheet1!$B:$B,MATCH($D495,[2]Sheet1!$A:$A,0)),"Not found") -> Not found | O495: =IF($N495="Retail",1,0) -> 0 | P495: =IF($N495="Non-Retail",1,0) -> 0
A496: PEF | B496: 42795 | C496: 43434 | D496: Ålandsbanken Dynamisk Ränta Placeringsfond | E496: 14713626#038 | F496: 27958 | G496: 28216989 | H496: UCITS | I496: Open-end | J496: Korkorahasto | K496: Merged | L496: =IF($K496="Continues",DATEDIF($B496,TODAY(),"Y"),DATEDIF($B496,$C496,"Y")) -> 1 | M496: =IFERROR(INDEX('[4]31.03.2024'!$H:$H,MATCH($E496,'[4]31.03.2024'!$B:$B,0)),"Not found") -> Not found | N496: =IFERROR(INDEX([2]Sheet1!$B:$B,MATCH($D496,[2]Sheet1!$A:$A,0)),"Not found") -> Not found | O496: =IF($N496="Retail",1,0) -> 0 | P496: =IF($N496="Non-Retail",1,0) -> 0
A497: PEF | B497: 42795 | C497: 43830 | D497: Erikoissijoitusrahasto UB Reaaliomaisuus | E497: 21181015#031 | F497: 27976 | G497: 28125569 | H497: Non-UCITS | I497: Open-end | J497: Kiinteistörahasto | K497: Merged | L497: =IF($K497="Continues",DATEDIF($B497,TODAY(),"Y"),DATEDIF($B497,$C497,"Y")) -> 2 | M497: =IFERROR(INDEX('[4]31.03.2024'!$H:$H,MATCH($E497,'[4]31.03.2024'!$B:$B,0)),"Not found") -> Not found | N497: =IFERROR(INDEX([2]Sheet1!$B:$B,MATCH($D497,[2]Sheet1!$A:$A,0)),"Not found") -> Not found | O497: =IF($N497="Retail",1,0) -> 0 | P497: =IF($N497="Non-Retail",1,0) -> 0
A498: PEF | B498: 42887 | C498: 43465 | D498: Ålandsbanken Premium 100 Global Aktie Placeringsfond | E498: 14713626#039 | F498: 28064 | G498: 28291444 | H498: UCITS | I498: Open-end | J498: Osakerahasto | K498: Merged | L498: =IF($K498="Continues",DATEDIF($B498,TODAY(),"Y"),DATEDIF($B498,$C498,"Y")) -> 1 | M498: =IFERROR(INDEX('[4]31.03.2024'!$H:$H,MATCH($E498,'[4]31.03.2024'!$B:$B,0)),"Not found") -> Not found | N498: =IFERROR(INDEX([2]Sheet1!$B:$B,MATCH($D498,[2]Sheet1!$A:$A,0)),"Not found") -> Not found | O498: =IF($N498="Retail",1,0) -> 0 | P498: =IF($N498="Non-Retail",1,0) -> 0
A499: PEF | B499: 43221 | C499: 44377 | D499: Sijoitusrahasto UB EM Frontier Real Assets | E499: 21181015#032 | F499: 28096 | G499: 28456229 | H499: UCITS | I499: Open-end | J499: Osakerahasto | K499: Merged | L499: =IF($K499="Continues",DATEDIF($B499,TODAY(),"Y"),DATEDIF($B499,$C499,"Y")) -> 3 | M499: =IFERROR(INDEX('[4]31.03.2024'!$H:$H,MATCH($E499,'[4]31.03.2024'!$B:$B,0)),"Not found") -> Not found | N499: =IFERROR(INDEX([2]Sheet1!$B:$B,MATCH($D499,[2]Sheet1!$A:$A,0)),"Not found") -> Not found | O499: =IF($N499="Retail",1,0) -> 0 | P499: =IF($N499="Non-Retail",1,0) -> 0
A500: PEF | B500: 42979 | C500: 43281 | D500: Elite PK-Yrityslaina I Ky | E500: 21793994#046 | F500: 28121 | G500: 28403979 | H500: Non-UCITS | I500: Closed-end | J500: Venture Capital -rahasto | K500: Closed | L500: =IF($K500="Continues",DATEDIF($B500,TODAY(),"Y"),DATEDIF($B500,$C500,"Y")) -> 0 | M500: =IFERROR(INDEX('[4]31.03.2024'!$H:$H,MATCH($E500,'[4]31.03.2024'!$B:$B,0)),"Not found") -> Not found | N500: =IFERROR(INDEX([2]Sheet1!$B:$B,MATCH($D500,[2]Sheet1!$A:$A,0)),"Not found") -> Not found | O500: =IF($N500="Retail",1,0) -> 0 | P500: =IF($N500="Non-Retail",1,0) -> 0
... A561: PEF | B561: 44075 | C561: 44712 | D561: Erikoissijoitusrahasto LähiTapiola Osaketähdet | E561: 16172050#029 | F561: 31468 | G561: 31403515 | H561: Non-UCITS | I561: Open-end | J561: Osakerahasto | K561: Closed | L561: =IF($K561="Continues",DATEDIF($B561,TODAY(),"Y"),DATEDIF($B561,$C561,"Y")) -> 1 | M561: =IFERROR(INDEX('[4]31.03.2024'!$H:$H,MATCH($E561,'[4]31.03.2024'!$B:$B,0)),"Not found") -> Not found | N561: =IFERROR(INDEX([2]Sheet1!$B:$B,MATCH($D561,[2]Sheet1!$A:$A,0)),"Not found") -> Not found | O561: =IF($N561="Retail",1,0) -> 0 | P561: =IF($N561="Non-Retail",1,0) -> 0
A562: IVF | B562: 44896 | C562: 44926 | D562: Minoria Fund I Ky | E562: 31385118#001 | F562: 31477 | G562: NULL | H562: Non-UCITS | I562: Closed-end | J562: Buyout-rahasto | K562: Closed | L562: =IF($K562="Continues",DATEDIF($B562,TODAY(),"Y"),DATEDIF($B562,$C562,"Y")) -> 0 | M562: =IFERROR(INDEX('[4]31.03.2024'!$H:$H,MATCH($E562,'[4]31.03.2024'!$B:$B,0)),"Not found") -> Not found | N562: =IFERROR(INDEX([2]Sheet1!$B:$B,MATCH($D562,[2]Sheet1!$A:$A,0)),"Not found") -> Not found | O562: =IF($N562="Retail",1,0) -> 0 | P562: =IF($N562="Non-Retail",1,0) -> 0
A563: IVF | B563: 44896 | C563: 44926 | D563: Minoria Feeder Fund I Ky | E563: 31385118#002 | F563: 31478 | G563: NULL | H563: Non-UCITS | I563: Closed-end | J563: Buyout-rahasto | K563: Closed | L563: =IF($K563="Continues",DATEDIF($B563,TODAY(),"Y"),DATEDIF($B563,$C563,"Y")) -> 0 | M563: =IFERROR(INDEX('[4]31.03.2024'!$H:$H,MATCH($E563,'[4]31.03.2024'!$B:$B,0)),"Not found") -> Not found | N563: =IFERROR(INDEX([2]Sheet1!$B:$B,MATCH($D563,[2]Sheet1!$A:$A,0)),"Not found") -> Not found | O563: =IF($N563="Retail",1,0) -> 0 | P563: =IF($N563="Non-Retail",1,0) -> 0
A564: IVF | B564: 44197 | C564: 44804 | D564: GRIT Innolab AI Equity Arbitrage Specialplaceringsfond | E564: 18300220#030 | F564: 31562 | G564: 31725725 | H564: Non-UCITS | I564: Open-end | J564: Hedge-rahasto | K564: Closed | L564: =IF($K564="Continues",DATEDIF($B564,TODAY(),"Y"),DATEDIF($B564,$C564,"Y")) -> 1 | M564: =IFERROR(INDEX('[4]31.03.2024'!$H:$H,MATCH($E564,'[4]31.03.2024'!$B:$B,0)),"Not found") -> Not found | N564: =IFERROR(INDEX([2]Sheet1!$B:$B,MATCH($D564,[2]Sheet1!$A:$A,0)),"Not found") -> Not found | O564: =IF($N564="Retail",1,0) -> 0 | P564: =IF($N564="Non-Retail",1,0) -> 0
A565: PEF | B565: 44256 | C565: 44530 | D565: Erikoissijoitusrahasto Aktia Mikro Kruunu | E565: 20628401#041 | F565: 31744 | G565: 31793453 | H565: Non-UCITS | I565: Open-end | J565: Osakerahasto | K565: Merged | L565: =IF($K565="Continues",DATEDIF($B565,TODAY(),"Y"),DATEDIF($B565,$C565,"Y")) -> 0 | M565: =IFERROR(INDEX('[4]31.03.2024'!$H:$H,MATCH($E565,'[4]31.03.2024'!$B:$B,0)),"Not found") -> Not found | N565: =IFERROR(INDEX([2]Sheet1!$B:$B,MATCH($D565,[2]Sheet1!$A:$A,0)),"Not found") -> Not found | O565: =IF($N565="Retail",1,0) -> 0 | P565: =IF($N565="Non-Retail",1,0) -> 0
A566: PEF | B566: 44348 | C566: 45199 | D566: Taaleri Infra I Ky | E566: 06725133#055 | F566: 35904 | G566: 32073968 | H566: Non-UCITS | I566: Closed-end | J566: Muu rahasto | K566: Closed | L566: =IF($K566="Continues",DATEDIF($B566,TODAY(),"Y"),DATEDIF($B566,$C566,"Y")) -> 2 | M566: =IFERROR(INDEX('[4]31.03.2024'!$H:$H,MATCH($E566,'[4]31.03.2024'!$B:$B,0)),"Not found") -> Not found | N566: =IFERROR(INDEX([2]Sheet1!$B:$B,MATCH($D566,[2]Sheet1!$A:$A,0)),"Not found") -> Not found | O566: =IF($N566="Retail",1,0) -> 0 | P566: =IF($N566="Non-Retail",1,0) -> 0
A567: PEF | B567: 44378 | C567: 44926 | D567: OP-Pohjoismaat Mikroyhtiöt -erikoissijoitusrahasto | E567: 07439622#148 | F567: 41574 | G567: 32103645 | H567: Non-UCITS | I567: Open-end | J567: Osakerahasto | K567: Merged | L567: =IF($K567="Continues",DATEDIF($B567,TODAY(),"Y"),DATEDIF($B567,$C567,"Y")) -> 1 | M567: =IFERROR(INDEX('[4]31.03.2024'!$H:$H,MATCH($E567,'[4]31.03.2024'!$B:$B,0)),"Not found") -> Not found | N567: =IFERROR(INDEX([2]Sheet1!$B:$B,MATCH($D567,[2]Sheet1!$A:$A,0)),"Not found") -> Not found | O567: =IF($N567="Retail",1,0) -> 0 | P567: =IF($N567="Non-Retail",1,0) -> 0
A568: PEF | B568: 44562 | C568: 45230 | D568: Coeus Invest GRIT Erikoissijoitusrahasto | E568: 18300220#036 | F568: 42154 | G568: 32550808 | H568: Non-UCITS | I568: Open-end | J568: Osakerahasto | K568: Closed | L568: =IF($K568="Continues",DATEDIF($B568,TODAY(),"Y"),DATEDIF($B568,$C568,"Y")) -> 1 | M568: =IFERROR(INDEX('[4]31.03.2024'!$H:$H,MATCH($E568,'[4]31.03.2024'!$B:$B,0)),"Not found") -> Not found | N568: =IFERROR(INDEX([2]Sheet1!$B:$B,MATCH($D568,[2]Sheet1!$A:$A,0)),"Not found") -> Not found | O568: =IF($N568="Retail",1,0) -> 0 | P568: =IF($N568="Non-Retail",1,0) -> 0
A569: PEF | B569: 44652 | C569: 45291 | D569: Visio Siilo Erikoissijoitusrahasto | E569: 18300220#037 | F569: 42389 | G569: 32655773 | H569: Non-UCITS | I569: Open-end | J569: Hedge-rahasto | K569: Closed | L569: =IF($K569="Continues",DATEDIF($B569,TODAY(),"Y"),DATEDIF($B569,$C569,"Y")) -> 1 | M569: =IFERROR(INDEX('[4]31.03.2024'!$H:$H,MATCH($E569,'[4]31.03.2024'!$B:$B,0)),"Not found") -> Not found | N569: =IFERROR(INDEX([2]Sheet1!$B:$B,MATCH($D569,[2]Sheet1!$A:$A,0)),"Not found") -> Not found | O569: =IF($N569="Retail",1,0) -> 0 | P569: =IF($N569="Non-Retail",1,0) -> 0
A570: IVF | B570: 39783 | C570: 45443 | D570: Sijoitusrahasto LähiTapiola Kuluttaja ESG | E570: 10932901#042 | F570: 13096 | G570: 17963321 | H570: UCITS | I570: Open-end | J570: Osakerahasto | K570: Merged | L570: =IF($K570="Continues",DATEDIF($B570,TODAY(),"Y"),DATEDIF($B570,$C570,"Y")) -> 15 | M570: =IFERROR(INDEX('[4]31.03.2024'!$H:$H,MATCH($E570,'[4]31.03.2024'!$B:$B,0)),"Not found") -> Seligson & Co Rahastoyhtiö Oyj | N570: =IFERROR(INDEX([2]Sheet1!$B:$B,MATCH($D570,[2]Sheet1!$A:$A,0)),"Not found") -> Retail | O570: =IF($N570="Retail",1,0) -> 1 | P570: =IF($N570="Non-Retail",1,0) -> 0
A571: IVF | B571: 39783 | C571: 45443 | D571: Sijoitusrahasto LähiTapiola Kuluttaja ESG | E571: 10932901#042 | F571: 13096 | G571: 17963321 | H571: UCITS | I571: Open-end | J571: Osakerahasto | K571: Merged | L571: =IF($K571="Continues",DATEDIF($B571,TODAY(),"Y"),DATEDIF($B571,$C571,"Y")) -> 15 | M571: =IFERROR(INDEX('[4]31.03.2024'!$H:$H,MATCH($E571,'[4]31.03.2024'!$B:$B,0)),"Not found") -> Seligson & Co Rahastoyhtiö Oyj | N571: =IFERROR(INDEX([2]Sheet1!$B:$B,MATCH($D571,[2]Sheet1!$A:$A,0)),"Not found") -> Retail | O571: =IF($N571="Retail",1,0) -> 1 | P571: =IF($N571="Non-Retail",1,0) -> 0
A572: IVF | B572: 39783 | C572: 45443 | D572: Sijoitusrahasto LähiTapiola Kuluttaja ESG | E572: 10932901#042 | F572: 13096 | G572: 17963321 | H572: UCITS | I572: Open-end | J572: Osakerahasto | K572: Merged | L572: =IF($K572="Continues",DATEDIF($B572,TODAY(),"Y"),DATEDIF($B572,$C572,"Y")) -> 15 | M572: =IFERROR(INDEX('[4]31.03.2024'!$H:$H,MATCH($E572,'[4]31.03.2024'!$B:$B,0)),"Not found") -> Seligson & Co Rahastoyhtiö Oyj | N572: =IFERROR(INDEX([2]Sheet1!$B:$B,MATCH($D572,[2]Sheet1!$A:$A,0)),"Not found") -> Retail | O572: =IF($N572="Retail",1,0) -> 1 | P572: =IF($N572="Non-Retail",1,0) -> 0
A573: IVF | B573: 39783 | C573: 45473 | D573: Sijoitusrahasto Nordea Aasialaiset Tähdet | E573: 17377859#038 | F573: 13160 | G573: 18641949 | H573: UCITS | I573: Open-end | J573: Osakerahasto | K573: Closed | L573: =IF($K573="Continues",DATEDIF($B573,TODAY(),"Y"),DATEDIF($B573,$C573,"Y")) -> 15 | M573: =IFERROR(INDEX('[4]31.03.2024'!$H:$H,MATCH($E573,'[4]31.03.2024'!$B:$B,0)),"Not found") -> Nordea Funds Oy | N573: =IFERROR(INDEX([2]Sheet1!$B:$B,MATCH($D573,[2]Sheet1!$A:$A,0)),"Not found") -> Retail | O573: =IF($N573="Retail",1,0) -> 1 | P573: =IF($N573="Non-Retail",1,0) -> 0
A574: IVF | B574: 40940 | C574: 45443 | D574: Erikoissijoitusrahasto Aktia Vakaa Korko | E574: 20628401#016 | F574: 17273 | G574: 24499918 | H574: Non-UCITS | I574: Open-end | J574: Korkorahasto | K574: Merged | L574: =IF($K574="Continues",DATEDIF($B574,TODAY(),"Y"),DATEDIF($B574,$C574,"Y")) -> 12 | M574: =IFERROR(INDEX('[4]31.03.2024'!$H:$H,MATCH($E574,'[4]31.03.2024'!$B:$B,0)),"Not found") -> Aktia Rahastoyhtiö Oy | N574: =IFERROR(INDEX([2]Sheet1!$B:$B,MATCH($D574,[2]Sheet1!$A:$A,0)),"Not found") -> Retail | O574: =IF($N574="Retail",1,0) -> 1 | P574: =IF($N574="Non-Retail",1,0) -> 0
A575: IVF | B575: 40940 | C575: 45443 | D575: Erikoissijoitusrahasto Aktia Vakaa Korko | E575: 20628401#016 | F575: 17273 | G575: 24499918 | H575: Non-UCITS | I575: Open-end | J575: Korkorahasto | K575: Merged | L575: =IF($K575="Continues",DATEDIF($B575,TODAY(),"Y"),DATEDIF($B575,$C575,"Y")) -> 12 | M575: =IFERROR(INDEX('[4]31.03.2024'!$H:$H,MATCH($E575,'[4]31.03.2024'!$B:$B,0)),"Not found") -> Aktia Rahastoyhtiö Oy | N575: =IFERROR(INDEX([2]Sheet1!$B:$B,MATCH($D575,[2]Sheet1!$A:$A,0)),"Not found") -> Retail | O575: =IF($N575="Retail",1,0) -> 1 | P575: =IF($N575="Non-Retail",1,0) -> 0
... A591: IVF | B591: 39783 | C591: 45626 | D591: Sijoitusrahasto Danske Invest Itä-Eurooppa Konvergenssi | E591: 06716026#094 | F591: 13374 | G591: 20594133 | H591: UCITS | I591: Open-end | J591: Osakerahasto | K591: Merged | L591: =IF($K591="Continues",DATEDIF($B591,TODAY(),"Y"),DATEDIF($B591,$C591,"Y")) -> 15 | M591: =IFERROR(INDEX('[4]31.03.2024'!$H:$H,MATCH($E591,'[4]31.03.2024'!$B:$B,0)),"Not found") -> Danske Invest Rahastoyhtiö Oy | N591: =IFERROR(INDEX([2]Sheet1!$B:$B,MATCH($D591,[2]Sheet1!$A:$A,0)),"Not found") -> Retail | O591: =IF($N591="Retail",1,0) -> 1 | P591: =IF($N591="Non-Retail",1,0) -> 0

Sheet Statistisk analys
A1: Raportoija | B1: Kysely (PEF = 0, IVF = 1) | C1: UCITS-tyyppi (NON = 0, UCITS = 1) | D1: Pääomanvaihtelevuus (Closed-end = 0, Open-end = 1) | E1: AIF - retail | F1: AIF - non-retail | G1: Venture Capital -rahasto | H1: Osakerahasto | I1: Muu rahasto | J1: Korkorahasto | K1: Kiinteistörahasto | L1: Hedge-rahasto | M1: Buyout-rahasto | N1: Yhdistelmärahasto | O1: Elinaika (kk) | AA1: Jatkaa | AB1: Sulautunut | AC1: Lakkautettu | AD1: RaportoinninLopetusPvm | AE1: RaportoinninAloitusPvm
A2: Oy Wedeco Ab | B2: 0 | C2: 0 | D2: 0 | E2: 0 | F2: 0 | G2: 0 | H2: 0 | I2: 0 | J2: 0 | K2: 0 | L2: 0 | M2: 1 | N2: 0 | O2: 34 | Q2: SUMMARY OUTPUT Buyout | AA2: 0 | AB2: 0 | AC2: 1 | AD2: 43100 | AE2: 41974
A3: Finnventure Rahasto V Ky | B3: 0 | C3: 0 | D3: 0 | E3: 0 | F3: 0 | G3: 0 | H3: 0 | I3: 0 | J3: 0 | K3: 0 | L3: 0 | M3: 1 | N3: 0 | O3: 24 | AA3: 0 | AB3: 0 | AC3: 1 | AD3: 42735 | AE3: 41974
A4: Maneq Fund 2002 Ky | B4: 0 | C4: 0 | D4: 0 | E4: 0 | F4: 0 | G4: 0 | H4: 0 | I4: 0 | J4: 0 | K4: 0 | L4: 0 | M4: 1 | N4: 0 | O4: 12 | Q4: Regression Statistics | AA4: 0 | AB4: 0 | AC4: 1 | AD4: 42369 | AE4: 41974
A5: Finnmezzanine Rahasto III A Ky | B5: 0 | C5: 0 | D5: 0 | E5: 0 | F5: 0 | G5: 0 | H5: 0 | I5: 0 | J5: 0 | K5: 0 | L5: 0 | M5: 1 | N5: 0 | O5: 55 | Q5: Multiple R | R5: 0.35843582 | AA5: 0 | AB5: 0 | AC5: 1 | AD5: 43738 | AE5: 41974
A6: Finnmezzanine Rahasto III C Ky | B6: 0 | C6: 0 | D6: 0 | E6: 0 | F6: 0 | G6: 0 | H6: 0 | I6: 0 | J6: 0 | K6: 0 | L6: 0 | M6: 1 | N6: 0 | O6: 11 | Q6: R Square | R6: 0.12847623 | AA6: 0 | AB6: 0 | AC6: 1 | AD6: 42369 | AE6: 41974
A7: Finnmezzanine Rahasto III B Ky | B7: 0 | C7: 0 | D7: 0 | E7: 0 | F7: 0 | G7: 0 | H7: 0 | I7: 0 | J7: 0 | K7: 0 | L7: 0 | M7: 1 | N7: 0 | O7: 55 | Q7: Adjusted R Square | R7: 0.12364785 | AA7: 0 | AB7: 0 | AC7: 1 | AD7: 43738 | AE7: 41974
A8: CapMan Real Estate I Ky | B8: 0 | C8: 0 | D8: 0 | E8: 0 | F8: 0 | G8: 0 | H8: 0 | I8: 0 | J8: 0 | K8: 1 | L8: 0 | M8: 0 | N8: 0 | O8: 72 | Q8: Standard Error | R8: 32.523922 | AA8: 0 | AB8: 0 | AC8: 1 | AD8: 44196 | AE8: 41974
A9: OP-Euro -sijoitusrahasto | B9: 1 | C9: 1 | D9: 1 | E9: 1 | F9: 0 | G9: 0 | H9: 0 | I9: 0 | J9: 1 | K9: 0 | L9: 0 | M9: 0 | N9: 0 | O9: 120 | Q9: Observations | R9: 1090 | AA9: 0 | AB9: 0 | AC9: 1 | AD9: 55153 | AE9: 43466
A10: S-Pankki Lyhyt Korko Sijoitusrahasto | B10: 1 | C10: 1 | D10: 1 | E10: 1 | F10: 0 | G10: 0 | H10: 0 | I10: 0 | J10: 1 | K10: 0 | L10: 0 | M10: 0 | N10: 0 | O10: 76 | AA10: 0 | AB10: 0 | AC10: 1 | AD10: 55153 | AE10: 43466
A11: Veraventure Oy | B11: 0 | C11: 0 | D11: 0 | E11: 0 | F11: 0 | G11: 1 | H11: 0 | I11: 0 | J11: 0 | K11: 0 | L11: 0 | M11: 0 | N11: 0 | O11: 81 | Q11: ANOVA | AA11: 0 | AB11: 0 | AC11: 1 | AD11: 44469 | AE11: 41974
A12: Aloitusrahasto Vera Oy | B12: 0 | C12: 0 | D12: 0 | E12: 0 | F12: 0 | G12: 1 | H12: 0 | I12: 0 | J12: 0 | K12: 0 | L12: 0 | M12: 0 | N12: 0 | O12: 34 | R12: df | S12: SS | T12: MS | U12: F | V12: Significance F | AA12: 0 | AB12: 0 | AC12: 1 | AD12: 43100 | AE12: 41974
A13: Sijoitusrahasto eQ Lyhyt Korko | B13: 1 | C13: 1 | D13: 1 | E13: 1 | F13: 0 | G13: 0 | H13: 0 | I13: 0 | J13: 1 | K13: 0 | L13: 0 | M13: 0 | N13: 0 | O13: 120 | Q13: Regression | R13: 6 | S13: 168879.86 | T13: 28146.643 | U13: 26.608523 | V13: 1.1436155e-29 | AA13: 0 | AB13: 0 | AC13: 1 | AD13: 55153 | AE13: 43466
A14: Sijoitusrahasto Danske Invest Suomi Osinko Plus | B14: 1 | C14: 1 | D14: 1 | E14: 0 | F14: 0 | G14: 0 | H14: 1 | I14: 0 | J14: 0 | K14: 0 | L14: 0 | M14: 0 | N14: 0 | O14: 100 | Q14: Residual | R14: 1083 | S14: 1145603.4 | T14: 1057.8055 | AA14: 0 | AB14: 1 | AC14: 0 | AD14: 44165 | AE14: 42856
A15: Sijoitusrahasto Nordea Korko Varovainen | B15: 1 | C15: 1 | D15: 1 | E15: 1 | F15: 0 | G15: 0 | H15: 0 | I15: 0 | J15: 1 | K15: 0 | L15: 0 | M15: 0 | N15: 0 | O15: 118 | Q15: Total | R15: 1089 | S15: 1314483.2 | AA15: 0 | AB15: 0 | AC15: 1 | AD15: 55153 | AE15: 43466
A16: Sijoitusrahasto Nordea Korko | B16: 1 | C16: 1 | D16: 1 | E16: 1 | F16: 0 | G16: 0 | H16: 0 | I16: 0 | J16: 1 | K16: 0 | L16: 0 | M16: 0 | N16: 0 | O16: 115 | AA16: 0 | AB16: 0 | AC16: 1 | AD16: 55153 | AE16: 43466
A17: DEAS Property Fund Finland I Ky | B17: 0 | C17: 0 | D17: 0 | E17: 0 | F17: 1 | G17: 0 | H17: 0 | I17: 0 | J17: 0 | K17: 1 | L17: 0 | M17: 0 | N17: 0 | O17: 113 | R17: Coefficients | S17: Standard Error | T17: t Stat | U17: P-value | V17: Lower 95% | W17: Upper 95% | X17: Lower 95,0% | Y17: Upper 95,0% | AA17: 1 | AB17: 0 | AC17: 0 | AD17: 55153 | AE17: 41974
A18: Amanda III Eastern Private Equity Ky | B18: 0 | C18: 0 | D18: 0 | E18: 0 | F18: 1 | G18: 0 | H18: 0 | I18: 0 | J18: 0 | K18: 0 | L18: 0 | M18: 1 | N18: 0 | O18: 113 | Q18: Intercept | R18: 41.241964 | S18: 2.1762372 | T18: 18.951042 | U18: 2.1560599e-69 | V18: 36.971845 | W18: 45.512083 | X18: 36.971845 | Y18: 45.512083 | AA18: 1 | AB18: 0 | AC18: 0 | AD18: 55153 | AE18: 41974
A19: ANL Kiinteistöt I Ky | B19: 0 | C19: 0 | D19: 0 | E19: 0 | F19: 0 | G19: 0 | H19: 0 | I19: 0 | J19: 0 | K19: 1 | L19: 0 | M19: 0 | N19: 0 | O19: 18 | Q19: Kysely (PEF = 0, IVF = 1) | R19: -27.325329 | S19: 4.9218419 | T19: -5.5518502 | U19: 3.5543335e-08 | V19: -36.982754 | W19: -17.667903 | X19: -36.982754 | Y19: -17.667903 | AA19: 0 | AB19: 0 | AC19: 1 | AD19: 42643 | AE19: 41974
A20: EPI Healthcare I Ky | B20: 0 | C20: 0 | D20: 0 | E20: 0 | F20: 0 | G20: 0 | H20: 0 | I20: 0 | J20: 0 | K20: 1 | L20: 0 | M20: 0 | N20: 0 | O20: 22 | Q20: UCITS-tyyppi (NON = 0, UCITS = 1) | R20: 10.799394 | S20: 3.5073119 | T20: 3.0791086 | U20: 0.0021284859 | V20: 3.9174982 | W20: 17.68129 | X20: 3.9174982 | Y20: 17.68129 | AA20: 0 | AB20: 0 | AC20: 1 | AD20: 42735 | AE20: 41974
A21: EPI Russia I Ky | B21: 0 | C21: 0 | D21: 0 | E21: 0 | F21: 0 | G21: 0 | H21: 0 | I21: 0 | J21: 0 | K21: 1 | L21: 0 | M21: 0 | N21: 0 | O21: 48 | Q21: Pääomanvaihtelevuus (Closed-end = 0, Open-end = 1) | R21: 33.395843 | S21: 5.7164233 | T21: 5.8420871 | U21: 6.8120074e-09 | V21: 22.179324 | W21: 44.612363 | X21: 22.179324 | Y21: 44.612363 | AA21: 0 | AB21: 0 | AC21: 1 | AD21: 43465 | AE21: 41974
A22: Icecapital Housing Fund I Ky | B22: 0 | C22: 0 | D22: 0 | E22: 0 | F22: 0 | G22: 0 | H22: 0 | I22: 0 | J22: 0 | K22: 1 | L22: 0 | M22: 0 | N22: 0 | O22: 9 | Q22: AIF - retail | R22: 11.717611 | S22: 2.4848622 | T22: 4.7155979 | U22: 2.724364e-06 | V22: 6.8419216 | W22: 16.5933 | X22: 6.8419216 | Y22: 16.5933 | AA22: 0 | AB22: 0 | AC22: 1 | AD22: 42277 | AE22: 41974
A23: Icecapital Saint Petersburg Residential Fund I Ky | B23: 0 | C23: 0 | D23: 0 | E23: 0 | F23: 0 | G23: 0 | H23: 0 | I23: 0 | J23: 0 | K23: 1 | L23: 0 | M23: 0 | N23: 0 | O23: 63 | Q23: AIF - non-retail | R23: 32.277788 | S23: 2.7554691 | T23: 11.714081 | U23: 6.3248439e-30 | V23: 26.871125 | W23: 37.684451 | X23: 26.871125 | Y23: 37.684451 | AA23: 0 | AB23: 0 | AC23: 1 | AD23: 44104 | AE23: 41974
A24: Intera Fund I Ky | B24: 0 | C24: 0 | D24: 0 | E24: 0 | F24: 0 | G24: 0 | H24: 0 | I24: 0 | J24: 0 | K24: 0 | L24: 0 | M24: 1 | N24: 0 | O24: 84 | Q24: Buyout-rahasto | R24: 4.3310758 | S24: 2.8530503 | T24: 1.518051 | U24: 0.1292934 | V24: -1.2670565 | W24: 9.9292081 | X24: -1.2670565 | Y24: 9.9292081 | AA24: 0 | AB24: 0 | AC24: 1 | AD24: 44561 | AE24: 41974
A25: Mandatum Pääomarahasto I Ky | B25: 0 | C25: 0 | D25: 0 | E25: 0 | F25: 0 | G25: 0 | H25: 0 | I25: 0 | J25: 0 | K25: 0 | L25: 0 | M25: 1 | N25: 0 | O25: 63 | AA25: 0 | AB25: 0 | AC25: 1 | AD25: 43921 | AE25: 41974
A26: Real Estate Fund Finland I Ky | B26: 0 | C26: 0 | D26: 0 | E26: 0 | F26: 0 | G26: 0 | H26: 0 | I26: 0 | J26: 0 | K26: 1 | L26: 0 | M26: 0 | N26: 0 | O26: 24 | Q26: SUMMARY OUTPUT Hedge | AA26: 0 | AB26: 0 | AC26: 1 | AD26: 42735 | AE26: 41974
A27: Selected Mezzanine Funds I Ky | B27: 0 | C27: 0 | D27: 0 | E27: 0 | F27: 1 | G27: 0 | H27: 0 | I27: 0 | J27: 0 | K27: 0 | L27: 0 | M27: 1 | N27: 0 | O27: 113 | AA27: 1 | AB27: 0 | AC27: 0 | AD27: 55153 | AE27: 41974
A28: Tapiola KR I Ky | B28: 0 | C28: 0 | D28: 0 | E28: 0 | F28: 1 | G28: 0 | H28: 0 | I28: 0 | J28: 0 | K28: 1 | L28: 0 | M28: 0 | N28: 0 | O28: 113 | Q28: Regression Statistics | AA28: 1 | AB28: 0 | AC28: 0 | AD28: 55153 | AE28: 41974
A29: Tapiola KR III Ky | B29: 0 | C29: 0 | D29: 0 | E29: 0 | F29: 0 | G29: 0 | H29: 0 | I29: 0 | J29: 0 | K29: 1 | L29: 0 | M29: 0 | N29: 0 | O29: 64 | Q29: Multiple R | R29: 0.36186495 | AA29: 0 | AB29: 0 | AC29: 1 | AD29: 44012 | AE29: 41974
A30: Armada Mezzanine Fund II Ky | B30: 0 | C30: 0 | D30: 0 | E30: 0 | F30: 0 | G30: 0 | H30: 0 | I30: 0 | J30: 0 | K30: 0 | L30: 0 | M30: 1 | N30: 0 | O30: 72 | Q30: R Square | R30: 0.13094624 | AA30: 0 | AB30: 0 | AC30: 1 | AD30: 44196 | AE30: 41974
A31: Kauppakeskuskiinteistöt FEA Ky | B31: 0 | C31: 0 | D31: 0 | E31: 0 | F31: 0 | G31: 0 | H31: 0 | I31: 0 | J31: 0 | K31: 1 | L31: 0 | M31: 0 | N31: 0 | O31: 36 | Q31: Adjusted R Square | R31: 0.12613154 | AA31: 0 | AB31: 0 | AC31: 1 | AD31: 43190 | AE31: 41974
A32: Selected Private Equity Funds I Ky | B32: 0 | C32: 0 | D32: 0 | E32: 0 | F32: 1 | G32: 0 | H32: 0 | I32: 0 | J32: 0 | K32: 0 | L32: 0 | M32: 1 | N32: 0 | O32: 113 | Q32: Standard Error | R32: 32.477801 | AA32: 1 | AB32: 0 | AC32: 0 | AD32: 55153 | AE32: 41974
A33: Medtech Rahasto Ky | B33: 0 | C33: 0 | D33: 0 | E33: 0 | F33: 0 | G33: 0 | H33: 0 | I33: 0 | J33: 0 | K33: 0 | L33: 0 | M33: 1 | N33: 0 | O33: 18 | Q33: Observations | R33: 1090 | AA33: 0 | AB33: 0 | AC33: 1 | AD33: 42551 | AE33: 41974
A34: OP-Dollari -sijoitusrahasto | B34: 1 | C34: 1 | D34: 1 | E34: 0 | F34: 0 | G34: 0 | H34: 0 | I34: 0 | J34: 1 | K34: 0 | L34: 0 | M34: 0 | N34: 0 | O34: 81 | AA34: 0 | AB34: 1 | AC34: 0 | AD34: 43799 | AE34: 43466
A35: Erikoissijoitusrahasto AURTUA+ | B35: 1 | C35: 0 | D35: 1 | E35: 0 | F35: 0 | G35: 0 | H35: 0 | I35: 0 | J35: 0 | K35: 0 | L35: 0 | M35: 0 | N35: 1 | O35: 26 | Q35: ANOVA | AA35: 0 | AB35: 0 | AC35: 1 | AD35: 42521 | AE35: 41699
A36: Ålandsbanken Bostadsfond Specialplaceringsfond | B36: 1 | C36: 0 | D36: 1 | E36: 1 | F36: 0 | G36: 0 | H36: 0 | I36: 0 | J36: 0 | K36: 1 | L36: 0 | M36: 0 | N36: 0 | O36: 136 | R36: df | S36: SS | T36: MS | U36: F | V36: Significance F | AA36: 1 | AB36: 0 | AC36: 0 | AD36: 55153 | AE36: 41275
A37: Sijoitusrahasto Taaleri Yrityskorko | B37: 1 | C37: 1 | D37: 1 | E37: 0 | F37: 0 | G37: 0 | H37: 0 | I37: 0 | J37: 1 | K37: 0 | L37: 0 | M37: 0 | N37: 0 | O37: 102 | Q37: Regression | R37: 6 | S37: 172126.64 | T37: 28687.773 | U37: 27.197162 | V37: 2.55351e-30 | AA37: 0 | AB37: 1 | AC37: 0 | AD37: 44439 | AE37: 41306
A38: Sijoitusrahasto Evli Ruotsi Select | B38: 1 | C38: 1 | D38: 1 | E38: 0 | F38: 0 | G38: 0 | H38: 1 | I38: 0 | J38: 0 | K38: 0 | L38: 0 | M38: 0 | N38: 0 | O38: 68 | Q38: Residual | R38: 1083 | S38: 1142356.6 | T38: 1054.8076 | AA38: 0 | AB38: 1 | AC38: 0 | AD38: 43496 | AE38: 41395
A39: Sijoitusrahasto Evli Ruotsi Osakeindeksi | B39: 1 | C39: 1 | D39: 1 | E39: 1 | F39: 0 | G39: 0 | H39: 1 | I39: 0 | J39: 0 | K39: 0 | L39: 0 | M39: 0 | N39: 0 | O39: 132 | Q39: Total | R39: 1089 | S39: 1314483.2 | AA39: 1 | AB39: 0 | AC39: 0 | AD39: 55153 | AE39: 41395
A40: Real Estate Fund of Funds II Ky | B40: 0 | C40: 0 | D40: 0 | E40: 0 | F40: 1 | G40: 0 | H40: 0 | I40: 0 | J40: 0 | K40: 1 | L40: 0 | M40: 0 | N40: 0 | O40: 113 | AA40: 1 | AB40: 0 | AC40: 0 | AD40: 55153 | AE40: 41974
A41: Sijoitusrahasto FOURTON Fiesta | B41: 1 | C41: 1 | D41: 1 | E41: 1 | F41: 0 | G41: 0 | H41: 1 | I41: 0 | J41: 0 | K41: 0 | L41: 0 | M41: 0 | N41: 0 | O41: 134 | R41: Coefficients | S41: Standard Error | T41: t Stat | U41: P-value | V41: Lower 95% | W41: Upper 95% | X41: Lower 95,0% | Y41: Upper 95,0% | AA41: 1 | AB41: 0 | AC41: 0 | AD41: 55153 | AE41: 41334
A42: Säästöpankki High Yield -sijoitusrahasto | B42: 1 | C42: 1 | D42: 1 | E42: 1 | F42: 0 | G42: 0 | H42: 0 | I42: 0 | J42: 1 | K42: 0 | L42: 0 | M42: 0 | N42: 0 | O42: 134 | Q42: Intercept | R42: 42.891461 | S42: 2.0169631 | T42: 21.265367 | U42: 3.8863414e-84 | V42: 38.933863 | W42: 46.849059 | X42: 38.933863 | Y42: 46.849059 | AA42: 1 | AB42: 0 | AC42: 0 | AD42: 55153 | AE42: 41334
A43: AC Cleantech Growth Fund I Ky | B43: 0 | C43: 0 | D43: 0 | E43: 0 | F43: 0 | G43: 0 | H43: 0 | I43: 0 | J43: 0 | K43: 0 | L43: 0 | M43: 1 | N43: 0 | O43: 101 | Q43: Kysely (PEF = 0, IVF = 1) | R43: -28.187343 | S43: 4.8650355 | T43: -5.7938618 | U43: 9.0102777e-09 | V43: -37.733306 | W43: -18.64138 | X43: -37.733306 | Y43: -18.64138 | AA43: 0 | AB43: 0 | AC43: 1 | AD43: 45107 | AE43: 41974
A44: ICECAPITAL Housing Fund II Ky | B44: 0 | C44: 0 | D44: 0 | E44: 0 | F44: 0 | G44: 0 | H44: 0 | I44: 0 | J44: 0 | K44: 1 | L44: 0 | M44: 0 | N44: 0 | O44: 18 | Q44: UCITS-tyyppi (NON = 0, UCITS = 1) | R44: 8.9593013 | S44: 3.5924153 | T44: 2.4939492 | U44: 0.012781319 | V44: 1.910419 | W44: 16.008184 | X44: 1.910419 | Y44: 16.008184 | AA44: 0 | AB44: 0 | AC44: 1 | AD44: 42643 | AE44: 41974
A45: Sentica Buyout III Ky | B45: 0 | C45: 0 | D45: 0 | E45: 0 | F45: 0 | G45: 0 | H45: 0 | I45: 0 | J45: 0 | K45: 0 | L45: 0 | M45: 1 | N45: 0 | O45: 93 | Q45: Pääomanvaihtelevuus (Closed-end = 0, Open-end = 1) | R45: 35.217331 | S45: 5.7635299 | T45: 6.1103753 | U45: 1.3844433e-09 | V45: 23.908381 | W45: 46.52628 | X45: 23.908381 | Y45: 46.52628 | AA45: 0 | AB45: 0 | AC45: 1 | AD45: 44834 | AE45: 41974
A46: Sponsor Fund III Ky | B46: 0 | C46: 0 | D46: 0 | E46: 0 | F46: 0 | G46: 0 | H46: 0 | I46: 0 | J46: 0 | K46: 0 | L46: 0 | M46: 1 | N46: 0 | O46: 72 | Q46: AIF - retail | R46: 10.657941 | S46: 2.5011044 | T46: 4.2612939 | U46: 2.2093131e-05 | V46: 5.7503818 | W46: 15.5655 | X46: 5.7503818 | Y46: 15.5655 | AA46: 0 | AB46: 0 | AC46: 1 | AD46: 44196 | AE46: 41974
A47: Tapiola KR IV Ky | B47: 0 | C47: 0 | D47: 0 | E47: 0 | F47: 1 | G47: 0 | H47: 0 | I47: 0 | J47: 0 | K47: 1 | L47: 0 | M47: 0 | N47: 0 | O47: 113 | Q47: AIF - non-retail | R47: 31.909305 | S47: 2.7507899 | T47: 11.600051 | U47: 2.0782106e-29 | V47: 26.511823 | W47: 37.306786 | X47: 26.511823 | Y47: 37.306786 | AA47: 1 | AB47: 0 | AC47: 0 | AD47: 55153 | AE47: 41974
A48: Sijoitusrahasto Aktia A100 | B48: 1 | C48: 1 | D48: 1 | E48: 0 | F48: 0 | G48: 0 | H48: 1 | I48: 0 | J48: 0 | K48: 0 | L48: 0 | M48: 0 | N48: 0 | O48: 105 | Q48: Hedge-rahasto | R48: -18.266454 | S48: 7.8685716 | T48: -2.3214448 | U48: 0.020447709 | V48: -33.705826 | W48: -2.8270827 | X48: -33.705826 | Y48: -2.8270827 | AA48: 0 | AB48: 1 | AC48: 0 | AD48: 44592 | AE48: 41365
A49: Sijoitusrahasto Aktia A25 | B49: 1 | C49: 1 | D49: 1 | E49: 0 | F49: 0 | G49: 0 | H49: 0 | I49: 0 | J49: 1 | K49: 0 | L49: 0 | M49: 0 | N49: 0 | O49: 105 | AA49: 0 | AB49: 1 | AC49: 0 | AD49: 44592 | AE49: 41365
A50: Sijoitusrahasto Taaleri Kehittyvät Markkinat | B50: 1 | C50: 1 | D50: 1 | E50: 0 | F50: 0 | G50: 0 | H50: 1 | I50: 0 | J50: 0 | K50: 0 | L50: 0 | M50: 0 | N50: 0 | O50: 77 | Q50: SUMMARY OUTPUT Kiinteistö | AA50: 0 | AB50: 1 | AC50: 0 | AD50: 43738 | AE50: 41365
A51: Sijoitusrahasto FOURTON Tempo | B51: 1 | C51: 1 | D51: 1 | E51: 1 | F51: 0 | G51: 0 | H51: 1 | I51: 0 | J51: 0 | K51: 0 | L51: 0 | M51: 0 | N51: 0 | O51: 133 | AA51: 1 | AB51: 0 | AC51: 0 | AD51: 55153 | AE51: 41365
A52: OP-Vuokratuotto -erikoissijoitusrahasto | B52: 1 | C52: 0 | D52: 1 | E52: 1 | F52: 0 | G52: 0 | H52: 0 | I52: 0 | J52: 0 | K52: 1 | L52: 0 | M52: 0 | N52: 0 | O52: 131 | Q52: Regression Statistics | AA52: 1 | AB52: 0 | AC52: 0 | AD52: 55153 | AE52: 41426
A53: Erikoissijoitusrahasto Titanium Hoivakiinteistö | B53: 1 | C53: 0 | D53: 1 | E53: 1 | F53: 0 | G53: 0 | H53: 0 | I53: 0 | J53: 0 | K53: 1 | L53: 0 | M53: 0 | N53: 0 | O53: 131 | Q53: Multiple R | R53: 0.38378122 | AA53: 1 | AB53: 0 | AC53: 0 | AD53: 55153 | AE53: 41426
A54: S-Pankki Kasvavat Taloudet Osake Sijoitusrahasto | B54: 1 | C54: 1 | D54: 1 | E54: 1 | F54: 0 | G54: 0 | H54: 1 | I54: 0 | J54: 0 | K54: 0 | L54: 0 | M54: 0 | N54: 0 | O54: 128 | Q54: R Square | R54: 0.14728802 | AA54: 1 | AB54: 0 | AC54: 0 | AD54: 55153 | AE54: 41518
A55: OP-Amerikka Pienyhtiöt -sijoitusrahasto | B55: 1 | C55: 1 | D55: 1 | E55: 1 | F55: 0 | G55: 0 | H55: 1 | I55: 0 | J55: 0 | K55: 0 | L55: 0 | M55: 0 | N55: 0 | O55: 130 | Q55: Adjusted R Square | R55: 0.14256386 | AA55: 1 | AB55: 0 | AC55: 0 | AD55: 55153 | AE55: 41456
A56: Sijoitusrahasto Evli Kehittyvät Markkinat Yrityslaina | B56: 1 | C56: 1 | D56: 1 | E56: 1 | F56: 0 | G56: 0 | H56: 0 | I56: 0 | J56: 1 | K56: 0 | L56: 0 | M56: 0 | N56: 0 | O56: 127 | Q56: Standard Error | R56: 32.170994 | AA56: 1 | AB56: 0 | AC56: 0 | AD56: 55153 | AE56: 41548
A57: Sijoitusrahasto Evli Emerging Frontier | B57: 1 | C57: 1 | D57: 1 | E57: 1 | F57: 0 | G57: 0 | H57: 1 | I57: 0 | J57: 0 | K57: 0 | L57: 0 | M57: 0 | N57: 0 | O57: 127 | Q57: Observations | R57: 1090 | AA57: 1 | AB57: 0 | AC57: 0 | AD57: 55153 | AE57: 41548
A58: Finlandia Globaali Allokaatio Erikoissijoitusrahasto | B58: 1 | C58: 0 | D58: 1 | E58: 0 | F58: 0 | G58: 0 | H58: 1 | I58: 0 | J58: 0 | K58: 0 | L58: 0 | M58: 0 | N58: 0 | O58: 34 | AA58: 0 | AB58: 1 | AC58: 0 | AD58: 42551 | AE58: 41487
A59: Sijoitusrahasto Nordea Stable Equities UCITS ETF | B59: 1 | C59: 1 | D59: 1 | E59: 0 | F59: 0 | G59: 0 | H59: 1 | I59: 0 | J59: 0 | K59: 0 | L59: 0 | M59: 0 | N59: 0 | O59: 37 | Q59: ANOVA | AA59: 0 | AB59: 0 | AC59: 1 | AD59: 42674 | AE59: 41518
A60: Sijoitusrahasto Nordea Global Emerging Markets Equities UCITS ETF | B60: 1 | C60: 1 | D60: 1 | E60: 0 | F60: 0 | G60: 0 | H60: 1 | I60: 0 | J60: 0 | K60: 0 | L60: 0 | M60: 0 | N60: 0 | O60: 37 | R60: df | S60: SS | T60: MS | U60: F | V60: Significance F | AA60: 0 | AB60: 0 | AC60: 1 | AD60: 42674 | AE60: 41518
A61: Sijoitusrahasto Nordea Euroopan Pienet Yhtiöt | B61: 1 | C61: 1 | D61: 1 | E61: 1 | F61: 0 | G61: 0 | H61: 1 | I61: 0 | J61: 0 | K61: 0 | L61: 0 | M61: 0 | N61: 0 | O61: 127 | Q61: Regression | R61: 6 | S61: 193607.64 | T61: 32267.94 | U61: 31.177571 | V61: 1.105737e-34 | AA61: 1 | AB61: 0 | AC61: 0 | AD61: 55153 | AE61: 41548
A62: Sijoitusrahasto LähiTapiola Pohjoinen Yrityskorko ESG | B62: 1 | C62: 1 | D62: 1 | E62: 1 | F62: 0 | G62: 0 | H62: 0 | I62: 0 | J62: 1 | K62: 0 | L62: 0 | M62: 0 | N62: 0 | O62: 127 | Q62: Residual | R62: 1083 | S62: 1120875.6 | T62: 1034.9728 | AA62: 1 | AB62: 0 | AC62: 0 | AD62: 55153 | AE62: 41548
A63: Sijoitusrahasto eQ LCR Korko | B63: 1 | C63: 1 | D63: 1 | E63: 0 | F63: 0 | G63: 0 | H63: 0 | I63: 0 | J63: 1 | K63: 0 | L63: 0 | M63: 0 | N63: 0 | O63: 49 | Q63: Total | R63: 1089 | S63: 1314483.2 | AA63: 0 | AB63: 0 | AC63: 1 | AD63: 43069 | AE63: 41548
A64: Front Suomi Sijoitusrahasto | B64: 1 | C64: 1 | D64: 1 | E64: 0 | F64: 0 | G64: 0 | H64: 1 | I64: 0 | J64: 0 | K64: 0 | L64: 0 | M64: 0 | N64: 0 | O64: 40 | AA64: 0 | AB64: 0 | AC64: 1 | AD64: 42794 | AE64: 41548
A65: Sijoitusrahasto Nordea Obligasjon Stars | B65: 1 | C65: 1 | D65: 1 | E65: 0 | F65: 0 | G65: 0 | H65: 0 | I65: 0 | J65: 1 | K65: 0 | L65: 0 | M65: 0 | N65: 0 | O65: 126 | R65: Coefficients | S65: Standard Error | T65: t Stat | U65: P-value | V65: Lower 95% | W65: Upper 95% | X65: Lower 95,0% | Y65: Upper 95,0% | AA65: 1 | AB65: 0 | AC65: 0 | AD65: 55153 | AE65: 41579
A66: Erikoissijoitusrahasto Aktia Mikro Markka | B66: 1 | C66: 0 | D66: 1 | E66: 1 | F66: 0 | G66: 0 | H66: 1 | I66: 0 | J66: 0 | K66: 0 | L66: 0 | M66: 0 | N66: 0 | O66: 125 | Q66: Intercept | R66: 38.012132 | S66: 2.1749308 | T66: 17.477398 | U66: 1.912006e-60 | V66: 33.744577 | W66: 42.279688 | X66: 33.744577 | Y66: 42.279688 | AA66: 1 | AB66: 0 | AC66: 0 | AD66: 55153 | AE66: 41609
A67: Specialplaceringsfonden Aktia Global High Yield Bond+ | B67: 1 | C67: 0 | D67: 1 | E67: 0 | F67: 0 | G67: 0 | H67: 0 | I67: 0 | J67: 1 | K67: 0 | L67: 0 | M67: 0 | N67: 0 | O67: 77 | Q67: Kysely (PEF = 0, IVF = 1) | R67: -26.264534 | S67: 4.8361761 | T67: -5.4308474 | U67: 6.9227244e-08 | V67: -35.753871 | W67: -16.775198 | X67: -35.753871 | Y67: -16.775198 | AA67: 0 | AB67: 1 | AC67: 0 | AD67: 43982 | AE67: 41609
A68: S-Pankki Toimitila Erikoissijoitusrahasto | B68: 1 | C68: 0 | D68: 1 | E68: 1 | F68: 0 | G68: 0 | H68: 0 | I68: 0 | J68: 0 | K68: 1 | L68: 0 | M68: 0 | N68: 0 | O68: 125 | Q68: UCITS-tyyppi (NON = 0, UCITS = 1) | R68: 13.310159 | S68: 3.5032489 | T68: 3.7993758 | U68: 0.00015313301 | V68: 6.4362352 | W68: 20.184083 | X68: 6.4362352 | Y68: 20.184083 | AA68: 1 | AB68: 0 | AC68: 0 | AD68: 55153 | AE68: 41609
A69: OP-Vaurastuva Keskiluokka -sijoitusrahasto | B69: 1 | C69: 1 | D69: 1 | E69: 1 | F69: 0 | G69: 0 | H69: 1 | I69: 0 | J69: 0 | K69: 0 | L69: 0 | M69: 0 | N69: 0 | O69: 123 | Q69: Pääomanvaihtelevuus (Closed-end = 0, Open-end = 1) | R69: 33.093595 | S69: 5.6546222 | T69: 5.8524856 | U69: 6.4116211e-09 | V69: 21.99834 | W69: 44.188851 | X69: 21.99834 | Y69: 44.188851 | AA69: 1 | AB69: 0 | AC69: 0 | AD69: 55153 | AE69: 41671
A70: Sijoitusrahasto UB LCR Korko | B70: 1 | C70: 1 | D70: 1 | E70: 0 | F70: 0 | G70: 0 | H70: 0 | I70: 0 | J70: 1 | K70: 0 | L70: 0 | M70: 0 | N70: 0 | O70: 43 | Q70: AIF - retail | R70: 11.505247 | S70: 2.4528223 | T70: 4.6906159 | U70: 3.0715575e-06 | V70: 6.6924253 | W70: 16.31807 | X70: 6.6924253 | Y70: 16.31807 | AA70: 0 | AB70: 0 | AC70: 1 | AD70: 43069 | AE70: 41730
A71: Finlandia Fokus Erikoissijoitusrahasto | B71: 1 | C71: 0 | D71: 1 | E71: 0 | F71: 0 | G71: 0 | H71: 0 | I71: 1 | J71: 0 | K71: 0 | L71: 0 | M71: 0 | N71: 0 | O71: 60 | Q71: AIF - non-retail | R71: 33.187531 | S71: 2.7315073 | T71: 12.149896 | U71: 6.1845697e-32 | V71: 27.827885 | W71: 38.547177 | X71: 27.827885 | Y71: 38.547177 | AA71: 0 | AB71: 0 | AC71: 1 | AD71: 43496 | AE71: 41640
A72: Finlandia Korkotuotto Sijoitusrahasto | B72: 1 | C72: 1 | D72: 1 | E72: 1 | F72: 0 | G72: 0 | H72: 0 | I72: 0 | J72: 1 | K72: 0 | L72: 0 | M72: 0 | N72: 0 | O72: 124 | Q72: Kiinteistörahasto | R72: 12.320338 | S72: 2.4047973 | T72: 5.1232336 | U72: 3.5539204e-07 | V72: 7.6017487 | W72: 17.038928 | X72: 7.6017487 | Y72: 17.038928 | AA72: 1 | AB72: 0 | AC72: 0 | AD72: 55153 | AE72: 41640
A73: OP-Pohjoismaat Plus -erikoissijoitusrahasto | B73: 1 | C73: 0 | D73: 1 | E73: 0 | F73: 0 | G73: 0 | H73: 1 | I73: 0 | J73: 0 | K73: 0 | L73: 0 | M73: 0 | N73: 0 | O73: 57 | AA73: 0 | AB73: 1 | AC73: 0 | AD73: 43404 | AE73: 41640
A74: Nordic Option Oy | B74: 0 | C74: 0 | D74: 0 | E74: 0 | F74: 0 | G74: 0 | H74: 0 | I74: 0 | J74: 0 | K74: 0 | L74: 0 | M74: 1 | N74: 0 | O74: 18 | Q74: SUMMARY OUTPUT Korko | AA74: 0 | AB74: 0 | AC74: 1 | AD74: 42643 | AE74: 41974
A75: Midinvest Oy | B75: 0 | C75: 0 | D75: 0 | E75: 0 | F75: 1 | G75: 1 | H75: 0 | I75: 0 | J75: 0 | K75: 0 | L75: 0 | M75: 0 | N75: 0 | O75: 113 | AA75: 1 | AB75: 0 | AC75: 0 | AD75: 55153 | AE75: 41974
A76: Matkailurahasto Nordia Oy | B76: 0 | C76: 0 | D76: 0 | E76: 0 | F76: 1 | G76: 0 | H76: 0 | I76: 0 | J76: 0 | K76: 0 | L76: 0 | M76: 1 | N76: 0 | O76: 113 | Q76: Regression Statistics | AA76: 1 | AB76: 0 | AC76: 0 | AD76: 55153 | AE76: 41974
A77: Pikespo Invest Oy Ltd | B77: 0 | C77: 0 | D77: 0 | E77: 0 | F77: 0 | G77: 0 | H77: 0 | I77: 0 | J77: 0 | K77: 0 | L77: 0 | M77: 1 | N77: 0 | O77: 17 | Q77: Multiple R | R77: 0.36004166 | AA77: 0 | AB77: 0 | AC77: 1 | AD77: 42825 | AE77: 41974
A78: Armada Mezzanine Fund II NIB Ky | B78: 0 | C78: 0 | D78: 0 | E78: 0 | F78: 0 | G78: 0 | H78: 0 | I78: 1 | J78: 0 | K78: 0 | L78: 0 | M78: 0 | N78: 0 | O78: 72 | Q78: R Square | R78: 0.12963 | AA78: 0 | AB78: 0 | AC78: 1 | AD78: 44196 | AE78: 41974
A79: CapMan Private Rahasto III Ky | B79: 0 | C79: 0 | D79: 0 | E79: 0 | F79: 1 | G79: 0 | H79: 0 | I79: 0 | J79: 0 | K79: 0 | L79: 0 | M79: 1 | N79: 0 | O79: 113 | Q79: Adjusted R Square | R79: 0.124808 | AA79: 1 | AB79: 0 | AC79: 0 | AD79: 55153 | AE79: 41974
A80: Wedeco Fund III Ky | B80: 0 | C80: 0 | D80: 0 | E80: 0 | F80: 0 | G80: 0 | H80: 0 | I80: 0 | J80: 0 | K80: 0 | L80: 0 | M80: 1 | N80: 0 | O80: 24 | Q80: Standard Error | R80: 32.502387 | AA80: 0 | AB80: 0 | AC80: 1 | AD80: 42735 | AE80: 41974
A81: Mandatum Pääomarahasto II Ky | B81: 0 | C81: 0 | D81: 0 | E81: 0 | F81: 0 | G81: 1 | H81: 0 | I81: 0 | J81: 0 | K81: 0 | L81: 0 | M81: 0 | N81: 0 | O81: 56 | Q81: Observations | R81: 1090 | AA81: 0 | AB81: 0 | AC81: 1 | AD81: 43738 | AE81: 41974
A82: Holtron Capital Fund II Ky | B82: 0 | C82: 0 | D82: 0 | E82: 0 | F82: 0 | G82: 1 | H82: 0 | I82: 0 | J82: 0 | K82: 0 | L82: 0 | M82: 0 | N82: 0 | O82: 72 | AA82: 0 | AB82: 0 | AC82: 1 | AD82: 44196 | AE82: 41974
A83: Promotion Equity I Ky | B83: 0 | C83: 0 | D83: 0 | E83: 0 | F83: 0 | G83: 0 | H83: 0 | I83: 0 | J83: 0 | K83: 0 | L83: 0 | M83: 1 | N83: 0 | O83: 12 | Q83: ANOVA | AA83: 0 | AB83: 0 | AC83: 1 | AD83: 42369 | AE83: 41974
A84: Promotion Equity I C Ky | B84: 0 | C84: 0 | D84: 0 | E84: 0 | F84: 0 | G84: 0 | H84: 0 | I84: 0 | J84: 0 | K84: 0 | L84: 0 | M84: 1 | N84: 0 | O84: 12 | R84: df | S84: SS | T84: MS | U84: F | V84: Significance F | AA84: 0 | AB84: 0 | AC84: 1 | AD84: 42369 | AE84: 41974
A85: Promotion Equity I D Ky | B85: 0 | C85: 0 | D85: 0 | E85: 0 | F85: 0 | G85: 0 | H85: 0 | I85: 0 | J85: 0 | K85: 0 | L85: 0 | M85: 1 | N85: 0 | O85: 12 | Q85: Regression | R85: 6 | S85: 170396.46 | T85: 28399.41 | U85: 26.883066 | V85: 5.6806619e-30 | AA85: 0 | AB85: 0 | AC85: 1 | AD85: 42369 | AE85: 41974
A86: Promotion Equity I E Ky | B86: 0 | C86: 0 | D86: 0 | E86: 0 | F86: 0 | G86: 0 | H86: 0 | I86: 0 | J86: 0 | K86: 0 | L86: 0 | M86: 1 | N86: 0 | O86: 12 | Q86: Residual | R86: 1083 | S86: 1144086.8 | T86: 1056.4051 | AA86: 0 | AB86: 0 | AC86: 1 | AD86: 42369 | AE86: 41974
A87: Power Fund I Ky | B87: 0 | C87: 0 | D87: 0 | E87: 0 | F87: 0 | G87: 1 | H87: 0 | I87: 0 | J87: 0 | K87: 0 | L87: 0 | M87: 0 | N87: 0 | O87: 51 | Q87: Total | R87: 1089 | S87: 1314483.2 | AA87: 0 | AB87: 0 | AC87: 1 | AD87: 43555 | AE87: 41974
A88: Teknoventure Rahasto II Ky | B88: 0 | C88: 0 | D88: 0 | E88: 0 | F88: 0 | G88: 0 | H88: 0 | I88: 0 | J88: 0 | K88: 0 | L88: 0 | M88: 1 | N88: 0 | O88: 24 | AA88: 0 | AB88: 0 | AC88: 1 | AD88: 42735 | AE88: 41974
A89: Ylä-Savon Pääomarahasto Oy | B89: 0 | C89: 0 | D89: 0 | E89: 0 | F89: 1 | G89: 0 | H89: 0 | I89: 0 | J89: 0 | K89: 0 | L89: 0 | M89: 1 | N89: 0 | O89: 113 | R89: Coefficients | S89: Standard Error | T89: t Stat | U89: P-value | V89: Lower 95% | W89: Upper 95% | X89: Lower 95,0% | Y89: Upper 95,0% | AA89: 1 | AB89: 0 | AC89: 0 | AD89: 55153 | AE89: 41974
A90: CapMan Private Rahasto II Ky | B90: 0 | C90: 0 | D90: 0 | E90: 0 | F90: 1 | G90: 0 | H90: 0 | I90: 0 | J90: 0 | K90: 0 | L90: 0 | M90: 1 | N90: 0 | O90: 113 | Q90: Intercept | R90: 42.429564 | S90: 2.0116809 | T90: 21.091598 | U90: 5.2752247e-83 | V90: 38.482331 | W90: 46.376798 | X90: 38.482331 | Y90: 46.376798 | AA90: 1 | AB90: 0 | AC90: 0 | AD90: 55153 | AE90: 41974
A91: Aboa Venture III Ky | B91: 0 | C91: 0 | D91: 0 | E91: 0 | F91: 0 | G91: 0 | H91: 0 | I91: 0 | J91: 0 | K91: 0 | L91: 0 | M91: 1 | N91: 0 | O91: 93 | Q91: Kysely (PEF = 0, IVF = 1) | R91: -28.569582 | S91: 4.8687274 | T91: -5.8679773 | U91: 5.8573106e-09 | V91: -38.122789 | W91: -19.016375 | X91: -38.122789 | Y91: -19.016375 | AA91: 0 | AB91: 0 | AC91: 1 | AD91: 44834 | AE91: 41974
A92: Jokilaaksojen Rahasto I Ky | B92: 0 | C92: 0 | D92: 0 | E92: 0 | F92: 0 | G92: 0 | H92: 0 | I92: 0 | J92: 0 | K92: 0 | L92: 0 | M92: 1 | N92: 0 | O92: 24 | Q92: UCITS-tyyppi (NON = 0, UCITS = 1) | R92: 9.3288708 | S92: 3.5881875 | T92: 2.5998839 | U92: 0.0094524338 | V92: 2.2882842 | W92: 16.369458 | X92: 2.2882842 | Y92: 16.369458 | AA92: 0 | AB92: 0 | AC92: 1 | AD92: 42735 | AE92: 41974
A93: CapMan Private Rahasto I Ky | B93: 0 | C93: 0 | D93: 0 | E93: 0 | F93: 0 | G93: 0 | H93: 0 | I93: 0 | J93: 0 | K93: 0 | L93: 0 | M93: 1 | N93: 0 | O93: 24 | Q93: Pääomanvaihtelevuus (Closed-end = 0, Open-end = 1) | R93: 32.607167 | S93: 5.7261789 | T93: 5.6944025 | U93: 1.5937373e-08 | V93: 21.371506 | W93: 43.842828 | X93: 21.371506 | Y93: 43.842828 | AA93: 0 | AB93: 0 | AC93: 1 | AD93: 42735 | AE93: 41974
A94: Aboa Venture II Ky | B94: 0 | C94: 0 | D94: 0 | E94: 0 | F94: 0 | G94: 0 | H94: 0 | I94: 0 | J94: 0 | K94: 0 | L94: 0 | M94: 1 | N94: 0 | O94: 48 | Q94: AIF - retail | R94: 11.622108 | S94: 2.4792456 | T94: 4.68776 | U94: 3.1138548e-06 | V94: 6.7574397 | W94: 16.486777 | X94: 6.7574397 | Y94: 16.486777 | AA94: 0 | AB94: 0 | AC94: 1 | AD94: 43465 | AE94: 41974
A95: Power Fund II Ky | B95: 0 | C95: 0 | D95: 0 | E95: 0 | F95: 1 | G95: 1 | H95: 0 | I95: 0 | J95: 0 | K95: 0 | L95: 0 | M95: 0 | N95: 0 | O95: 113 | Q95: AIF - non-retail | R95: 32.180757 | S95: 2.7517125 | T95: 11.694811 | U95: 7.7379921e-30 | V95: 26.781465 | W95: 37.580048 | X95: 26.781465 | Y95: 37.580048 | AA95: 1 | AB95: 0 | AC95: 0 | AD95: 55153 | AE95: 41974
A96: Länsi-Suomen Pääomarahasto Oy | B96: 0 | C96: 0 | D96: 0 | E96: 0 | F96: 1 | G96: 0 | H96: 0 | I96: 0 | J96: 0 | K96: 0 | L96: 0 | M96: 1 | N96: 0 | O96: 113 | Q96: Korkorahasto | R96: 8.1397883 | S96: 4.207208 | T96: 1.9347245 | U96: 0.053284279 | V96: -0.1154136 | W96: 16.39499 | X96: -0.1154136 | Y96: 16.39499 | AA96: 1 | AB96: 0 | AC96: 0 | AD96: 55153 | AE96: 41974
A97: MB Equity Fund IV Ky | B97: 0 | C97: 0 | D97: 0 | E97: 0 | F97: 1 | G97: 0 | H97: 0 | I97: 0 | J97: 0 | K97: 0 | L97: 0 | M97: 1 | N97: 0 | O97: 113 | AA97: 1 | AB97: 0 | AC97: 0 | AD97: 55153 | AE97: 41974
A98: Sentica Terveysteknologia I Ky | B98: 0 | C98: 0 | D98: 0 | E98: 0 | F98: 0 | G98: 0 | H98: 0 | I98: 0 | J98: 0 | K98: 0 | L98: 0 | M98: 1 | N98: 0 | O98: 24 | Q98: SUMMARY OUTPUT Muu | AA98: 0 | AB98: 0 | AC98: 1 | AD98: 42735 | AE98: 41974
A99: Amanda IV West Ky | B99: 0 | C99: 0 | D99: 0 | E99: 0 | F99: 0 | G99: 0 | H99: 0 | I99: 0 | J99: 0 | K99: 0 | L99: 0 | M99: 1 | N99: 0 | O99: 113 | AA99: 1 | AB99: 0 | AC99: 0 | AD99: 55153 | AE99: 41974
A100: Teknoventure Rahasto III Ky | B100: 0 | C100: 0 | D100: 0 | E100: 0 | F100: 0 | G100: 0 | H100: 0 | I100: 0 | J100: 0 | K100: 0 | L100: 0 | M100: 1 | N100: 0 | O100: 40 | Q100: Regression Statistics | AA100: 0 | AB100: 0 | AC100: 1 | AD100: 43281 | AE100: 41974
...

Sheet Statistisk analys på stängde
A1: Raportoija | B1: UCITS-tyyppi (NON = 0, UCITS = 1) | C1: Kysely (PEF = 0, IVF = 1) | D1: Pääomanvaihtelevuus (Closed-end = 0, Open-end = 1) | E1: AIF - retail | F1: AIF - non-retail | G1: Yhdistelmärahasto | H1: Venture Capital -rahasto | I1: Osakerahasto | J1: Muu rahasto | K1: Korkorahasto | L1: Kiinteistörahasto | M1: Hedge-rahasto | N1: Buyout-rahasto | O1: Elinaika (kk) | AD1: Jatkaa | AE1: Sulautunut | AF1: Lakkautettu | AG1: RaportoinninLopetusPvm | AH1: RaportoinninAloitusPvm
A2: Oy Wedeco Ab | B2: 0 | C2: 0 | D2: 0 | E2: =IF($O2="Retail",1,0) -> 0 | F2: =IF($O2="Non-Retail",1,0) -> 0 | G2: 0 | H2: 0 | I2: 0 | J2: 0 | K2: 0 | L2: 0 | M2: 0 | N2: 1 | O2: 34 | Q2: SUMMARY OUTPUT Buyout | AD2: 0 | AE2: 0 | AF2: 1 | AG2: 43100 | AH2: 41974
A3: Finnventure Rahasto V Ky | B3: 0 | C3: 0 | D3: 0 | E3: =IF($O3="Retail",1,0) -> 0 | F3: =IF($O3="Non-Retail",1,0) -> 0 | G3: 0 | H3: 0 | I3: 0 | J3: 0 | K3: 0 | L3: 0 | M3: 0 | N3: 1 | O3: 24 | AD3: 0 | AE3: 0 | AF3: 1 | AG3: 42735 | AH3: 41974
A4: Maneq Fund 2002 Ky | B4: 0 | C4: 0 | D4: 0 | E4: =IF($O4="Retail",1,0) -> 0 | F4: =IF($O4="Non-Retail",1,0) -> 0 | G4: 0 | H4: 0 | I4: 0 | J4: 0 | K4: 0 | L4: 0 | M4: 0 | N4: 1 | O4: 12 | Q4: Regression Statistics | AD4: 0 | AE4: 0 | AF4: 1 | AG4: 42369 | AH4: 41974
A5: Finnmezzanine Rahasto III A Ky | B5: 0 | C5: 0 | D5: 0 | E5: =IF($O5="Retail",1,0) -> 0 | F5: =IF($O5="Non-Retail",1,0) -> 0 | G5: 0 | H5: 0 | I5: 0 | J5: 0 | K5: 0 | L5: 0 | M5: 0 | N5: 1 | O5: 55 | Q5: Multiple R | R5: 0.19688555 | AD5: 0 | AE5: 0 | AF5: 1 | AG5: 43738 | AH5: 41974
A6: Finnmezzanine Rahasto III C Ky | B6: 0 | C6: 0 | D6: 0 | E6: =IF($O6="Retail",1,0) -> 0 | F6: =IF($O6="Non-Retail",1,0) -> 0 | G6: 0 | H6: 0 | I6: 0 | J6: 0 | K6: 0 | L6: 0 | M6: 0 | N6: 1 | O6: 11 | Q6: R Square | R6: 0.038763918 | AD6: 0 | AE6: 0 | AF6: 1 | AG6: 42369 | AH6: 41974
A7: CapMan Real Estate I Ky | B7: 0 | C7: 0 | D7: 0 | E7: =IF($O7="Retail",1,0) -> 0 | F7: =IF($O7="Non-Retail",1,0) -> 0 | G7: 0 | H7: 0 | I7: 0 | J7: 0 | K7: 0 | L7: 1 | M7: 0 | N7: 0 | O7: 72 | Q7: Adjusted R Square | R7: 0.020541433 | AD7: 0 | AE7: 0 | AF7: 1 | AG7: 44196 | AH7: 41974
A8: OP-Euro -sijoitusrahasto | B8: 1 | C8: 1 | D8: 1 | E8: =IF($O8="Retail",1,0) -> 0 | F8: =IF($O8="Non-Retail",1,0) -> 0 | G8: 0 | H8: 0 | I8: 0 | J8: 0 | K8: 1 | L8: 0 | M8: 0 | N8: 0 | O8: 120 | Q8: Standard Error | R8: 28.651064 | AD8: 0 | AE8: 0 | AF8: 1 | AG8: 55153 | AH8: 43466
A9: S-Pankki Lyhyt Korko Sijoitusrahasto | B9: 1 | C9: 1 | D9: 1 | E9: =IF($O9="Retail",1,0) -> 0 | F9: =IF($O9="Non-Retail",1,0) -> 0 | G9: 0 | H9: 0 | I9: 0 | J9: 0 | K9: 1 | L9: 0 | M9: 0 | N9: 0 | O9: 76 | Q9: Observations | R9: 216 | AD9: 0 | AE9: 0 | AF9: 1 | AG9: 55153 | AH9: 43466
A10: Veraventure Oy | B10: 0 | C10: 0 | D10: 0 | E10: =IF($O10="Retail",1,0) -> 0 | F10: =IF($O10="Non-Retail",1,0) -> 0 | G10: 0 | H10: 1 | I10: 0 | J10: 0 | K10: 0 | L10: 0 | M10: 0 | N10: 0 | O10: 81 | AD10: 0 | AE10: 0 | AF10: 1 | AG10: 44469 | AH10: 41974
A11: Aloitusrahasto Vera Oy | B11: 0 | C11: 0 | D11: 0 | E11: =IF($O11="Retail",1,0) -> 0 | F11: =IF($O11="Non-Retail",1,0) -> 0 | G11: 0 | H11: 1 | I11: 0 | J11: 0 | K11: 0 | L11: 0 | M11: 0 | N11: 0 | O11: 34 | Q11: ANOVA | AD11: 0 | AE11: 0 | AF11: 1 | AG11: 43100 | AH11: 41974
A12: Sijoitusrahasto Danske Invest Suomi Osinko Plus | B12: 1 | C12: 1 | D12: 1 | E12: =IF($O12="Retail",1,0) -> 0 | F12: =IF($O12="Non-Retail",1,0) -> 0 | G12: 0 | H12: 0 | I12: 1 | J12: 0 | K12: 0 | L12: 0 | M12: 0 | N12: 0 | O12: 100 | R12: df | S12: SS | T12: MS | U12: F | V12: Significance F | AD12: 0 | AE12: 1 | AF12: 0 | AG12: 44165 | AH12: 42856
A13: Sijoitusrahasto Nordea Korko Varovainen | B13: 1 | C13: 1 | D13: 1 | E13: =IF($O13="Retail",1,0) -> 0 | F13: =IF($O13="Non-Retail",1,0) -> 0 | G13: 0 | H13: 0 | I13: 0 | J13: 0 | K13: 1 | L13: 0 | M13: 0 | N13: 0 | O13: 118 | Q13: Regression | R13: 4 | S13: 6984.9221 | T13: 1746.2305 | U13: 2.1272575 | V13: 0.078569665 | AD13: 0 | AE13: 0 | AF13: 1 | AG13: 55153 | AH13: 43466
A14: Sijoitusrahasto Nordea Korko | B14: 1 | C14: 1 | D14: 1 | E14: =IF($O14="Retail",1,0) -> 0 | F14: =IF($O14="Non-Retail",1,0) -> 0 | G14: 0 | H14: 0 | I14: 0 | J14: 0 | K14: 1 | L14: 0 | M14: 0 | N14: 0 | O14: 115 | Q14: Residual | R14: 211 | S14: 173206.41 | T14: 820.88347 | AD14: 0 | AE14: 0 | AF14: 1 | AG14: 55153 | AH14: 43466
A15: ANL Kiinteistöt I Ky | B15: 0 | C15: 0 | D15: 0 | E15: =IF($O15="Retail",1,0) -> 0 | F15: =IF($O15="Non-Retail",1,0) -> 0 | G15: 0 | H15: 0 | I15: 0 | J15: 0 | K15: 0 | L15: 1 | M15: 0 | N15: 0 | O15: 18 | Q15: Total | R15: 215 | S15: 180191.33 | AD15: 0 | AE15: 0 | AF15: 1 | AG15: 42643 | AH15: 41974
